Workbook

Sheet Statistics
B2: AUTOBONO — Statistics
B3: Counted automatically from the Sales date column on the 2024 tab, from January 2024 (Brutto profit, Sale price, Sale time, Cash stuck). Nothing to type here — new cars, months and years appear by themselves.
B5: Quick view
B6: Period | C6: Cars bought | D6: Cars sold | E6: Profit | F6: Avg profit / car | G6: Half profit (each of you) | H6: Sales total | I6: Avg days online | J6: Avg days bought → sold
B7: This month | C7: =IF(FALSE,"",COUNTIFS('2024'!$AD$5:$AD$178,">="&DATE(YEAR(TODAY()),MONTH(TODAY()),1),'2024'!$AD$5:$AD$178,"<"&DATE(YEAR(TODAY()),MONTH(TODAY())+1,1))) | D7: =IF(FALSE,"",COUNTIFS('2024'!$AG$5:$AG$178,">="&DATE(YEAR(TODAY()),MONTH(TODAY()),1),'2024'!$AG$5:$AG$178,"<"&DATE(YEAR(TODAY()),MONTH(TODAY())+1,1))) | E7: =IF(FALSE,"",SUMIFS('2024'!$X$5:$X$178,'2024'!$AG$5:$AG$178,">="&DATE(YEAR(TODAY()),MONTH(TODAY()),1),'2024'!$AG$5:$AG$178,"<"&DATE(YEAR(TODAY()),MONTH(TODAY())+1,1))) | F7: =IF(N(D7)=0,"",E7/D7) | G7: =IF(E7="","",E7/2) | H7: =IF(FALSE,"",SUMIFS('2024'!$V$5:$V$178,'2024'!$AG$5:$AG$178,">="&DATE(YEAR(TODAY()),MONTH(TODAY()),1),'2024'!$AG$5:$AG$178,"<"&DATE(YEAR(TODAY()),MONTH(TODAY())+1,1))) | I7: =IF(N(D7)=0,"",(SUMIFS('2024'!$AH$5:$AH$178,'2024'!$AG$5:$AG$178,">="&DATE(YEAR(TODAY()),MONTH(TODAY()),1),'2024'!$AG$5:$AG$178,"<"&DATE(YEAR(TODAY()),MONTH(TODAY())+1,1)))/D7) | J7: =IF(N(D7)=0,"",(SUMIFS('2024'!$AI$5:$AI$178,'2024'!$AG$5:$AG$178,">="&DATE(YEAR(TODAY()),MONTH(TODAY()),1),'2024'!$AG$5:$AG$178,"<"&DATE(YEAR(TODAY()),MONTH(TODAY())+1,1)))/D7)
B8: Last month | C8: =IF(FALSE,"",COUNTIFS('2024'!$AD$5:$AD$178,">="&DATE(YEAR(TODAY()),MONTH(TODAY())-1,1),'2024'!$AD$5:$AD$178,"<"&DATE(YEAR(TODAY()),MONTH(TODAY()),1))) | D8: =IF(FALSE,"",COUNTIFS('2024'!$AG$5:$AG$178,">="&DATE(YEAR(TODAY()),MONTH(TODAY())-1,1),'2024'!$AG$5:$AG$178,"<"&DATE(YEAR(TODAY()),MONTH(TODAY()),1))) | E8: =IF(FALSE,"",SUMIFS('2024'!$X$5:$X$178,'2024'!$AG$5:$AG$178,">="&DATE(YEAR(TODAY()),MONTH(TODAY())-1,1),'2024'!$AG$5:$AG$178,"<"&DATE(YEAR(TODAY()),MONTH(TODAY()),1))) | F8: =IF(N(D8)=0,"",E8/D8) | G8: =IF(E8="","",E8/2) | H8: =IF(FALSE,"",SUMIFS('2024'!$V$5:$V$178,'2024'!$AG$5:$AG$178,">="&DATE(YEAR(TODAY()),MONTH(TODAY())-1,1),'2024'!$AG$5:$AG$178,"<"&DATE(YEAR(TODAY()),MONTH(TODAY()),1))) | I8: =IF(N(D8)=0,"",(SUMIFS('2024'!$AH$5:$AH$178,'2024'!$AG$5:$AG$178,">="&DATE(YEAR(TODAY()),MONTH(TODAY())-1,1),'2024'!$AG$5:$AG$178,"<"&DATE(YEAR(TODAY()),MONTH(TODAY()),1)))/D8) | J8: =IF(N(D8)=0,"",(SUMIFS('2024'!$AI$5:$AI$178,'2024'!$AG$5:$AG$178,">="&DATE(YEAR(TODAY()),MONTH(TODAY())-1,1),'2024'!$AG$5:$AG$178,"<"&DATE(YEAR(TODAY()),MONTH(TODAY()),1)))/D8)
B9: This year | C9: =IF(FALSE,"",COUNTIFS('2024'!$AD$5:$AD$178,">="&DATE(YEAR(TODAY()),1,1),'2024'!$AD$5:$AD$178,"<"&DATE(YEAR(TODAY())+1,1,1))) | D9: =IF(FALSE,"",COUNTIFS('2024'!$AG$5:$AG$178,">="&DATE(YEAR(TODAY()),1,1),'2024'!$AG$5:$AG$178,"<"&DATE(YEAR(TODAY())+1,1,1))) | E9: =IF(FALSE,"",SUMIFS('2024'!$X$5:$X$178,'2024'!$AG$5:$AG$178,">="&DATE(YEAR(TODAY()),1,1),'2024'!$AG$5:$AG$178,"<"&DATE(YEAR(TODAY())+1,1,1))) | F9: =IF(N(D9)=0,"",E9/D9) | G9: =IF(E9="","",E9/2) | H9: =IF(FALSE,"",SUMIFS('2024'!$V$5:$V$178,'2024'!$AG$5:$AG$178,">="&DATE(YEAR(TODAY()),1,1),'2024'!$AG$5:$AG$178,"<"&DATE(YEAR(TODAY())+1,1,1))) | I9: =IF(N(D9)=0,"",(SUMIFS('2024'!$AH$5:$AH$178,'2024'!$AG$5:$AG$178,">="&DATE(YEAR(TODAY()),1,1),'2024'!$AG$5:$AG$178,"<"&DATE(YEAR(TODAY())+1,1,1)))/D9) | J9: =IF(N(D9)=0,"",(SUMIFS('2024'!$AI$5:$AI$178,'2024'!$AG$5:$AG$178,">="&DATE(YEAR(TODAY()),1,1),'2024'!$AG$5:$AG$178,"<"&DATE(YEAR(TODAY())+1,1,1)))/D9)
B10: Last year | C10: =IF(FALSE,"",COUNTIFS('2024'!$AD$5:$AD$178,">="&DATE(YEAR(TODAY())-1,1,1),'2024'!$AD$5:$AD$178,"<"&DATE(YEAR(TODAY()),1,1))) | D10: =IF(FALSE,"",COUNTIFS('2024'!$AG$5:$AG$178,">="&DATE(YEAR(TODAY())-1,1,1),'2024'!$AG$5:$AG$178,"<"&DATE(YEAR(TODAY()),1,1))) | E10: =IF(FALSE,"",SUMIFS('2024'!$X$5:$X$178,'2024'!$AG$5:$AG$178,">="&DATE(YEAR(TODAY())-1,1,1),'2024'!$AG$5:$AG$178,"<"&DATE(YEAR(TODAY()),1,1))) | F10: =IF(N(D10)=0,"",E10/D10) | G10: =IF(E10="","",E10/2) | H10: =IF(FALSE,"",SUMIFS('2024'!$V$5:$V$178,'2024'!$AG$5:$AG$178,">="&DATE(YEAR(TODAY())-1,1,1),'2024'!$AG$5:$AG$178,"<"&DATE(YEAR(TODAY()),1,1))) | I10: =IF(N(D10)=0,"",(SUMIFS('2024'!$AH$5:$AH$178,'2024'!$AG$5:$AG$178,">="&DATE(YEAR(TODAY())-1,1,1),'2024'!$AG$5:$AG$178,"<"&DATE(YEAR(TODAY()),1,1)))/D10) | J10: =IF(N(D10)=0,"",(SUMIFS('2024'!$AI$5:$AI$178,'2024'!$AG$5:$AG$178,">="&DATE(YEAR(TODAY())-1,1,1),'2024'!$AG$5:$AG$178,"<"&DATE(YEAR(TODAY()),1,1)))/D10)
B11: Last 12 months | C11: =IF(FALSE,"",COUNTIFS('2024'!$AD$5:$AD$178,">="&EDATE(DATE(YEAR(TODAY()),MONTH(TODAY()),1),-11),'2024'!$AD$5:$AD$178,"<"&DATE(YEAR(TODAY()),MONTH(TODAY())+1,1))) | D11: =IF(FALSE,"",COUNTIFS('2024'!$AG$5:$AG$178,">="&EDATE(DATE(YEAR(TODAY()),MONTH(TODAY()),1),-11),'2024'!$AG$5:$AG$178,"<"&DATE(YEAR(TODAY()),MONTH(TODAY())+1,1))) | E11: =IF(FALSE,"",SUMIFS('2024'!$X$5:$X$178,'2024'!$AG$5:$AG$178,">="&EDATE(DATE(YEAR(TODAY()),MONTH(TODAY()),1),-11),'2024'!$AG$5:$AG$178,"<"&DATE(YEAR(TODAY()),MONTH(TODAY())+1,1))) | F11: =IF(N(D11)=0,"",E11/D11) | G11: =IF(E11="","",E11/2) | H11: =IF(FALSE,"",SUMIFS('2024'!$V$5:$V$178,'2024'!$AG$5:$AG$178,">="&EDATE(DATE(YEAR(TODAY()),MONTH(TODAY()),1),-11),'2024'!$AG$5:$AG$178,"<"&DATE(YEAR(TODAY()),MONTH(TODAY())+1,1))) | I11: =IF(N(D11)=0,"",(SUMIFS('2024'!$AH$5:$AH$178,'2024'!$AG$5:$AG$178,">="&EDATE(DATE(YEAR(TODAY()),MONTH(TODAY()),1),-11),'2024'!$AG$5:$AG$178,"<"&DATE(YEAR(TODAY()),MONTH(TODAY())+1,1)))/D11) | J11: =IF(N(D11)=0,"",(SUMIFS('2024'!$AI$5:$AI$178,'2024'!$AG$5:$AG$178,">="&EDATE(DATE(YEAR(TODAY()),MONTH(TODAY()),1),-11),'2024'!$AG$5:$AG$178,"<"&DATE(YEAR(TODAY()),MONTH(TODAY())+1,1)))/D11)
B13: By year — a new year appears by itself on 1 January
B14: Year | C14: Cars bought | D14: Cars sold | E14: Profit | F14: Avg profit / car | G14: Half profit (each of you) | H14: Sales total | I14: Avg days online | J14: Avg days bought → sold
B15: =IF(2024>YEAR(TODAY()),"",2024) | C15: =IF(2024>YEAR(TODAY()),"",COUNTIFS('2024'!$AD$5:$AD$178,">="&DATE(2024,1,1),'2024'!$AD$5:$AD$178,"<"&DATE(2025,1,1))) | D15: =IF(2024>YEAR(TODAY()),"",COUNTIFS('2024'!$AG$5:$AG$178,">="&DATE(2024,1,1),'2024'!$AG$5:$AG$178,"<"&DATE(2025,1,1))) | E15: =IF(2024>YEAR(TODAY()),"",SUMIFS('2024'!$X$5:$X$178,'2024'!$AG$5:$AG$178,">="&DATE(2024,1,1),'2024'!$AG$5:$AG$178,"<"&DATE(2025,1,1))) | F15: =IF(N(D15)=0,"",E15/D15) | G15: =IF(E15="","",E15/2) | H15: =IF(2024>YEAR(TODAY()),"",SUMIFS('2024'!$V$5:$V$178,'2024'!$AG$5:$AG$178,">="&DATE(2024,1,1),'2024'!$AG$5:$AG$178,"<"&DATE(2025,1,1))) | I15: =IF(N(D15)=0,"",(SUMIFS('2024'!$AH$5:$AH$178,'2024'!$AG$5:$AG$178,">="&DATE(2024,1,1),'2024'!$AG$5:$AG$178,"<"&DATE(2025,1,1)))/D15) | J15: =IF(N(D15)=0,"",(SUMIFS('2024'!$AI$5:$AI$178,'2024'!$AG$5:$AG$178,">="&DATE(2024,1,1),'2024'!$AG$5:$AG$178,"<"&DATE(2025,1,1)))/D15)
B16: =IF(2025>YEAR(TODAY()),"",2025) | C16: =IF(2025>YEAR(TODAY()),"",COUNTIFS('2024'!$AD$5:$AD$178,">="&DATE(2025,1,1),'2024'!$AD$5:$AD$178,"<"&DATE(2026,1,1))) | D16: =IF(2025>YEAR(TODAY()),"",COUNTIFS('2024'!$AG$5:$AG$178,">="&DATE(2025,1,1),'2024'!$AG$5:$AG$178,"<"&DATE(2026,1,1))) | E16: =IF(2025>YEAR(TODAY()),"",SUMIFS('2024'!$X$5:$X$178,'2024'!$AG$5:$AG$178,">="&DATE(2025,1,1),'2024'!$AG$5:$AG$178,"<"&DATE(2026,1,1))) | F16: =IF(N(D16)=0,"",E16/D16) | G16: =IF(E16="","",E16/2) | H16: =IF(2025>YEAR(TODAY()),"",SUMIFS('2024'!$V$5:$V$178,'2024'!$AG$5:$AG$178,">="&DATE(2025,1,1),'2024'!$AG$5:$AG$178,"<"&DATE(2026,1,1))) | I16: =IF(N(D16)=0,"",(SUMIFS('2024'!$AH$5:$AH$178,'2024'!$AG$5:$AG$178,">="&DATE(2025,1,1),'2024'!$AG$5:$AG$178,"<"&DATE(2026,1,1)))/D16) | J16: =IF(N(D16)=0,"",(SUMIFS('2024'!$AI$5:$AI$178,'2024'!$AG$5:$AG$178,">="&DATE(2025,1,1),'2024'!$AG$5:$AG$178,"<"&DATE(2026,1,1)))/D16)
B17: =IF(2026>YEAR(TODAY()),"",2026) | C17: =IF(2026>YEAR(TODAY()),"",COUNTIFS('2024'!$AD$5:$AD$178,">="&DATE(2026,1,1),'2024'!$AD$5:$AD$178,"<"&DATE(2027,1,1))) | D17: =IF(2026>YEAR(TODAY()),"",COUNTIFS('2024'!$AG$5:$AG$178,">="&DATE(2026,1,1),'2024'!$AG$5:$AG$178,"<"&DATE(2027,1,1))) | E17: =IF(2026>YEAR(TODAY()),"",SUMIFS('2024'!$X$5:$X$178,'2024'!$AG$5:$AG$178,">="&DATE(2026,1,1),'2024'!$AG$5:$AG$178,"<"&DATE(2027,1,1))) | F17: =IF(N(D17)=0,"",E17/D17) | G17: =IF(E17="","",E17/2) | H17: =IF(2026>YEAR(TODAY()),"",SUMIFS('2024'!$V$5:$V$178,'2024'!$AG$5:$AG$178,">="&DATE(2026,1,1),'2024'!$AG$5:$AG$178,"<"&DATE(2027,1,1))) | I17: =IF(N(D17)=0,"",(SUMIFS('2024'!$AH$5:$AH$178,'2024'!$AG$5:$AG$178,">="&DATE(2026,1,1),'2024'!$AG$5:$AG$178,"<"&DATE(2027,1,1)))/D17) | J17: =IF(N(D17)=0,"",(SUMIFS('2024'!$AI$5:$AI$178,'2024'!$AG$5:$AG$178,">="&DATE(2026,1,1),'2024'!$AG$5:$AG$178,"<"&DATE(2027,1,1)))/D17)
B18: =IF(2027>YEAR(TODAY()),"",2027) | C18: =IF(2027>YEAR(TODAY()),"",COUNTIFS('2024'!$AD$5:$AD$178,">="&DATE(2027,1,1),'2024'!$AD$5:$AD$178,"<"&DATE(2028,1,1))) | D18: =IF(2027>YEAR(TODAY()),"",COUNTIFS('2024'!$AG$5:$AG$178,">="&DATE(2027,1,1),'2024'!$AG$5:$AG$178,"<"&DATE(2028,1,1))) | E18: =IF(2027>YEAR(TODAY()),"",SUMIFS('2024'!$X$5:$X$178,'2024'!$AG$5:$AG$178,">="&DATE(2027,1,1),'2024'!$AG$5:$AG$178,"<"&DATE(2028,1,1))) | F18: =IF(N(D18)=0,"",E18/D18) | G18: =IF(E18="","",E18/2) | H18: =IF(2027>YEAR(TODAY()),"",SUMIFS('2024'!$V$5:$V$178,'2024'!$AG$5:$AG$178,">="&DATE(2027,1,1),'2024'!$AG$5:$AG$178,"<"&DATE(2028,1,1))) | I18: =IF(N(D18)=0,"",(SUMIFS('2024'!$AH$5:$AH$178,'2024'!$AG$5:$AG$178,">="&DATE(2027,1,1),'2024'!$AG$5:$AG$178,"<"&DATE(2028,1,1)))/D18) | J18: =IF(N(D18)=0,"",(SUMIFS('2024'!$AI$5:$AI$178,'2024'!$AG$5:$AG$178,">="&DATE(2027,1,1),'2024'!$AG$5:$AG$178,"<"&DATE(2028,1,1)))/D18)
B19: =IF(2028>YEAR(TODAY()),"",2028) | C19: =IF(2028>YEAR(TODAY()),"",COUNTIFS('2024'!$AD$5:$AD$178,">="&DATE(2028,1,1),'2024'!$AD$5:$AD$178,"<"&DATE(2029,1,1))) | D19: =IF(2028>YEAR(TODAY()),"",COUNTIFS('2024'!$AG$5:$AG$178,">="&DATE(2028,1,1),'2024'!$AG$5:$AG$178,"<"&DATE(2029,1,1))) | E19: =IF(2028>YEAR(TODAY()),"",SUMIFS('2024'!$X$5:$X$178,'2024'!$AG$5:$AG$178,">="&DATE(2028,1,1),'2024'!$AG$5:$AG$178,"<"&DATE(2029,1,1))) | F19: =IF(N(D19)=0,"",E19/D19) | G19: =IF(E19="","",E19/2) | H19: =IF(2028>YEAR(TODAY()),"",SUMIFS('2024'!$V$5:$V$178,'2024'!$AG$5:$AG$178,">="&DATE(2028,1,1),'2024'!$AG$5:$AG$178,"<"&DATE(2029,1,1))) | I19: =IF(N(D19)=0,"",(SUMIFS('2024'!$AH$5:$AH$178,'2024'!$AG$5:$AG$178,">="&DATE(2028,1,1),'2024'!$AG$5:$AG$178,"<"&DATE(2029,1,1)))/D19) | J19: =IF(N(D19)=0,"",(SUMIFS('2024'!$AI$5:$AI$178,'2024'!$AG$5:$AG$178,">="&DATE(2028,1,1),'2024'!$AG$5:$AG$178,"<"&DATE(2029,1,1)))/D19)
B20: =IF(2029>YEAR(TODAY()),"",2029) | C20: =IF(2029>YEAR(TODAY()),"",COUNTIFS('2024'!$AD$5:$AD$178,">="&DATE(2029,1,1),'2024'!$AD$5:$AD$178,"<"&DATE(2030,1,1))) | D20: =IF(2029>YEAR(TODAY()),"",COUNTIFS('2024'!$AG$5:$AG$178,">="&DATE(2029,1,1),'2024'!$AG$5:$AG$178,"<"&DATE(2030,1,1))) | E20: =IF(2029>YEAR(TODAY()),"",SUMIFS('2024'!$X$5:$X$178,'2024'!$AG$5:$AG$178,">="&DATE(2029,1,1),'2024'!$AG$5:$AG$178,"<"&DATE(2030,1,1))) | F20: =IF(N(D20)=0,"",E20/D20) | G20: =IF(E20="","",E20/2) | H20: =IF(2029>YEAR(TODAY()),"",SUMIFS('2024'!$V$5:$V$178,'2024'!$AG$5:$AG$178,">="&DATE(2029,1,1),'2024'!$AG$5:$AG$178,"<"&DATE(2030,1,1))) | I20: =IF(N(D20)=0,"",(SUMIFS('2024'!$AH$5:$AH$178,'2024'!$AG$5:$AG$178,">="&DATE(2029,1,1),'2024'!$AG$5:$AG$178,"<"&DATE(2030,1,1)))/D20) | J20: =IF(N(D20)=0,"",(SUMIFS('2024'!$AI$5:$AI$178,'2024'!$AG$5:$AG$178,">="&DATE(2029,1,1),'2024'!$AG$5:$AG$178,"<"&DATE(2030,1,1)))/D20)
B21: =IF(2030>YEAR(TODAY()),"",2030) | C21: =IF(2030>YEAR(TODAY()),"",COUNTIFS('2024'!$AD$5:$AD$178,">="&DATE(2030,1,1),'2024'!$AD$5:$AD$178,"<"&DATE(2031,1,1))) | D21: =IF(2030>YEAR(TODAY()),"",COUNTIFS('2024'!$AG$5:$AG$178,">="&DATE(2030,1,1),'2024'!$AG$5:$AG$178,"<"&DATE(2031,1,1))) | E21: =IF(2030>YEAR(TODAY()),"",SUMIFS('2024'!$X$5:$X$178,'2024'!$AG$5:$AG$178,">="&DATE(2030,1,1),'2024'!$AG$5:$AG$178,"<"&DATE(2031,1,1))) | F21: =IF(N(D21)=0,"",E21/D21) | G21: =IF(E21="","",E21/2) | H21: =IF(2030>YEAR(TODAY()),"",SUMIFS('2024'!$V$5:$V$178,'2024'!$AG$5:$AG$178,">="&DATE(2030,1,1),'2024'!$AG$5:$AG$178,"<"&DATE(2031,1,1))) | I21: =IF(N(D21)=0,"",(SUMIFS('2024'!$AH$5:$AH$178,'2024'!$AG$5:$AG$178,">="&DATE(2030,1,1),'2024'!$AG$5:$AG$178,"<"&DATE(2031,1,1)))/D21) | J21: =IF(N(D21)=0,"",(SUMIFS('2024'!$AI$5:$AI$178,'2024'!$AG$5:$AG$178,">="&DATE(2030,1,1),'2024'!$AG$5:$AG$178,"<"&DATE(2031,1,1)))/D21)
B22: =IF(2031>YEAR(TODAY()),"",2031) | C22: =IF(2031>YEAR(TODAY()),"",COUNTIFS('2024'!$AD$5:$AD$178,">="&DATE(2031,1,1),'2024'!$AD$5:$AD$178,"<"&DATE(2032,1,1))) | D22: =IF(2031>YEAR(TODAY()),"",COUNTIFS('2024'!$AG$5:$AG$178,">="&DATE(2031,1,1),'2024'!$AG$5:$AG$178,"<"&DATE(2032,1,1))) | E22: =IF(2031>YEAR(TODAY()),"",SUMIFS('2024'!$X$5:$X$178,'2024'!$AG$5:$AG$178,">="&DATE(2031,1,1),'2024'!$AG$5:$AG$178,"<"&DATE(2032,1,1))) | F22: =IF(N(D22)=0,"",E22/D22) | G22: =IF(E22="","",E22/2) | H22: =IF(2031>YEAR(TODAY()),"",SUMIFS('2024'!$V$5:$V$178,'2024'!$AG$5:$AG$178,">="&DATE(2031,1,1),'2024'!$AG$5:$AG$178,"<"&DATE(2032,1,1))) | I22: =IF(N(D22)=0,"",(SUMIFS('2024'!$AH$5:$AH$178,'2024'!$AG$5:$AG$178,">="&DATE(2031,1,1),'2024'!$AG$5:$AG$178,"<"&DATE(2032,1,1)))/D22) | J22: =IF(N(D22)=0,"",(SUMIFS('2024'!$AI$5:$AI$178,'2024'!$AG$5:$AG$178,">="&DATE(2031,1,1),'2024'!$AG$5:$AG$178,"<"&DATE(2032,1,1)))/D22)
B23: =IF(2032>YEAR(TODAY()),"",2032) | C23: =IF(2032>YEAR(TODAY()),"",COUNTIFS('2024'!$AD$5:$AD$178,">="&DATE(2032,1,1),'2024'!$AD$5:$AD$178,"<"&DATE(2033,1,1))) | D23: =IF(2032>YEAR(TODAY()),"",COUNTIFS('2024'!$AG$5:$AG$178,">="&DATE(2032,1,1),'2024'!$AG$5:$AG$178,"<"&DATE(2033,1,1))) | E23: =IF(2032>YEAR(TODAY()),"",SUMIFS('2024'!$X$5:$X$178,'2024'!$AG$5:$AG$178,">="&DATE(2032,1,1),'2024'!$AG$5:$AG$178,"<"&DATE(2033,1,1))) | F23: =IF(N(D23)=0,"",E23/D23) | G23: =IF(E23="","",E23/2) | H23: =IF(2032>YEAR(TODAY()),"",SUMIFS('2024'!$V$5:$V$178,'2024'!$AG$5:$AG$178,">="&DATE(2032,1,1),'2024'!$AG$5:$AG$178,"<"&DATE(2033,1,1))) | I23: =IF(N(D23)=0,"",(SUMIFS('2024'!$AH$5:$AH$178,'2024'!$AG$5:$AG$178,">="&DATE(2032,1,1),'2024'!$AG$5:$AG$178,"<"&DATE(2033,1,1)))/D23) | J23: =IF(N(D23)=0,"",(SUMIFS('2024'!$AI$5:$AI$178,'2024'!$AG$5:$AG$178,">="&DATE(2032,1,1),'2024'!$AG$5:$AG$178,"<"&DATE(2033,1,1)))/D23)
B24: =IF(2033>YEAR(TODAY()),"",2033) | C24: =IF(2033>YEAR(TODAY()),"",COUNTIFS('2024'!$AD$5:$AD$178,">="&DATE(2033,1,1),'2024'!$AD$5:$AD$178,"<"&DATE(2034,1,1))) | D24: =IF(2033>YEAR(TODAY()),"",COUNTIFS('2024'!$AG$5:$AG$178,">="&DATE(2033,1,1),'2024'!$AG$5:$AG$178,"<"&DATE(2034,1,1))) | E24: =IF(2033>YEAR(TODAY()),"",SUMIFS('2024'!$X$5:$X$178,'2024'!$AG$5:$AG$178,">="&DATE(2033,1,1),'2024'!$AG$5:$AG$178,"<"&DATE(2034,1,1))) | F24: =IF(N(D24)=0,"",E24/D24) | G24: =IF(E24="","",E24/2) | H24: =IF(2033>YEAR(TODAY()),"",SUMIFS('2024'!$V$5:$V$178,'2024'!$AG$5:$AG$178,">="&DATE(2033,1,1),'2024'!$AG$5:$AG$178,"<"&DATE(2034,1,1))) | I24: =IF(N(D24)=0,"",(SUMIFS('2024'!$AH$5:$AH$178,'2024'!$AG$5:$AG$178,">="&DATE(2033,1,1),'2024'!$AG$5:$AG$178,"<"&DATE(2034,1,1)))/D24) | J24: =IF(N(D24)=0,"",(SUMIFS('2024'!$AI$5:$AI$178,'2024'!$AG$5:$AG$178,">="&DATE(2033,1,1),'2024'!$AG$5:$AG$178,"<"&DATE(2034,1,1)))/D24)
B25: =IF(2034>YEAR(TODAY()),"",2034) | C25: =IF(2034>YEAR(TODAY()),"",COUNTIFS('2024'!$AD$5:$AD$178,">="&DATE(2034,1,1),'2024'!$AD$5:$AD$178,"<"&DATE(2035,1,1))) | D25: =IF(2034>YEAR(TODAY()),"",COUNTIFS('2024'!$AG$5:$AG$178,">="&DATE(2034,1,1),'2024'!$AG$5:$AG$178,"<"&DATE(2035,1,1))) | E25: =IF(2034>YEAR(TODAY()),"",SUMIFS('2024'!$X$5:$X$178,'2024'!$AG$5:$AG$178,">="&DATE(2034,1,1),'2024'!$AG$5:$AG$178,"<"&DATE(2035,1,1))) | F25: =IF(N(D25)=0,"",E25/D25) | G25: =IF(E25="","",E25/2) | H25: =IF(2034>YEAR(TODAY()),"",SUMIFS('2024'!$V$5:$V$178,'2024'!$AG$5:$AG$178,">="&DATE(2034,1,1),'2024'!$AG$5:$AG$178,"<"&DATE(2035,1,1))) | I25: =IF(N(D25)=0,"",(SUMIFS('2024'!$AH$5:$AH$178,'2024'!$AG$5:$AG$178,">="&DATE(2034,1,1),'2024'!$AG$5:$AG$178,"<"&DATE(2035,1,1)))/D25) | J25: =IF(N(D25)=0,"",(SUMIFS('2024'!$AI$5:$AI$178,'2024'!$AG$5:$AG$178,">="&DATE(2034,1,1),'2024'!$AG$5:$AG$178,"<"&DATE(2035,1,1)))/D25)
B26: =IF(2035>YEAR(TODAY()),"",2035) | C26: =IF(2035>YEAR(TODAY()),"",COUNTIFS('2024'!$AD$5:$AD$178,">="&DATE(2035,1,1),'2024'!$AD$5:$AD$178,"<"&DATE(2036,1,1))) | D26: =IF(2035>YEAR(TODAY()),"",COUNTIFS('2024'!$AG$5:$AG$178,">="&DATE(2035,1,1),'2024'!$AG$5:$AG$178,"<"&DATE(2036,1,1))) | E26: =IF(2035>YEAR(TODAY()),"",SUMIFS('2024'!$X$5:$X$178,'2024'!$AG$5:$AG$178,">="&DATE(2035,1,1),'2024'!$AG$5:$AG$178,"<"&DATE(2036,1,1))) | F26: =IF(N(D26)=0,"",E26/D26) | G26: =IF(E26="","",E26/2) | H26: =IF(2035>YEAR(TODAY()),"",SUMIFS('2024'!$V$5:$V$178,'2024'!$AG$5:$AG$178,">="&DATE(2035,1,1),'2024'!$AG$5:$AG$178,"<"&DATE(2036,1,1))) | I26: =IF(N(D26)=0,"",(SUMIFS('2024'!$AH$5:$AH$178,'2024'!$AG$5:$AG$178,">="&DATE(2035,1,1),'2024'!$AG$5:$AG$178,"<"&DATE(2036,1,1)))/D26) | J26: =IF(N(D26)=0,"",(SUMIFS('2024'!$AI$5:$AI$178,'2024'!$AG$5:$AG$178,">="&DATE(2035,1,1),'2024'!$AG$5:$AG$178,"<"&DATE(2036,1,1)))/D26)
B27: All years | C27: =SUM(C15:C26) | D27: =SUM(D15:D26) | E27: =SUM(E15:E26) | F27: =IF(D27=0,"",E27/D27) | G27: =E27/2 | H27: =SUM(H15:H26)
B29: By month — the current month is highlighted
B30: Month | C30: Cars bought | D30: Cars sold | E30: Profit | F30: Avg profit / car | G30: Half profit (each of you) | H30: Sales total | I30: Avg days online | J30: Avg days bought → sold
B31: =IF(DATE(2024,1,1)>TODAY(),"",DATE(2024,1,1)) | C31: =IF(DATE(2024,1,1)>TODAY(),"",COUNTIFS('2024'!$AD$5:$AD$178,">="&DATE(2024,1,1),'2024'!$AD$5:$AD$178,"<"&EDATE(DATE(2024,1,1),1))) | D31: =IF(DATE(2024,1,1)>TODAY(),"",COUNTIFS('2024'!$AG$5:$AG$178,">="&DATE(2024,1,1),'2024'!$AG$5:$AG$178,"<"&EDATE(DATE(2024,1,1),1))) | E31: =IF(DATE(2024,1,1)>TODAY(),"",SUMIFS('2024'!$X$5:$X$178,'2024'!$AG$5:$AG$178,">="&DATE(2024,1,1),'2024'!$AG$5:$AG$178,"<"&EDATE(DATE(2024,1,1),1))) | F31: =IF(N(D31)=0,"",E31/D31) | G31: =IF(E31="","",E31/2) | H31: =IF(DATE(2024,1,1)>TODAY(),"",SUMIFS('2024'!$V$5:$V$178,'2024'!$AG$5:$AG$178,">="&DATE(2024,1,1),'2024'!$AG$5:$AG$178,"<"&EDATE(DATE(2024,1,1),1))) | I31: =IF(N(D31)=0,"",(SUMIFS('2024'!$AH$5:$AH$178,'2024'!$AG$5:$AG$178,">="&DATE(2024,1,1),'2024'!$AG$5:$AG$178,"<"&EDATE(DATE(2024,1,1),1)))/D31) | J31: =IF(N(D31)=0,"",(SUMIFS('2024'!$AI$5:$AI$178,'2024'!$AG$5:$AG$178,">="&DATE(2024,1,1),'2024'!$AG$5:$AG$178,"<"&EDATE(DATE(2024,1,1),1)))/D31)
B32: =IF(DATE(2024,2,1)>TODAY(),"",DATE(2024,2,1)) | C32: =IF(DATE(2024,2,1)>TODAY(),"",COUNTIFS('2024'!$AD$5:$AD$178,">="&DATE(2024,2,1),'2024'!$AD$5:$AD$178,"<"&EDATE(DATE(2024,2,1),1))) | D32: =IF(DATE(2024,2,1)>TODAY(),"",COUNTIFS('2024'!$AG$5:$AG$178,">="&DATE(2024,2,1),'2024'!$AG$5:$AG$178,"<"&EDATE(DATE(2024,2,1),1))) | E32: =IF(DATE(2024,2,1)>TODAY(),"",SUMIFS('2024'!$X$5:$X$178,'2024'!$AG$5:$AG$178,">="&DATE(2024,2,1),'2024'!$AG$5:$AG$178,"<"&EDATE(DATE(2024,2,1),1))) | F32: =IF(N(D32)=0,"",E32/D32) | G32: =IF(E32="","",E32/2) | H32: =IF(DATE(2024,2,1)>TODAY(),"",SUMIFS('2024'!$V$5:$V$178,'2024'!$AG$5:$AG$178,">="&DATE(2024,2,1),'2024'!$AG$5:$AG$178,"<"&EDATE(DATE(2024,2,1),1))) | I32: =IF(N(D32)=0,"",(SUMIFS('2024'!$AH$5:$AH$178,'2024'!$AG$5:$AG$178,">="&DATE(2024,2,1),'2024'!$AG$5:$AG$178,"<"&EDATE(DATE(2024,2,1),1)))/D32) | J32: =IF(N(D32)=0,"",(SUMIFS('2024'!$AI$5:$AI$178,'2024'!$AG$5:$AG$178,">="&DATE(2024,2,1),'2024'!$AG$5:$AG$178,"<"&EDATE(DATE(2024,2,1),1)))/D32)
B33: =IF(DATE(2024,3,1)>TODAY(),"",DATE(2024,3,1)) | C33: =IF(DATE(2024,3,1)>TODAY(),"",COUNTIFS('2024'!$AD$5:$AD$178,">="&DATE(2024,3,1),'2024'!$AD$5:$AD$178,"<"&EDATE(DATE(2024,3,1),1))) | D33: =IF(DATE(2024,3,1)>TODAY(),"",COUNTIFS('2024'!$AG$5:$AG$178,">="&DATE(2024,3,1),'2024'!$AG$5:$AG$178,"<"&EDATE(DATE(2024,3,1),1))) | E33: =IF(DATE(2024,3,1)>TODAY(),"",SUMIFS('2024'!$X$5:$X$178,'2024'!$AG$5:$AG$178,">="&DATE(2024,3,1),'2024'!$AG$5:$AG$178,"<"&EDATE(DATE(2024,3,1),1))) | F33: =IF(N(D33)=0,"",E33/D33) | G33: =IF(E33="","",E33/2) | H33: =IF(DATE(2024,3,1)>TODAY(),"",SUMIFS('2024'!$V$5:$V$178,'2024'!$AG$5:$AG$178,">="&DATE(2024,3,1),'2024'!$AG$5:$AG$178,"<"&EDATE(DATE(2024,3,1),1))) | I33: =IF(N(D33)=0,"",(SUMIFS('2024'!$AH$5:$AH$178,'2024'!$AG$5:$AG$178,">="&DATE(2024,3,1),'2024'!$AG$5:$AG$178,"<"&EDATE(DATE(2024,3,1),1)))/D33) | J33: =IF(N(D33)=0,"",(SUMIFS('2024'!$AI$5:$AI$178,'2024'!$AG$5:$AG$178,">="&DATE(2024,3,1),'2024'!$AG$5:$AG$178,"<"&EDATE(DATE(2024,3,1),1)))/D33)
B34: =IF(DATE(2024,4,1)>TODAY(),"",DATE(2024,4,1)) | C34: =IF(DATE(2024,4,1)>TODAY(),"",COUNTIFS('2024'!$AD$5:$AD$178,">="&DATE(2024,4,1),'2024'!$AD$5:$AD$178,"<"&EDATE(DATE(2024,4,1),1))) | D34: =IF(DATE(2024,4,1)>TODAY(),"",COUNTIFS('2024'!$AG$5:$AG$178,">="&DATE(2024,4,1),'2024'!$AG$5:$AG$178,"<"&EDATE(DATE(2024,4,1),1))) | E34: =IF(DATE(2024,4,1)>TODAY(),"",SUMIFS('2024'!$X$5:$X$178,'2024'!$AG$5:$AG$178,">="&DATE(2024,4,1),'2024'!$AG$5:$AG$178,"<"&EDATE(DATE(2024,4,1),1))) | F34: =IF(N(D34)=0,"",E34/D34) | G34: =IF(E34="","",E34/2) | H34: =IF(DATE(2024,4,1)>TODAY(),"",SUMIFS('2024'!$V$5:$V$178,'2024'!$AG$5:$AG$178,">="&DATE(2024,4,1),'2024'!$AG$5:$AG$178,"<"&EDATE(DATE(2024,4,1),1))) | I34: =IF(N(D34)=0,"",(SUMIFS('2024'!$AH$5:$AH$178,'2024'!$AG$5:$AG$178,">="&DATE(2024,4,1),'2024'!$AG$5:$AG$178,"<"&EDATE(DATE(2024,4,1),1)))/D34) | J34: =IF(N(D34)=0,"",(SUMIFS('2024'!$AI$5:$AI$178,'2024'!$AG$5:$AG$178,">="&DATE(2024,4,1),'2024'!$AG$5:$AG$178,"<"&EDATE(DATE(2024,4,1),1)))/D34)
B35: =IF(DATE(2024,5,1)>TODAY(),"",DATE(2024,5,1)) | C35: =IF(DATE(2024,5,1)>TODAY(),"",COUNTIFS('2024'!$AD$5:$AD$178,">="&DATE(2024,5,1),'2024'!$AD$5:$AD$178,"<"&EDATE(DATE(2024,5,1),1))) | D35: =IF(DATE(2024,5,1)>TODAY(),"",COUNTIFS('2024'!$AG$5:$AG$178,">="&DATE(2024,5,1),'2024'!$AG$5:$AG$178,"<"&EDATE(DATE(2024,5,1),1))) | E35: =IF(DATE(2024,5,1)>TODAY(),"",SUMIFS('2024'!$X$5:$X$178,'2024'!$AG$5:$AG$178,">="&DATE(2024,5,1),'2024'!$AG$5:$AG$178,"<"&EDATE(DATE(2024,5,1),1))) | F35: =IF(N(D35)=0,"",E35/D35) | G35: =IF(E35="","",E35/2) | H35: =IF(DATE(2024,5,1)>TODAY(),"",SUMIFS('2024'!$V$5:$V$178,'2024'!$AG$5:$AG$178,">="&DATE(2024,5,1),'2024'!$AG$5:$AG$178,"<"&EDATE(DATE(2024,5,1),1))) | I35: =IF(N(D35)=0,"",(SUMIFS('2024'!$AH$5:$AH$178,'2024'!$AG$5:$AG$178,">="&DATE(2024,5,1),'2024'!$AG$5:$AG$178,"<"&EDATE(DATE(2024,5,1),1)))/D35) | J35: =IF(N(D35)=0,"",(SUMIFS('2024'!$AI$5:$AI$178,'2024'!$AG$5:$AG$178,">="&DATE(2024,5,1),'2024'!$AG$5:$AG$178,"<"&EDATE(DATE(2024,5,1),1)))/D35)
B36: =IF(DATE(2024,6,1)>TODAY(),"",DATE(2024,6,1)) | C36: =IF(DATE(2024,6,1)>TODAY(),"",COUNTIFS('2024'!$AD$5:$AD$178,">="&DATE(2024,6,1),'2024'!$AD$5:$AD$178,"<"&EDATE(DATE(2024,6,1),1))) | D36: =IF(DATE(2024,6,1)>TODAY(),"",COUNTIFS('2024'!$AG$5:$AG$178,">="&DATE(2024,6,1),'2024'!$AG$5:$AG$178,"<"&EDATE(DATE(2024,6,1),1))) | E36: =IF(DATE(2024,6,1)>TODAY(),"",SUMIFS('2024'!$X$5:$X$178,'2024'!$AG$5:$AG$178,">="&DATE(2024,6,1),'2024'!$AG$5:$AG$178,"<"&EDATE(DATE(2024,6,1),1))) | F36: =IF(N(D36)=0,"",E36/D36) | G36: =IF(E36="","",E36/2) | H36: =IF(DATE(2024,6,1)>TODAY(),"",SUMIFS('2024'!$V$5:$V$178,'2024'!$AG$5:$AG$178,">="&DATE(2024,6,1),'2024'!$AG$5:$AG$178,"<"&EDATE(DATE(2024,6,1),1))) | I36: =IF(N(D36)=0,"",(SUMIFS('2024'!$AH$5:$AH$178,'2024'!$AG$5:$AG$178,">="&DATE(2024,6,1),'2024'!$AG$5:$AG$178,"<"&EDATE(DATE(2024,6,1),1)))/D36) | J36: =IF(N(D36)=0,"",(SUMIFS('2024'!$AI$5:$AI$178,'2024'!$AG$5:$AG$178,">="&DATE(2024,6,1),'2024'!$AG$5:$AG$178,"<"&EDATE(DATE(2024,6,1),1)))/D36)
B37: =IF(DATE(2024,7,1)>TODAY(),"",DATE(2024,7,1)) | C37: =IF(DATE(2024,7,1)>TODAY(),"",COUNTIFS('2024'!$AD$5:$AD$178,">="&DATE(2024,7,1),'2024'!$AD$5:$AD$178,"<"&EDATE(DATE(2024,7,1),1))) | D37: =IF(DATE(2024,7,1)>TODAY(),"",COUNTIFS('2024'!$AG$5:$AG$178,">="&DATE(2024,7,1),'2024'!$AG$5:$AG$178,"<"&EDATE(DATE(2024,7,1),1))) | E37: =IF(DATE(2024,7,1)>TODAY(),"",SUMIFS('2024'!$X$5:$X$178,'2024'!$AG$5:$AG$178,">="&DATE(2024,7,1),'2024'!$AG$5:$AG$178,"<"&EDATE(DATE(2024,7,1),1))) | F37: =IF(N(D37)=0,"",E37/D37) | G37: =IF(E37="","",E37/2) | H37: =IF(DATE(2024,7,1)>TODAY(),"",SUMIFS('2024'!$V$5:$V$178,'2024'!$AG$5:$AG$178,">="&DATE(2024,7,1),'2024'!$AG$5:$AG$178,"<"&EDATE(DATE(2024,7,1),1))) | I37: =IF(N(D37)=0,"",(SUMIFS('2024'!$AH$5:$AH$178,'2024'!$AG$5:$AG$178,">="&DATE(2024,7,1),'2024'!$AG$5:$AG$178,"<"&EDATE(DATE(2024,7,1),1)))/D37) | J37: =IF(N(D37)=0,"",(SUMIFS('2024'!$AI$5:$AI$178,'2024'!$AG$5:$AG$178,">="&DATE(2024,7,1),'2024'!$AG$5:$AG$178,"<"&EDATE(DATE(2024,7,1),1)))/D37)
B38: =IF(DATE(2024,8,1)>TODAY(),"",DATE(2024,8,1)) | C38: =IF(DATE(2024,8,1)>TODAY(),"",COUNTIFS('2024'!$AD$5:$AD$178,">="&DATE(2024,8,1),'2024'!$AD$5:$AD$178,"<"&EDATE(DATE(2024,8,1),1))) | D38: =IF(DATE(2024,8,1)>TODAY(),"",COUNTIFS('2024'!$AG$5:$AG$178,">="&DATE(2024,8,1),'2024'!$AG$5:$AG$178,"<"&EDATE(DATE(2024,8,1),1))) | E38: =IF(DATE(2024,8,1)>TODAY(),"",SUMIFS('2024'!$X$5:$X$178,'2024'!$AG$5:$AG$178,">="&DATE(2024,8,1),'2024'!$AG$5:$AG$178,"<"&EDATE(DATE(2024,8,1),1))) | F38: =IF(N(D38)=0,"",E38/D38) | G38: =IF(E38="","",E38/2) | H38: =IF(DATE(2024,8,1)>TODAY(),"",SUMIFS('2024'!$V$5:$V$178,'2024'!$AG$5:$AG$178,">="&DATE(2024,8,1),'2024'!$AG$5:$AG$178,"<"&EDATE(DATE(2024,8,1),1))) | I38: =IF(N(D38)=0,"",(SUMIFS('2024'!$AH$5:$AH$178,'2024'!$AG$5:$AG$178,">="&DATE(2024,8,1),'2024'!$AG$5:$AG$178,"<"&EDATE(DATE(2024,8,1),1)))/D38) | J38: =IF(N(D38)=0,"",(SUMIFS('2024'!$AI$5:$AI$178,'2024'!$AG$5:$AG$178,">="&DATE(2024,8,1),'2024'!$AG$5:$AG$178,"<"&EDATE(DATE(2024,8,1),1)))/D38)
B39: =IF(DATE(2024,9,1)>TODAY(),"",DATE(2024,9,1)) | C39: =IF(DATE(2024,9,1)>TODAY(),"",COUNTIFS('2024'!$AD$5:$AD$178,">="&DATE(2024,9,1),'2024'!$AD$5:$AD$178,"<"&EDATE(DATE(2024,9,1),1))) | D39: =IF(DATE(2024,9,1)>TODAY(),"",COUNTIFS('2024'!$AG$5:$AG$178,">="&DATE(2024,9,1),'2024'!$AG$5:$AG$178,"<"&EDATE(DATE(2024,9,1),1))) | E39: =IF(DATE(2024,9,1)>TODAY(),"",SUMIFS('2024'!$X$5:$X$178,'2024'!$AG$5:$AG$178,">="&DATE(2024,9,1),'2024'!$AG$5:$AG$178,"<"&EDATE(DATE(2024,9,1),1))) | F39: =IF(N(D39)=0,"",E39/D39) | G39: =IF(E39="","",E39/2) | H39: =IF(DATE(2024,9,1)>TODAY(),"",SUMIFS('2024'!$V$5:$V$178,'2024'!$AG$5:$AG$178,">="&DATE(2024,9,1),'2024'!$AG$5:$AG$178,"<"&EDATE(DATE(2024,9,1),1))) | I39: =IF(N(D39)=0,"",(SUMIFS('2024'!$AH$5:$AH$178,'2024'!$AG$5:$AG$178,">="&DATE(2024,9,1),'2024'!$AG$5:$AG$178,"<"&EDATE(DATE(2024,9,1),1)))/D39) | J39: =IF(N(D39)=0,"",(SUMIFS('2024'!$AI$5:$AI$178,'2024'!$AG$5:$AG$178,">="&DATE(2024,9,1),'2024'!$AG$5:$AG$178,"<"&EDATE(DATE(2024,9,1),1)))/D39)
B40: =IF(DATE(2024,10,1)>TODAY(),"",DATE(2024,10,1)) | C40: =IF(DATE(2024,10,1)>TODAY(),"",COUNTIFS('2024'!$AD$5:$AD$178,">="&DATE(2024,10,1),'2024'!$AD$5:$AD$178,"<"&EDATE(DATE(2024,10,1),1))) | D40: =IF(DATE(2024,10,1)>TODAY(),"",COUNTIFS('2024'!$AG$5:$AG$178,">="&DATE(2024,10,1),'2024'!$AG$5:$AG$178,"<"&EDATE(DATE(2024,10,1),1))) | E40: =IF(DATE(2024,10,1)>TODAY(),"",SUMIFS('2024'!$X$5:$X$178,'2024'!$AG$5:$AG$178,">="&DATE(2024,10,1),'2024'!$AG$5:$AG$178,"<"&EDATE(DATE(2024,10,1),1))) | F40: =IF(N(D40)=0,"",E40/D40) | G40: =IF(E40="","",E40/2) | H40: =IF(DATE(2024,10,1)>TODAY(),"",SUMIFS('2024'!$V$5:$V$178,'2024'!$AG$5:$AG$178,">="&DATE(2024,10,1),'2024'!$AG$5:$AG$178,"<"&EDATE(DATE(2024,10,1),1))) | I40: =IF(N(D40)=0,"",(SUMIFS('2024'!$AH$5:$AH$178,'2024'!$AG$5:$AG$178,">="&DATE(2024,10,1),'2024'!$AG$5:$AG$178,"<"&EDATE(DATE(2024,10,1),1)))/D40) | J40: =IF(N(D40)=0,"",(SUMIFS('2024'!$AI$5:$AI$178,'2024'!$AG$5:$AG$178,">="&DATE(2024,10,1),'2024'!$AG$5:$AG$178,"<"&EDATE(DATE(2024,10,1),1)))/D40)
B41: =IF(DATE(2024,11,1)>TODAY(),"",DATE(2024,11,1)) | C41: =IF(DATE(2024,11,1)>TODAY(),"",COUNTIFS('2024'!$AD$5:$AD$178,">="&DATE(2024,11,1),'2024'!$AD$5:$AD$178,"<"&EDATE(DATE(2024,11,1),1))) | D41: =IF(DATE(2024,11,1)>TODAY(),"",COUNTIFS('2024'!$AG$5:$AG$178,">="&DATE(2024,11,1),'2024'!$AG$5:$AG$178,"<"&EDATE(DATE(2024,11,1),1))) | E41: =IF(DATE(2024,11,1)>TODAY(),"",SUMIFS('2024'!$X$5:$X$178,'2024'!$AG$5:$AG$178,">="&DATE(2024,11,1),'2024'!$AG$5:$AG$178,"<"&EDATE(DATE(2024,11,1),1))) | F41: =IF(N(D41)=0,"",E41/D41) | G41: =IF(E41="","",E41/2) | H41: =IF(DATE(2024,11,1)>TODAY(),"",SUMIFS('2024'!$V$5:$V$178,'2024'!$AG$5:$AG$178,">="&DATE(2024,11,1),'2024'!$AG$5:$AG$178,"<"&EDATE(DATE(2024,11,1),1))) | I41: =IF(N(D41)=0,"",(SUMIFS('2024'!$AH$5:$AH$178,'2024'!$AG$5:$AG$178,">="&DATE(2024,11,1),'2024'!$AG$5:$AG$178,"<"&EDATE(DATE(2024,11,1),1)))/D41) | J41: =IF(N(D41)=0,"",(SUMIFS('2024'!$AI$5:$AI$178,'2024'!$AG$5:$AG$178,">="&DATE(2024,11,1),'2024'!$AG$5:$AG$178,"<"&EDATE(DATE(2024,11,1),1)))/D41)
B42: =IF(DATE(2024,12,1)>TODAY(),"",DATE(2024,12,1)) | C42: =IF(DATE(2024,12,1)>TODAY(),"",COUNTIFS('2024'!$AD$5:$AD$178,">="&DATE(2024,12,1),'2024'!$AD$5:$AD$178,"<"&EDATE(DATE(2024,12,1),1))) | D42: =IF(DATE(2024,12,1)>TODAY(),"",COUNTIFS('2024'!$AG$5:$AG$178,">="&DATE(2024,12,1),'2024'!$AG$5:$AG$178,"<"&EDATE(DATE(2024,12,1),1))) | E42: =IF(DATE(2024,12,1)>TODAY(),"",SUMIFS('2024'!$X$5:$X$178,'2024'!$AG$5:$AG$178,">="&DATE(2024,12,1),'2024'!$AG$5:$AG$178,"<"&EDATE(DATE(2024,12,1),1))) | F42: =IF(N(D42)=0,"",E42/D42) | G42: =IF(E42="","",E42/2) | H42: =IF(DATE(2024,12,1)>TODAY(),"",SUMIFS('2024'!$V$5:$V$178,'2024'!$AG$5:$AG$178,">="&DATE(2024,12,1),'2024'!$AG$5:$AG$178,"<"&EDATE(DATE(2024,12,1),1))) | I42: =IF(N(D42)=0,"",(SUMIFS('2024'!$AH$5:$AH$178,'2024'!$AG$5:$AG$178,">="&DATE(2024,12,1),'2024'!$AG$5:$AG$178,"<"&EDATE(DATE(2024,12,1),1)))/D42) | J42: =IF(N(D42)=0,"",(SUMIFS('2024'!$AI$5:$AI$178,'2024'!$AG$5:$AG$178,">="&DATE(2024,12,1),'2024'!$AG$5:$AG$178,"<"&EDATE(DATE(2024,12,1),1)))/D42)
B43: =IF(DATE(2025,1,1)>TODAY(),"",DATE(2025,1,1)) | C43: =IF(DATE(2025,1,1)>TODAY(),"",COUNTIFS('2024'!$AD$5:$AD$178,">="&DATE(2025,1,1),'2024'!$AD$5:$AD$178,"<"&EDATE(DATE(2025,1,1),1))) | D43: =IF(DATE(2025,1,1)>TODAY(),"",COUNTIFS('2024'!$AG$5:$AG$178,">="&DATE(2025,1,1),'2024'!$AG$5:$AG$178,"<"&EDATE(DATE(2025,1,1),1))) | E43: =IF(DATE(2025,1,1)>TODAY(),"",SUMIFS('2024'!$X$5:$X$178,'2024'!$AG$5:$AG$178,">="&DATE(2025,1,1),'2024'!$AG$5:$AG$178,"<"&EDATE(DATE(2025,1,1),1))) | F43: =IF(N(D43)=0,"",E43/D43) | G43: =IF(E43="","",E43/2) | H43: =IF(DATE(2025,1,1)>TODAY(),"",SUMIFS('2024'!$V$5:$V$178,'2024'!$AG$5:$AG$178,">="&DATE(2025,1,1),'2024'!$AG$5:$AG$178,"<"&EDATE(DATE(2025,1,1),1))) | I43: =IF(N(D43)=0,"",(SUMIFS('2024'!$AH$5:$AH$178,'2024'!$AG$5:$AG$178,">="&DATE(2025,1,1),'2024'!$AG$5:$AG$178,"<"&EDATE(DATE(2025,1,1),1)))/D43) | J43: =IF(N(D43)=0,"",(SUMIFS('2024'!$AI$5:$AI$178,'2024'!$AG$5:$AG$178,">="&DATE(2025,1,1),'2024'!$AG$5:$AG$178,"<"&EDATE(DATE(2025,1,1),1)))/D43)
B44: =IF(DATE(2025,2,1)>TODAY(),"",DATE(2025,2,1)) | C44: =IF(DATE(2025,2,1)>TODAY(),"",COUNTIFS('2024'!$AD$5:$AD$178,">="&DATE(2025,2,1),'2024'!$AD$5:$AD$178,"<"&EDATE(DATE(2025,2,1),1))) | D44: =IF(DATE(2025,2,1)>TODAY(),"",COUNTIFS('2024'!$AG$5:$AG$178,">="&DATE(2025,2,1),'2024'!$AG$5:$AG$178,"<"&EDATE(DATE(2025,2,1),1))) | E44: =IF(DATE(2025,2,1)>TODAY(),"",SUMIFS('2024'!$X$5:$X$178,'2024'!$AG$5:$AG$178,">="&DATE(2025,2,1),'2024'!$AG$5:$AG$178,"<"&EDATE(DATE(2025,2,1),1))) | F44: =IF(N(D44)=0,"",E44/D44) | G44: =IF(E44="","",E44/2) | H44: =IF(DATE(2025,2,1)>TODAY(),"",SUMIFS('2024'!$V$5:$V$178,'2024'!$AG$5:$AG$178,">="&DATE(2025,2,1),'2024'!$AG$5:$AG$178,"<"&EDATE(DATE(2025,2,1),1))) | I44: =IF(N(D44)=0,"",(SUMIFS('2024'!$AH$5:$AH$178,'2024'!$AG$5:$AG$178,">="&DATE(2025,2,1),'2024'!$AG$5:$AG$178,"<"&EDATE(DATE(2025,2,1),1)))/D44) | J44: =IF(N(D44)=0,"",(SUMIFS('2024'!$AI$5:$AI$178,'2024'!$AG$5:$AG$178,">="&DATE(2025,2,1),'2024'!$AG$5:$AG$178,"<"&EDATE(DATE(2025,2,1),1)))/D44)
B45: =IF(DATE(2025,3,1)>TODAY(),"",DATE(2025,3,1)) | C45: =IF(DATE(2025,3,1)>TODAY(),"",COUNTIFS('2024'!$AD$5:$AD$178,">="&DATE(2025,3,1),'2024'!$AD$5:$AD$178,"<"&EDATE(DATE(2025,3,1),1))) | D45: =IF(DATE(2025,3,1)>TODAY(),"",COUNTIFS('2024'!$AG$5:$AG$178,">="&DATE(2025,3,1),'2024'!$AG$5:$AG$178,"<"&EDATE(DATE(2025,3,1),1))) | E45: =IF(DATE(2025,3,1)>TODAY(),"",SUMIFS('2024'!$X$5:$X$178,'2024'!$AG$5:$AG$178,">="&DATE(2025,3,1),'2024'!$AG$5:$AG$178,"<"&EDATE(DATE(2025,3,1),1))) | F45: =IF(N(D45)=0,"",E45/D45) | G45: =IF(E45="","",E45/2) | H45: =IF(DATE(2025,3,1)>TODAY(),"",SUMIFS('2024'!$V$5:$V$178,'2024'!$AG$5:$AG$178,">="&DATE(2025,3,1),'2024'!$AG$5:$AG$178,"<"&EDATE(DATE(2025,3,1),1))) | I45: =IF(N(D45)=0,"",(SUMIFS('2024'!$AH$5:$AH$178,'2024'!$AG$5:$AG$178,">="&DATE(2025,3,1),'2024'!$AG$5:$AG$178,"<"&EDATE(DATE(2025,3,1),1)))/D45) | J45: =IF(N(D45)=0,"",(SUMIFS('2024'!$AI$5:$AI$178,'2024'!$AG$5:$AG$178,">="&DATE(2025,3,1),'2024'!$AG$5:$AG$178,"<"&EDATE(DATE(2025,3,1),1)))/D45)
B46: =IF(DATE(2025,4,1)>TODAY(),"",DATE(2025,4,1)) | C46: =IF(DATE(2025,4,1)>TODAY(),"",COUNTIFS('2024'!$AD$5:$AD$178,">="&DATE(2025,4,1),'2024'!$AD$5:$AD$178,"<"&EDATE(DATE(2025,4,1),1))) | D46: =IF(DATE(2025,4,1)>TODAY(),"",COUNTIFS('2024'!$AG$5:$AG$178,">="&DATE(2025,4,1),'2024'!$AG$5:$AG$178,"<"&EDATE(DATE(2025,4,1),1))) | E46: =IF(DATE(2025,4,1)>TODAY(),"",SUMIFS('2024'!$X$5:$X$178,'2024'!$AG$5:$AG$178,">="&DATE(2025,4,1),'2024'!$AG$5:$AG$178,"<"&EDATE(DATE(2025,4,1),1))) | F46: =IF(N(D46)=0,"",E46/D46) | G46: =IF(E46="","",E46/2) | H46: =IF(DATE(2025,4,1)>TODAY(),"",SUMIFS('2024'!$V$5:$V$178,'2024'!$AG$5:$AG$178,">="&DATE(2025,4,1),'2024'!$AG$5:$AG$178,"<"&EDATE(DATE(2025,4,1),1))) | I46: =IF(N(D46)=0,"",(SUMIFS('2024'!$AH$5:$AH$178,'2024'!$AG$5:$AG$178,">="&DATE(2025,4,1),'2024'!$AG$5:$AG$178,"<"&EDATE(DATE(2025,4,1),1)))/D46) | J46: =IF(N(D46)=0,"",(SUMIFS('2024'!$AI$5:$AI$178,'2024'!$AG$5:$AG$178,">="&DATE(2025,4,1),'2024'!$AG$5:$AG$178,"<"&EDATE(DATE(2025,4,1),1)))/D46)
B47: =IF(DATE(2025,5,1)>TODAY(),"",DATE(2025,5,1)) | C47: =IF(DATE(2025,5,1)>TODAY(),"",COUNTIFS('2024'!$AD$5:$AD$178,">="&DATE(2025,5,1),'2024'!$AD$5:$AD$178,"<"&EDATE(DATE(2025,5,1),1))) | D47: =IF(DATE(2025,5,1)>TODAY(),"",COUNTIFS('2024'!$AG$5:$AG$178,">="&DATE(2025,5,1),'2024'!$AG$5:$AG$178,"<"&EDATE(DATE(2025,5,1),1))) | E47: =IF(DATE(2025,5,1)>TODAY(),"",SUMIFS('2024'!$X$5:$X$178,'2024'!$AG$5:$AG$178,">="&DATE(2025,5,1),'2024'!$AG$5:$AG$178,"<"&EDATE(DATE(2025,5,1),1))) | F47: =IF(N(D47)=0,"",E47/D47) | G47: =IF(E47="","",E47/2) | H47: =IF(DATE(2025,5,1)>TODAY(),"",SUMIFS('2024'!$V$5:$V$178,'2024'!$AG$5:$AG$178,">="&DATE(2025,5,1),'2024'!$AG$5:$AG$178,"<"&EDATE(DATE(2025,5,1),1))) | I47: =IF(N(D47)=0,"",(SUMIFS('2024'!$AH$5:$AH$178,'2024'!$AG$5:$AG$178,">="&DATE(2025,5,1),'2024'!$AG$5:$AG$178,"<"&EDATE(DATE(2025,5,1),1)))/D47) | J47: =IF(N(D47)=0,"",(SUMIFS('2024'!$AI$5:$AI$178,'2024'!$AG$5:$AG$178,">="&DATE(2025,5,1),'2024'!$AG$5:$AG$178,"<"&EDATE(DATE(2025,5,1),1)))/D47)
B48: =IF(DATE(2025,6,1)>TODAY(),"",DATE(2025,6,1)) | C48: =IF(DATE(2025,6,1)>TODAY(),"",COUNTIFS('2024'!$AD$5:$AD$178,">="&DATE(2025,6,1),'2024'!$AD$5:$AD$178,"<"&EDATE(DATE(2025,6,1),1))) | D48: =IF(DATE(2025,6,1)>TODAY(),"",COUNTIFS('2024'!$AG$5:$AG$178,">="&DATE(2025,6,1),'2024'!$AG$5:$AG$178,"<"&EDATE(DATE(2025,6,1),1))) | E48: =IF(DATE(2025,6,1)>TODAY(),"",SUMIFS('2024'!$X$5:$X$178,'2024'!$AG$5:$AG$178,">="&DATE(2025,6,1),'2024'!$AG$5:$AG$178,"<"&EDATE(DATE(2025,6,1),1))) | F48: =IF(N(D48)=0,"",E48/D48) | G48: =IF(E48="","",E48/2) | H48: =IF(DATE(2025,6,1)>TODAY(),"",SUMIFS('2024'!$V$5:$V$178,'2024'!$AG$5:$AG$178,">="&DATE(2025,6,1),'2024'!$AG$5:$AG$178,"<"&EDATE(DATE(2025,6,1),1))) | I48: =IF(N(D48)=0,"",(SUMIFS('2024'!$AH$5:$AH$178,'2024'!$AG$5:$AG$178,">="&DATE(2025,6,1),'2024'!$AG$5:$AG$178,"<"&EDATE(DATE(2025,6,1),1)))/D48) | J48: =IF(N(D48)=0,"",(SUMIFS('2024'!$AI$5:$AI$178,'2024'!$AG$5:$AG$178,">="&DATE(2025,6,1),'2024'!$AG$5:$AG$178,"<"&EDATE(DATE(2025,6,1),1)))/D48)
B49: =IF(DATE(2025,7,1)>TODAY(),"",DATE(2025,7,1)) | C49: =IF(DATE(2025,7,1)>TODAY(),"",COUNTIFS('2024'!$AD$5:$AD$178,">="&DATE(2025,7,1),'2024'!$AD$5:$AD$178,"<"&EDATE(DATE(2025,7,1),1))) | D49: =IF(DATE(2025,7,1)>TODAY(),"",COUNTIFS('2024'!$AG$5:$AG$178,">="&DATE(2025,7,1),'2024'!$AG$5:$AG$178,"<"&EDATE(DATE(2025,7,1),1))) | E49: =IF(DATE(2025,7,1)>TODAY(),"",SUMIFS('2024'!$X$5:$X$178,'2024'!$AG$5:$AG$178,">="&DATE(2025,7,1),'2024'!$AG$5:$AG$178,"<"&EDATE(DATE(2025,7,1),1))) | F49: =IF(N(D49)=0,"",E49/D49) | G49: =IF(E49="","",E49/2) | H49: =IF(DATE(2025,7,1)>TODAY(),"",SUMIFS('2024'!$V$5:$V$178,'2024'!$AG$5:$AG$178,">="&DATE(2025,7,1),'2024'!$AG$5:$AG$178,"<"&EDATE(DATE(2025,7,1),1))) | I49: =IF(N(D49)=0,"",(SUMIFS('2024'!$AH$5:$AH$178,'2024'!$AG$5:$AG$178,">="&DATE(2025,7,1),'2024'!$AG$5:$AG$178,"<"&EDATE(DATE(2025,7,1),1)))/D49) | J49: =IF(N(D49)=0,"",(SUMIFS('2024'!$AI$5:$AI$178,'2024'!$AG$5:$AG$178,">="&DATE(2025,7,1),'2024'!$AG$5:$AG$178,"<"&EDATE(DATE(2025,7,1),1)))/D49)
B50: =IF(DATE(2025,8,1)>TODAY(),"",DATE(2025,8,1)) | C50: =IF(DATE(2025,8,1)>TODAY(),"",COUNTIFS('2024'!$AD$5:$AD$178,">="&DATE(2025,8,1),'2024'!$AD$5:$AD$178,"<"&EDATE(DATE(2025,8,1),1))) | D50: =IF(DATE(2025,8,1)>TODAY(),"",COUNTIFS('2024'!$AG$5:$AG$178,">="&DATE(2025,8,1),'2024'!$AG$5:$AG$178,"<"&EDATE(DATE(2025,8,1),1))) | E50: =IF(DATE(2025,8,1)>TODAY(),"",SUMIFS('2024'!$X$5:$X$178,'2024'!$AG$5:$AG$178,">="&DATE(2025,8,1),'2024'!$AG$5:$AG$178,"<"&EDATE(DATE(2025,8,1),1))) | F50: =IF(N(D50)=0,"",E50/D50) | G50: =IF(E50="","",E50/2) | H50: =IF(DATE(2025,8,1)>TODAY(),"",SUMIFS('2024'!$V$5:$V$178,'2024'!$AG$5:$AG$178,">="&DATE(2025,8,1),'2024'!$AG$5:$AG$178,"<"&EDATE(DATE(2025,8,1),1))) | I50: =IF(N(D50)=0,"",(SUMIFS('2024'!$AH$5:$AH$178,'2024'!$AG$5:$AG$178,">="&DATE(2025,8,1),'2024'!$AG$5:$AG$178,"<"&EDATE(DATE(2025,8,1),1)))/D50) | J50: =IF(N(D50)=0,"",(SUMIFS('2024'!$AI$5:$AI$178,'2024'!$AG$5:$AG$178,">="&DATE(2025,8,1),'2024'!$AG$5:$AG$178,"<"&EDATE(DATE(2025,8,1),1)))/D50)
B51: =IF(DATE(2025,9,1)>TODAY(),"",DATE(2025,9,1)) | C51: =IF(DATE(2025,9,1)>TODAY(),"",COUNTIFS('2024'!$AD$5:$AD$178,">="&DATE(2025,9,1),'2024'!$AD$5:$AD$178,"<"&EDATE(DATE(2025,9,1),1))) | D51: =IF(DATE(2025,9,1)>TODAY(),"",COUNTIFS('2024'!$AG$5:$AG$178,">="&DATE(2025,9,1),'2024'!$AG$5:$AG$178,"<"&EDATE(DATE(2025,9,1),1))) | E51: =IF(DATE(2025,9,1)>TODAY(),"",SUMIFS('2024'!$X$5:$X$178,'2024'!$AG$5:$AG$178,">="&DATE(2025,9,1),'2024'!$AG$5:$AG$178,"<"&EDATE(DATE(2025,9,1),1))) | F51: =IF(N(D51)=0,"",E51/D51) | G51: =IF(E51="","",E51/2) | H51: =IF(DATE(2025,9,1)>TODAY(),"",SUMIFS('2024'!$V$5:$V$178,'2024'!$AG$5:$AG$178,">="&DATE(2025,9,1),'2024'!$AG$5:$AG$178,"<"&EDATE(DATE(2025,9,1),1))) | I51: =IF(N(D51)=0,"",(SUMIFS('2024'!$AH$5:$AH$178,'2024'!$AG$5:$AG$178,">="&DATE(2025,9,1),'2024'!$AG$5:$AG$178,"<"&EDATE(DATE(2025,9,1),1)))/D51) | J51: =IF(N(D51)=0,"",(SUMIFS('2024'!$AI$5:$AI$178,'2024'!$AG$5:$AG$178,">="&DATE(2025,9,1),'2024'!$AG$5:$AG$178,"<"&EDATE(DATE(2025,9,1),1)))/D51)
B52: =IF(DATE(2025,10,1)>TODAY(),"",DATE(2025,10,1)) | C52: =IF(DATE(2025,10,1)>TODAY(),"",COUNTIFS('2024'!$AD$5:$AD$178,">="&DATE(2025,10,1),'2024'!$AD$5:$AD$178,"<"&EDATE(DATE(2025,10,1),1))) | D52: =IF(DATE(2025,10,1)>TODAY(),"",COUNTIFS('2024'!$AG$5:$AG$178,">="&DATE(2025,10,1),'2024'!$AG$5:$AG$178,"<"&EDATE(DATE(2025,10,1),1))) | E52: =IF(DATE(2025,10,1)>TODAY(),"",SUMIFS('2024'!$X$5:$X$178,'2024'!$AG$5:$AG$178,">="&DATE(2025,10,1),'2024'!$AG$5:$AG$178,"<"&EDATE(DATE(2025,10,1),1))) | F52: =IF(N(D52)=0,"",E52/D52) | G52: =IF(E52="","",E52/2) | H52: =IF(DATE(2025,10,1)>TODAY(),"",SUMIFS('2024'!$V$5:$V$178,'2024'!$AG$5:$AG$178,">="&DATE(2025,10,1),'2024'!$AG$5:$AG$178,"<"&EDATE(DATE(2025,10,1),1))) | I52: =IF(N(D52)=0,"",(SUMIFS('2024'!$AH$5:$AH$178,'2024'!$AG$5:$AG$178,">="&DATE(2025,10,1),'2024'!$AG$5:$AG$178,"<"&EDATE(DATE(2025,10,1),1)))/D52) | J52: =IF(N(D52)=0,"",(SUMIFS('2024'!$AI$5:$AI$178,'2024'!$AG$5:$AG$178,">="&DATE(2025,10,1),'2024'!$AG$5:$AG$178,"<"&EDATE(DATE(2025,10,1),1)))/D52)
B53: =IF(DATE(2025,11,1)>TODAY(),"",DATE(2025,11,1)) | C53: =IF(DATE(2025,11,1)>TODAY(),"",COUNTIFS('2024'!$AD$5:$AD$178,">="&DATE(2025,11,1),'2024'!$AD$5:$AD$178,"<"&EDATE(DATE(2025,11,1),1))) | D53: =IF(DATE(2025,11,1)>TODAY(),"",COUNTIFS('2024'!$AG$5:$AG$178,">="&DATE(2025,11,1),'2024'!$AG$5:$AG$178,"<"&EDATE(DATE(2025,11,1),1))) | E53: =IF(DATE(2025,11,1)>TODAY(),"",SUMIFS('2024'!$X$5:$X$178,'2024'!$AG$5:$AG$178,">="&DATE(2025,11,1),'2024'!$AG$5:$AG$178,"<"&EDATE(DATE(2025,11,1),1))) | F53: =IF(N(D53)=0,"",E53/D53) | G53: =IF(E53="","",E53/2) | H53: =IF(DATE(2025,11,1)>TODAY(),"",SUMIFS('2024'!$V$5:$V$178,'2024'!$AG$5:$AG$178,">="&DATE(2025,11,1),'2024'!$AG$5:$AG$178,"<"&EDATE(DATE(2025,11,1),1))) | I53: =IF(N(D53)=0,"",(SUMIFS('2024'!$AH$5:$AH$178,'2024'!$AG$5:$AG$178,">="&DATE(2025,11,1),'2024'!$AG$5:$AG$178,"<"&EDATE(DATE(2025,11,1),1)))/D53) | J53: =IF(N(D53)=0,"",(SUMIFS('2024'!$AI$5:$AI$178,'2024'!$AG$5:$AG$178,">="&DATE(2025,11,1),'2024'!$AG$5:$AG$178,"<"&EDATE(DATE(2025,11,1),1)))/D53)
B54: =IF(DATE(2025,12,1)>TODAY(),"",DATE(2025,12,1)) | C54: =IF(DATE(2025,12,1)>TODAY(),"",COUNTIFS('2024'!$AD$5:$AD$178,">="&DATE(2025,12,1),'2024'!$AD$5:$AD$178,"<"&EDATE(DATE(2025,12,1),1))) | D54: =IF(DATE(2025,12,1)>TODAY(),"",COUNTIFS('2024'!$AG$5:$AG$178,">="&DATE(2025,12,1),'2024'!$AG$5:$AG$178,"<"&EDATE(DATE(2025,12,1),1))) | E54: =IF(DATE(2025,12,1)>TODAY(),"",SUMIFS('2024'!$X$5:$X$178,'2024'!$AG$5:$AG$178,">="&DATE(2025,12,1),'2024'!$AG$5:$AG$178,"<"&EDATE(DATE(2025,12,1),1))) | F54: =IF(N(D54)=0,"",E54/D54) | G54: =IF(E54="","",E54/2) | H54: =IF(DATE(2025,12,1)>TODAY(),"",SUMIFS('2024'!$V$5:$V$178,'2024'!$AG$5:$AG$178,">="&DATE(2025,12,1),'2024'!$AG$5:$AG$178,"<"&EDATE(DATE(2025,12,1),1))) | I54: =IF(N(D54)=0,"",(SUMIFS('2024'!$AH$5:$AH$178,'2024'!$AG$5:$AG$178,">="&DATE(2025,12,1),'2024'!$AG$5:$AG$178,"<"&EDATE(DATE(2025,12,1),1)))/D54) | J54: =IF(N(D54)=0,"",(SUMIFS('2024'!$AI$5:$AI$178,'2024'!$AG$5:$AG$178,">="&DATE(2025,12,1),'2024'!$AG$5:$AG$178,"<"&EDATE(DATE(2025,12,1),1)))/D54)
B55: =IF(DATE(2026,1,1)>TODAY(),"",DATE(2026,1,1)) | C55: =IF(DATE(2026,1,1)>TODAY(),"",COUNTIFS('2024'!$AD$5:$AD$178,">="&DATE(2026,1,1),'2024'!$AD$5:$AD$178,"<"&EDATE(DATE(2026,1,1),1))) | D55: =IF(DATE(2026,1,1)>TODAY(),"",COUNTIFS('2024'!$AG$5:$AG$178,">="&DATE(2026,1,1),'2024'!$AG$5:$AG$178,"<"&EDATE(DATE(2026,1,1),1))) | E55: =IF(DATE(2026,1,1)>TODAY(),"",SUMIFS('2024'!$X$5:$X$178,'2024'!$AG$5:$AG$178,">="&DATE(2026,1,1),'2024'!$AG$5:$AG$178,"<"&EDATE(DATE(2026,1,1),1))) | F55: =IF(N(D55)=0,"",E55/D55) | G55: =IF(E55="","",E55/2) | H55: =IF(DATE(2026,1,1)>TODAY(),"",SUMIFS('2024'!$V$5:$V$178,'2024'!$AG$5:$AG$178,">="&DATE(2026,1,1),'2024'!$AG$5:$AG$178,"<"&EDATE(DATE(2026,1,1),1))) | I55: =IF(N(D55)=0,"",(SUMIFS('2024'!$AH$5:$AH$178,'2024'!$AG$5:$AG$178,">="&DATE(2026,1,1),'2024'!$AG$5:$AG$178,"<"&EDATE(DATE(2026,1,1),1)))/D55) | J55: =IF(N(D55)=0,"",(SUMIFS('2024'!$AI$5:$AI$178,'2024'!$AG$5:$AG$178,">="&DATE(2026,1,1),'2024'!$AG$5:$AG$178,"<"&EDATE(DATE(2026,1,1),1)))/D55)
B56: =IF(DATE(2026,2,1)>TODAY(),"",DATE(2026,2,1)) | C56: =IF(DATE(2026,2,1)>TODAY(),"",COUNTIFS('2024'!$AD$5:$AD$178,">="&DATE(2026,2,1),'2024'!$AD$5:$AD$178,"<"&EDATE(DATE(2026,2,1),1))) | D56: =IF(DATE(2026,2,1)>TODAY(),"",COUNTIFS('2024'!$AG$5:$AG$178,">="&DATE(2026,2,1),'2024'!$AG$5:$AG$178,"<"&EDATE(DATE(2026,2,1),1))) | E56: =IF(DATE(2026,2,1)>TODAY(),"",SUMIFS('2024'!$X$5:$X$178,'2024'!$AG$5:$AG$178,">="&DATE(2026,2,1),'2024'!$AG$5:$AG$178,"<"&EDATE(DATE(2026,2,1),1))) | F56: =IF(N(D56)=0,"",E56/D56) | G56: =IF(E56="","",E56/2) | H56: =IF(DATE(2026,2,1)>TODAY(),"",SUMIFS('2024'!$V$5:$V$178,'2024'!$AG$5:$AG$178,">="&DATE(2026,2,1),'2024'!$AG$5:$AG$178,"<"&EDATE(DATE(2026,2,1),1))) | I56: =IF(N(D56)=0,"",(SUMIFS('2024'!$AH$5:$AH$178,'2024'!$AG$5:$AG$178,">="&DATE(2026,2,1),'2024'!$AG$5:$AG$178,"<"&EDATE(DATE(2026,2,1),1)))/D56) | J56: =IF(N(D56)=0,"",(SUMIFS('2024'!$AI$5:$AI$178,'2024'!$AG$5:$AG$178,">="&DATE(2026,2,1),'2024'!$AG$5:$AG$178,"<"&EDATE(DATE(2026,2,1),1)))/D56)
B57: =IF(DATE(2026,3,1)>TODAY(),"",DATE(2026,3,1)) | C57: =IF(DATE(2026,3,1)>TODAY(),"",COUNTIFS('2024'!$AD$5:$AD$178,">="&DATE(2026,3,1),'2024'!$AD$5:$AD$178,"<"&EDATE(DATE(2026,3,1),1))) | D57: =IF(DATE(2026,3,1)>TODAY(),"",COUNTIFS('2024'!$AG$5:$AG$178,">="&DATE(2026,3,1),'2024'!$AG$5:$AG$178,"<"&EDATE(DATE(2026,3,1),1))) | E57: =IF(DATE(2026,3,1)>TODAY(),"",SUMIFS('2024'!$X$5:$X$178,'2024'!$AG$5:$AG$178,">="&DATE(2026,3,1),'2024'!$AG$5:$AG$178,"<"&EDATE(DATE(2026,3,1),1))) | F57: =IF(N(D57)=0,"",E57/D57) | G57: =IF(E57="","",E57/2) | H57: =IF(DATE(2026,3,1)>TODAY(),"",SUMIFS('2024'!$V$5:$V$178,'2024'!$AG$5:$AG$178,">="&DATE(2026,3,1),'2024'!$AG$5:$AG$178,"<"&EDATE(DATE(2026,3,1),1))) | I57: =IF(N(D57)=0,"",(SUMIFS('2024'!$AH$5:$AH$178,'2024'!$AG$5:$AG$178,">="&DATE(2026,3,1),'2024'!$AG$5:$AG$178,"<"&EDATE(DATE(2026,3,1),1)))/D57) | J57: =IF(N(D57)=0,"",(SUMIFS('2024'!$AI$5:$AI$178,'2024'!$AG$5:$AG$178,">="&DATE(2026,3,1),'2024'!$AG$5:$AG$178,"<"&EDATE(DATE(2026,3,1),1)))/D57)
B58: =IF(DATE(2026,4,1)>TODAY(),"",DATE(2026,4,1)) | C58: =IF(DATE(2026,4,1)>TODAY(),"",COUNTIFS('2024'!$AD$5:$AD$178,">="&DATE(2026,4,1),'2024'!$AD$5:$AD$178,"<"&EDATE(DATE(2026,4,1),1))) | D58: =IF(DATE(2026,4,1)>TODAY(),"",COUNTIFS('2024'!$AG$5:$AG$178,">="&DATE(2026,4,1),'2024'!$AG$5:$AG$178,"<"&EDATE(DATE(2026,4,1),1))) | E58: =IF(DATE(2026,4,1)>TODAY(),"",SUMIFS('2024'!$X$5:$X$178,'2024'!$AG$5:$AG$178,">="&DATE(2026,4,1),'2024'!$AG$5:$AG$178,"<"&EDATE(DATE(2026,4,1),1))) | F58: =IF(N(D58)=0,"",E58/D58) | G58: =IF(E58="","",E58/2) | H58: =IF(DATE(2026,4,1)>TODAY(),"",SUMIFS('2024'!$V$5:$V$178,'2024'!$AG$5:$AG$178,">="&DATE(2026,4,1),'2024'!$AG$5:$AG$178,"<"&EDATE(DATE(2026,4,1),1))) | I58: =IF(N(D58)=0,"",(SUMIFS('2024'!$AH$5:$AH$178,'2024'!$AG$5:$AG$178,">="&DATE(2026,4,1),'2024'!$AG$5:$AG$178,"<"&EDATE(DATE(2026,4,1),1)))/D58) | J58: =IF(N(D58)=0,"",(SUMIFS('2024'!$AI$5:$AI$178,'2024'!$AG$5:$AG$178,">="&DATE(2026,4,1),'2024'!$AG$5:$AG$178,"<"&EDATE(DATE(2026,4,1),1)))/D58)
B59: =IF(DATE(2026,5,1)>TODAY(),"",DATE(2026,5,1)) | C59: =IF(DATE(2026,5,1)>TODAY(),"",COUNTIFS('2024'!$AD$5:$AD$178,">="&DATE(2026,5,1),'2024'!$AD$5:$AD$178,"<"&EDATE(DATE(2026,5,1),1))) | D59: =IF(DATE(2026,5,1)>TODAY(),"",COUNTIFS('2024'!$AG$5:$AG$178,">="&DATE(2026,5,1),'2024'!$AG$5:$AG$178,"<"&EDATE(DATE(2026,5,1),1))) | E59: =IF(DATE(2026,5,1)>TODAY(),"",SUMIFS('2024'!$X$5:$X$178,'2024'!$AG$5:$AG$178,">="&DATE(2026,5,1),'2024'!$AG$5:$AG$178,"<"&EDATE(DATE(2026,5,1),1))) | F59: =IF(N(D59)=0,"",E59/D59) | G59: =IF(E59="","",E59/2) | H59: =IF(DATE(2026,5,1)>TODAY(),"",SUMIFS('2024'!$V$5:$V$178,'2024'!$AG$5:$AG$178,">="&DATE(2026,5,1),'2024'!$AG$5:$AG$178,"<"&EDATE(DATE(2026,5,1),1))) | I59: =IF(N(D59)=0,"",(SUMIFS('2024'!$AH$5:$AH$178,'2024'!$AG$5:$AG$178,">="&DATE(2026,5,1),'2024'!$AG$5:$AG$178,"<"&EDATE(DATE(2026,5,1),1)))/D59) | J59: =IF(N(D59)=0,"",(SUMIFS('2024'!$AI$5:$AI$178,'2024'!$AG$5:$AG$178,">="&DATE(2026,5,1),'2024'!$AG$5:$AG$178,"<"&EDATE(DATE(2026,5,1),1)))/D59)
B60: =IF(DATE(2026,6,1)>TODAY(),"",DATE(2026,6,1)) | C60: =IF(DATE(2026,6,1)>TODAY(),"",COUNTIFS('2024'!$AD$5:$AD$178,">="&DATE(2026,6,1),'2024'!$AD$5:$AD$178,"<"&EDATE(DATE(2026,6,1),1))) | D60: =IF(DATE(2026,6,1)>TODAY(),"",COUNTIFS('2024'!$AG$5:$AG$178,">="&DATE(2026,6,1),'2024'!$AG$5:$AG$178,"<"&EDATE(DATE(2026,6,1),1))) | E60: =IF(DATE(2026,6,1)>TODAY(),"",SUMIFS('2024'!$X$5:$X$178,'2024'!$AG$5:$AG$178,">="&DATE(2026,6,1),'2024'!$AG$5:$AG$178,"<"&EDATE(DATE(2026,6,1),1))) | F60: =IF(N(D60)=0,"",E60/D60) | G60: =IF(E60="","",E60/2) | H60: =IF(DATE(2026,6,1)>TODAY(),"",SUMIFS('2024'!$V$5:$V$178,'2024'!$AG$5:$AG$178,">="&DATE(2026,6,1),'2024'!$AG$5:$AG$178,"<"&EDATE(DATE(2026,6,1),1))) | I60: =IF(N(D60)=0,"",(SUMIFS('2024'!$AH$5:$AH$178,'2024'!$AG$5:$AG$178,">="&DATE(2026,6,1),'2024'!$AG$5:$AG$178,"<"&EDATE(DATE(2026,6,1),1)))/D60) | J60: =IF(N(D60)=0,"",(SUMIFS('2024'!$AI$5:$AI$178,'2024'!$AG$5:$AG$178,">="&DATE(2026,6,1),'2024'!$AG$5:$AG$178,"<"&EDATE(DATE(2026,6,1),1)))/D60)
B61: =IF(DATE(2026,7,1)>TODAY(),"",DATE(2026,7,1)) | C61: =IF(DATE(2026,7,1)>TODAY(),"",COUNTIFS('2024'!$AD$5:$AD$178,">="&DATE(2026,7,1),'2024'!$AD$5:$AD$178,"<"&EDATE(DATE(2026,7,1),1))) | D61: =IF(DATE(2026,7,1)>TODAY(),"",COUNTIFS('2024'!$AG$5:$AG$178,">="&DATE(2026,7,1),'2024'!$AG$5:$AG$178,"<"&EDATE(DATE(2026,7,1),1))) | E61: =IF(DATE(2026,7,1)>TODAY(),"",SUMIFS('2024'!$X$5:$X$178,'2024'!$AG$5:$AG$178,">="&DATE(2026,7,1),'2024'!$AG$5:$AG$178,"<"&EDATE(DATE(2026,7,1),1))) | F61: =IF(N(D61)=0,"",E61/D61) | G61: =IF(E61="","",E61/2) | H61: =IF(DATE(2026,7,1)>TODAY(),"",SUMIFS('2024'!$V$5:$V$178,'2024'!$AG$5:$AG$178,">="&DATE(2026,7,1),'2024'!$AG$5:$AG$178,"<"&EDATE(DATE(2026,7,1),1))) | I61: =IF(N(D61)=0,"",(SUMIFS('2024'!$AH$5:$AH$178,'2024'!$AG$5:$AG$178,">="&DATE(2026,7,1),'2024'!$AG$5:$AG$178,"<"&EDATE(DATE(2026,7,1),1)))/D61) | J61: =IF(N(D61)=0,"",(SUMIFS('2024'!$AI$5:$AI$178,'2024'!$AG$5:$AG$178,">="&DATE(2026,7,1),'2024'!$AG$5:$AG$178,"<"&EDATE(DATE(2026,7,1),1)))/D61)
B62: =IF(DATE(2026,8,1)>TODAY(),"",DATE(2026,8,1)) | C62: =IF(DATE(2026,8,1)>TODAY(),"",COUNTIFS('2024'!$AD$5:$AD$178,">="&DATE(2026,8,1),'2024'!$AD$5:$AD$178,"<"&EDATE(DATE(2026,8,1),1))) | D62: =IF(DATE(2026,8,1)>TODAY(),"",COUNTIFS('2024'!$AG$5:$AG$178,">="&DATE(2026,8,1),'2024'!$AG$5:$AG$178,"<"&EDATE(DATE(2026,8,1),1))) | E62: =IF(DATE(2026,8,1)>TODAY(),"",SUMIFS('2024'!$X$5:$X$178,'2024'!$AG$5:$AG$178,">="&DATE(2026,8,1),'2024'!$AG$5:$AG$178,"<"&EDATE(DATE(2026,8,1),1))) | F62: =IF(N(D62)=0,"",E62/D62) | G62: =IF(E62="","",E62/2) | H62: =IF(DATE(2026,8,1)>TODAY(),"",SUMIFS('2024'!$V$5:$V$178,'2024'!$AG$5:$AG$178,">="&DATE(2026,8,1),'2024'!$AG$5:$AG$178,"<"&EDATE(DATE(2026,8,1),1))) | I62: =IF(N(D62)=0,"",(SUMIFS('2024'!$AH$5:$AH$178,'2024'!$AG$5:$AG$178,">="&DATE(2026,8,1),'2024'!$AG$5:$AG$178,"<"&EDATE(DATE(2026,8,1),1)))/D62) | J62: =IF(N(D62)=0,"",(SUMIFS('2024'!$AI$5:$AI$178,'2024'!$AG$5:$AG$178,">="&DATE(2026,8,1),'2024'!$AG$5:$AG$178,"<"&EDATE(DATE(2026,8,1),1)))/D62)
B63: =IF(DATE(2026,9,1)>TODAY(),"",DATE(2026,9,1)) | C63: =IF(DATE(2026,9,1)>TODAY(),"",COUNTIFS('2024'!$AD$5:$AD$178,">="&DATE(2026,9,1),'2024'!$AD$5:$AD$178,"<"&EDATE(DATE(2026,9,1),1))) | D63: =IF(DATE(2026,9,1)>TODAY(),"",COUNTIFS('2024'!$AG$5:$AG$178,">="&DATE(2026,9,1),'2024'!$AG$5:$AG$178,"<"&EDATE(DATE(2026,9,1),1))) | E63: =IF(DATE(2026,9,1)>TODAY(),"",SUMIFS('2024'!$X$5:$X$178,'2024'!$AG$5:$AG$178,">="&DATE(2026,9,1),'2024'!$AG$5:$AG$178,"<"&EDATE(DATE(2026,9,1),1))) | F63: =IF(N(D63)=0,"",E63/D63) | G63: =IF(E63="","",E63/2) | H63: =IF(DATE(2026,9,1)>TODAY(),"",SUMIFS('2024'!$V$5:$V$178,'2024'!$AG$5:$AG$178,">="&DATE(2026,9,1),'2024'!$AG$5:$AG$178,"<"&EDATE(DATE(2026,9,1),1))) | I63: =IF(N(D63)=0,"",(SUMIFS('2024'!$AH$5:$AH$178,'2024'!$AG$5:$AG$178,">="&DATE(2026,9,1),'2024'!$AG$5:$AG$178,"<"&EDATE(DATE(2026,9,1),1)))/D63) | J63: =IF(N(D63)=0,"",(SUMIFS('2024'!$AI$5:$AI$178,'2024'!$AG$5:$AG$178,">="&DATE(2026,9,1),'2024'!$AG$5:$AG$178,"<"&EDATE(DATE(2026,9,1),1)))/D63)
B64: =IF(DATE(2026,10,1)>TODAY(),"",DATE(2026,10,1)) | C64: =IF(DATE(2026,10,1)>TODAY(),"",COUNTIFS('2024'!$AD$5:$AD$178,">="&DATE(2026,10,1),'2024'!$AD$5:$AD$178,"<"&EDATE(DATE(2026,10,1),1))) | D64: =IF(DATE(2026,10,1)>TODAY(),"",COUNTIFS('2024'!$AG$5:$AG$178,">="&DATE(2026,10,1),'2024'!$AG$5:$AG$178,"<"&EDATE(DATE(2026,10,1),1))) | E64: =IF(DATE(2026,10,1)>TODAY(),"",SUMIFS('2024'!$X$5:$X$178,'2024'!$AG$5:$AG$178,">="&DATE(2026,10,1),'2024'!$AG$5:$AG$178,"<"&EDATE(DATE(2026,10,1),1))) | F64: =IF(N(D64)=0,"",E64/D64) | G64: =IF(E64="","",E64/2) | H64: =IF(DATE(2026,10,1)>TODAY(),"",SUMIFS('2024'!$V$5:$V$178,'2024'!$AG$5:$AG$178,">="&DATE(2026,10,1),'2024'!$AG$5:$AG$178,"<"&EDATE(DATE(2026,10,1),1))) | I64: =IF(N(D64)=0,"",(SUMIFS('2024'!$AH$5:$AH$178,'2024'!$AG$5:$AG$178,">="&DATE(2026,10,1),'2024'!$AG$5:$AG$178,"<"&EDATE(DATE(2026,10,1),1)))/D64) | J64: =IF(N(D64)=0,"",(SUMIFS('2024'!$AI$5:$AI$178,'2024'!$AG$5:$AG$178,">="&DATE(2026,10,1),'2024'!$AG$5:$AG$178,"<"&EDATE(DATE(2026,10,1),1)))/D64)
B65: =IF(DATE(2026,11,1)>TODAY(),"",DATE(2026,11,1)) | C65: =IF(DATE(2026,11,1)>TODAY(),"",COUNTIFS('2024'!$AD$5:$AD$178,">="&DATE(2026,11,1),'2024'!$AD$5:$AD$178,"<"&EDATE(DATE(2026,11,1),1))) | D65: =IF(DATE(2026,11,1)>TODAY(),"",COUNTIFS('2024'!$AG$5:$AG$178,">="&DATE(2026,11,1),'2024'!$AG$5:$AG$178,"<"&EDATE(DATE(2026,11,1),1))) | E65: =IF(DATE(2026,11,1)>TODAY(),"",SUMIFS('2024'!$X$5:$X$178,'2024'!$AG$5:$AG$178,">="&DATE(2026,11,1),'2024'!$AG$5:$AG$178,"<"&EDATE(DATE(2026,11,1),1))) | F65: =IF(N(D65)=0,"",E65/D65) | G65: =IF(E65="","",E65/2) | H65: =IF(DATE(2026,11,1)>TODAY(),"",SUMIFS('2024'!$V$5:$V$178,'2024'!$AG$5:$AG$178,">="&DATE(2026,11,1),'2024'!$AG$5:$AG$178,"<"&EDATE(DATE(2026,11,1),1))) | I65: =IF(N(D65)=0,"",(SUMIFS('2024'!$AH$5:$AH$178,'2024'!$AG$5:$AG$178,">="&DATE(2026,11,1),'2024'!$AG$5:$AG$178,"<"&EDATE(DATE(2026,11,1),1)))/D65) | J65: =IF(N(D65)=0,"",(SUMIFS('2024'!$AI$5:$AI$178,'2024'!$AG$5:$AG$178,">="&DATE(2026,11,1),'2024'!$AG$5:$AG$178,"<"&EDATE(DATE(2026,11,1),1)))/D65)
B66: =IF(DATE(2026,12,1)>TODAY(),"",DATE(2026,12,1)) | C66: =IF(DATE(2026,12,1)>TODAY(),"",COUNTIFS('2024'!$AD$5:$AD$178,">="&DATE(2026,12,1),'2024'!$AD$5:$AD$178,"<"&EDATE(DATE(2026,12,1),1))) | D66: =IF(DATE(2026,12,1)>TODAY(),"",COUNTIFS('2024'!$AG$5:$AG$178,">="&DATE(2026,12,1),'2024'!$AG$5:$AG$178,"<"&EDATE(DATE(2026,12,1),1))) | E66: =IF(DATE(2026,12,1)>TODAY(),"",SUMIFS('2024'!$X$5:$X$178,'2024'!$AG$5:$AG$178,">="&DATE(2026,12,1),'2024'!$AG$5:$AG$178,"<"&EDATE(DATE(2026,12,1),1))) | F66: =IF(N(D66)=0,"",E66/D66) | G66: =IF(E66="","",E66/2) | H66: =IF(DATE(2026,12,1)>TODAY(),"",SUMIFS('2024'!$V$5:$V$178,'2024'!$AG$5:$AG$178,">="&DATE(2026,12,1),'2024'!$AG$5:$AG$178,"<"&EDATE(DATE(2026,12,1),1))) | I66: =IF(N(D66)=0,"",(SUMIFS('2024'!$AH$5:$AH$178,'2024'!$AG$5:$AG$178,">="&DATE(2026,12,1),'2024'!$AG$5:$AG$178,"<"&EDATE(DATE(2026,12,1),1)))/D66) | J66: =IF(N(D66)=0,"",(SUMIFS('2024'!$AI$5:$AI$178,'2024'!$AG$5:$AG$178,">="&DATE(2026,12,1),'2024'!$AG$5:$AG$178,"<"&EDATE(DATE(2026,12,1),1)))/D66)
B67: =IF(DATE(2027,1,1)>TODAY(),"",DATE(2027,1,1)) | C67: =IF(DATE(2027,1,1)>TODAY(),"",COUNTIFS('2024'!$AD$5:$AD$178,">="&DATE(2027,1,1),'2024'!$AD$5:$AD$178,"<"&EDATE(DATE(2027,1,1),1))) | D67: =IF(DATE(2027,1,1)>TODAY(),"",COUNTIFS('2024'!$AG$5:$AG$178,">="&DATE(2027,1,1),'2024'!$AG$5:$AG$178,"<"&EDATE(DATE(2027,1,1),1))) | E67: =IF(DATE(2027,1,1)>TODAY(),"",SUMIFS('2024'!$X$5:$X$178,'2024'!$AG$5:$AG$178,">="&DATE(2027,1,1),'2024'!$AG$5:$AG$178,"<"&EDATE(DATE(2027,1,1),1))) | F67: =IF(N(D67)=0,"",E67/D67) | G67: =IF(E67="","",E67/2) | H67: =IF(DATE(2027,1,1)>TODAY(),"",SUMIFS('2024'!$V$5:$V$178,'2024'!$AG$5:$AG$178,">="&DATE(2027,1,1),'2024'!$AG$5:$AG$178,"<"&EDATE(DATE(2027,1,1),1))) | I67: =IF(N(D67)=0,"",(SUMIFS('2024'!$AH$5:$AH$178,'2024'!$AG$5:$AG$178,">="&DATE(2027,1,1),'2024'!$AG$5:$AG$178,"<"&EDATE(DATE(2027,1,1),1)))/D67) | J67: =IF(N(D67)=0,"",(SUMIFS('2024'!$AI$5:$AI$178,'2024'!$AG$5:$AG$178,">="&DATE(2027,1,1),'2024'!$AG$5:$AG$178,"<"&EDATE(DATE(2027,1,1),1)))/D67)
B68: =IF(DATE(2027,2,1)>TODAY(),"",DATE(2027,2,1)) | C68: =IF(DATE(2027,2,1)>TODAY(),"",COUNTIFS('2024'!$AD$5:$AD$178,">="&DATE(2027,2,1),'2024'!$AD$5:$AD$178,"<"&EDATE(DATE(2027,2,1),1))) | D68: =IF(DATE(2027,2,1)>TODAY(),"",COUNTIFS('2024'!$AG$5:$AG$178,">="&DATE(2027,2,1),'2024'!$AG$5:$AG$178,"<"&EDATE(DATE(2027,2,1),1))) | E68: =IF(DATE(2027,2,1)>TODAY(),"",SUMIFS('2024'!$X$5:$X$178,'2024'!$AG$5:$AG$178,">="&DATE(2027,2,1),'2024'!$AG$5:$AG$178,"<"&EDATE(DATE(2027,2,1),1))) | F68: =IF(N(D68)=0,"",E68/D68) | G68: =IF(E68="","",E68/2) | H68: =IF(DATE(2027,2,1)>TODAY(),"",SUMIFS('2024'!$V$5:$V$178,'2024'!$AG$5:$AG$178,">="&DATE(2027,2,1),'2024'!$AG$5:$AG$178,"<"&EDATE(DATE(2027,2,1),1))) | I68: =IF(N(D68)=0,"",(SUMIFS('2024'!$AH$5:$AH$178,'2024'!$AG$5:$AG$178,">="&DATE(2027,2,1),'2024'!$AG$5:$AG$178,"<"&EDATE(DATE(2027,2,1),1)))/D68) | J68: =IF(N(D68)=0,"",(SUMIFS('2024'!$AI$5:$AI$178,'2024'!$AG$5:$AG$178,">="&DATE(2027,2,1),'2024'!$AG$5:$AG$178,"<"&EDATE(DATE(2027,2,1),1)))/D68)
B69: =IF(DATE(2027,3,1)>TODAY(),"",DATE(2027,3,1)) | C69: =IF(DATE(2027,3,1)>TODAY(),"",COUNTIFS('2024'!$AD$5:$AD$178,">="&DATE(2027,3,1),'2024'!$AD$5:$AD$178,"<"&EDATE(DATE(2027,3,1),1))) | D69: =IF(DATE(2027,3,1)>TODAY(),"",COUNTIFS('2024'!$AG$5:$AG$178,">="&DATE(2027,3,1),'2024'!$AG$5:$AG$178,"<"&EDATE(DATE(2027,3,1),1))) | E69: =IF(DATE(2027,3,1)>TODAY(),"",SUMIFS('2024'!$X$5:$X$178,'2024'!$AG$5:$AG$178,">="&DATE(2027,3,1),'2024'!$AG$5:$AG$178,"<"&EDATE(DATE(2027,3,1),1))) | F69: =IF(N(D69)=0,"",E69/D69) | G69: =IF(E69="","",E69/2) | H69: =IF(DATE(2027,3,1)>TODAY(),"",SUMIFS('2024'!$V$5:$V$178,'2024'!$AG$5:$AG$178,">="&DATE(2027,3,1),'2024'!$AG$5:$AG$178,"<"&EDATE(DATE(2027,3,1),1))) | I69: =IF(N(D69)=0,"",(SUMIFS('2024'!$AH$5:$AH$178,'2024'!$AG$5:$AG$178,">="&DATE(2027,3,1),'2024'!$AG$5:$AG$178,"<"&EDATE(DATE(2027,3,1),1)))/D69) | J69: =IF(N(D69)=0,"",(SUMIFS('2024'!$AI$5:$AI$178,'2024'!$AG$5:$AG$178,">="&DATE(2027,3,1),'2024'!$AG$5:$AG$178,"<"&EDATE(DATE(2027,3,1),1)))/D69)
B70: =IF(DATE(2027,4,1)>TODAY(),"",DATE(2027,4,1)) | C70: =IF(DATE(2027,4,1)>TODAY(),"",COUNTIFS('2024'!$AD$5:$AD$178,">="&DATE(2027,4,1),'2024'!$AD$5:$AD$178,"<"&EDATE(DATE(2027,4,1),1))) | D70: =IF(DATE(2027,4,1)>TODAY(),"",COUNTIFS('2024'!$AG$5:$AG$178,">="&DATE(2027,4,1),'2024'!$AG$5:$AG$178,"<"&EDATE(DATE(2027,4,1),1))) | E70: =IF(DATE(2027,4,1)>TODAY(),"",SUMIFS('2024'!$X$5:$X$178,'2024'!$AG$5:$AG$178,">="&DATE(2027,4,1),'2024'!$AG$5:$AG$178,"<"&EDATE(DATE(2027,4,1),1))) | F70: =IF(N(D70)=0,"",E70/D70) | G70: =IF(E70="","",E70/2) | H70: =IF(DATE(2027,4,1)>TODAY(),"",SUMIFS('2024'!$V$5:$V$178,'2024'!$AG$5:$AG$178,">="&DATE(2027,4,1),'2024'!$AG$5:$AG$178,"<"&EDATE(DATE(2027,4,1),1))) | I70: =IF(N(D70)=0,"",(SUMIFS('2024'!$AH$5:$AH$178,'2024'!$AG$5:$AG$178,">="&DATE(2027,4,1),'2024'!$AG$5:$AG$178,"<"&EDATE(DATE(2027,4,1),1)))/D70) | J70: =IF(N(D70)=0,"",(SUMIFS('2024'!$AI$5:$AI$178,'2024'!$AG$5:$AG$178,">="&DATE(2027,4,1),'2024'!$AG$5:$AG$178,"<"&EDATE(DATE(2027,4,1),1)))/D70)
B71: =IF(DATE(2027,5,1)>TODAY(),"",DATE(2027,5,1)) | C71: =IF(DATE(2027,5,1)>TODAY(),"",COUNTIFS('2024'!$AD$5:$AD$178,">="&DATE(2027,5,1),'2024'!$AD$5:$AD$178,"<"&EDATE(DATE(2027,5,1),1))) | D71: =IF(DATE(2027,5,1)>TODAY(),"",COUNTIFS('2024'!$AG$5:$AG$178,">="&DATE(2027,5,1),'2024'!$AG$5:$AG$178,"<"&EDATE(DATE(2027,5,1),1))) | E71: =IF(DATE(2027,5,1)>TODAY(),"",SUMIFS('2024'!$X$5:$X$178,'2024'!$AG$5:$AG$178,">="&DATE(2027,5,1),'2024'!$AG$5:$AG$178,"<"&EDATE(DATE(2027,5,1),1))) | F71: =IF(N(D71)=0,"",E71/D71) | G71: =IF(E71="","",E71/2) | H71: =IF(DATE(2027,5,1)>TODAY(),"",SUMIFS('2024'!$V$5:$V$178,'2024'!$AG$5:$AG$178,">="&DATE(2027,5,1),'2024'!$AG$5:$AG$178,"<"&EDATE(DATE(2027,5,1),1))) | I71: =IF(N(D71)=0,"",(SUMIFS('2024'!$AH$5:$AH$178,'2024'!$AG$5:$AG$178,">="&DATE(2027,5,1),'2024'!$AG$5:$AG$178,"<"&EDATE(DATE(2027,5,1),1)))/D71) | J71: =IF(N(D71)=0,"",(SUMIFS('2024'!$AI$5:$AI$178,'2024'!$AG$5:$AG$178,">="&DATE(2027,5,1),'2024'!$AG$5:$AG$178,"<"&EDATE(DATE(2027,5,1),1)))/D71)
B72: =IF(DATE(2027,6,1)>TODAY(),"",DATE(2027,6,1)) | C72: =IF(DATE(2027,6,1)>TODAY(),"",COUNTIFS('2024'!$AD$5:$AD$178,">="&DATE(2027,6,1),'2024'!$AD$5:$AD$178,"<"&EDATE(DATE(2027,6,1),1))) | D72: =IF(DATE(2027,6,1)>TODAY(),"",COUNTIFS('2024'!$AG$5:$AG$178,">="&DATE(2027,6,1),'2024'!$AG$5:$AG$178,"<"&EDATE(DATE(2027,6,1),1))) | E72: =IF(DATE(2027,6,1)>TODAY(),"",SUMIFS('2024'!$X$5:$X$178,'2024'!$AG$5:$AG$178,">="&DATE(2027,6,1),'2024'!$AG$5:$AG$178,"<"&EDATE(DATE(2027,6,1),1))) | F72: =IF(N(D72)=0,"",E72/D72) | G72: =IF(E72="","",E72/2) | H72: =IF(DATE(2027,6,1)>TODAY(),"",SUMIFS('2024'!$V$5:$V$178,'2024'!$AG$5:$AG$178,">="&DATE(2027,6,1),'2024'!$AG$5:$AG$178,"<"&EDATE(DATE(2027,6,1),1))) | I72: =IF(N(D72)=0,"",(SUMIFS('2024'!$AH$5:$AH$178,'2024'!$AG$5:$AG$178,">="&DATE(2027,6,1),'2024'!$AG$5:$AG$178,"<"&EDATE(DATE(2027,6,1),1)))/D72) | J72: =IF(N(D72)=0,"",(SUMIFS('2024'!$AI$5:$AI$178,'2024'!$AG$5:$AG$178,">="&DATE(2027,6,1),'2024'!$AG$5:$AG$178,"<"&EDATE(DATE(2027,6,1),1)))/D72)
B73: =IF(DATE(2027,7,1)>TODAY(),"",DATE(2027,7,1)) | C73: =IF(DATE(2027,7,1)>TODAY(),"",COUNTIFS('2024'!$AD$5:$AD$178,">="&DATE(2027,7,1),'2024'!$AD$5:$AD$178,"<"&EDATE(DATE(2027,7,1),1))) | D73: =IF(DATE(2027,7,1)>TODAY(),"",COUNTIFS('2024'!$AG$5:$AG$178,">="&DATE(2027,7,1),'2024'!$AG$5:$AG$178,"<"&EDATE(DATE(2027,7,1),1))) | E73: =IF(DATE(2027,7,1)>TODAY(),"",SUMIFS('2024'!$X$5:$X$178,'2024'!$AG$5:$AG$178,">="&DATE(2027,7,1),'2024'!$AG$5:$AG$178,"<"&EDATE(DATE(2027,7,1),1))) | F73: =IF(N(D73)=0,"",E73/D73) | G73: =IF(E73="","",E73/2) | H73: =IF(DATE(2027,7,1)>TODAY(),"",SUMIFS('2024'!$V$5:$V$178,'2024'!$AG$5:$AG$178,">="&DATE(2027,7,1),'2024'!$AG$5:$AG$178,"<"&EDATE(DATE(2027,7,1),1))) | I73: =IF(N(D73)=0,"",(SUMIFS('2024'!$AH$5:$AH$178,'2024'!$AG$5:$AG$178,">="&DATE(2027,7,1),'2024'!$AG$5:$AG$178,"<"&EDATE(DATE(2027,7,1),1)))/D73) | J73: =IF(N(D73)=0,"",(SUMIFS('2024'!$AI$5:$AI$178,'2024'!$AG$5:$AG$178,">="&DATE(2027,7,1),'2024'!$AG$5:$AG$178,"<"&EDATE(DATE(2027,7,1),1)))/D73)
B74: =IF(DATE(2027,8,1)>TODAY(),"",DATE(2027,8,1)) | C74: =IF(DATE(2027,8,1)>TODAY(),"",COUNTIFS('2024'!$AD$5:$AD$178,">="&DATE(2027,8,1),'2024'!$AD$5:$AD$178,"<"&EDATE(DATE(2027,8,1),1))) | D74: =IF(DATE(2027,8,1)>TODAY(),"",COUNTIFS('2024'!$AG$5:$AG$178,">="&DATE(2027,8,1),'2024'!$AG$5:$AG$178,"<"&EDATE(DATE(2027,8,1),1))) | E74: =IF(DATE(2027,8,1)>TODAY(),"",SUMIFS('2024'!$X$5:$X$178,'2024'!$AG$5:$AG$178,">="&DATE(2027,8,1),'2024'!$AG$5:$AG$178,"<"&EDATE(DATE(2027,8,1),1))) | F74: =IF(N(D74)=0,"",E74/D74) | G74: =IF(E74="","",E74/2) | H74: =IF(DATE(2027,8,1)>TODAY(),"",SUMIFS('2024'!$V$5:$V$178,'2024'!$AG$5:$AG$178,">="&DATE(2027,8,1),'2024'!$AG$5:$AG$178,"<"&EDATE(DATE(2027,8,1),1))) | I74: =IF(N(D74)=0,"",(SUMIFS('2024'!$AH$5:$AH$178,'2024'!$AG$5:$AG$178,">="&DATE(2027,8,1),'2024'!$AG$5:$AG$178,"<"&EDATE(DATE(2027,8,1),1)))/D74) | J74: =IF(N(D74)=0,"",(SUMIFS('2024'!$AI$5:$AI$178,'2024'!$AG$5:$AG$178,">="&DATE(2027,8,1),'2024'!$AG$5:$AG$178,"<"&EDATE(DATE(2027,8,1),1)))/D74)
B75: =IF(DATE(2027,9,1)>TODAY(),"",DATE(2027,9,1)) | C75: =IF(DATE(2027,9,1)>TODAY(),"",COUNTIFS('2024'!$AD$5:$AD$178,">="&DATE(2027,9,1),'2024'!$AD$5:$AD$178,"<"&EDATE(DATE(2027,9,1),1))) | D75: =IF(DATE(2027,9,1)>TODAY(),"",COUNTIFS('2024'!$AG$5:$AG$178,">="&DATE(2027,9,1),'2024'!$AG$5:$AG$178,"<"&EDATE(DATE(2027,9,1),1))) | E75: =IF(DATE(2027,9,1)>TODAY(),"",SUMIFS('2024'!$X$5:$X$178,'2024'!$AG$5:$AG$178,">="&DATE(2027,9,1),'2024'!$AG$5:$AG$178,"<"&EDATE(DATE(2027,9,1),1))) | F75: =IF(N(D75)=0,"",E75/D75) | G75: =IF(E75="","",E75/2) | H75: =IF(DATE(2027,9,1)>TODAY(),"",SUMIFS('2024'!$V$5:$V$178,'2024'!$AG$5:$AG$178,">="&DATE(2027,9,1),'2024'!$AG$5:$AG$178,"<"&EDATE(DATE(2027,9,1),1))) | I75: =IF(N(D75)=0,"",(SUMIFS('2024'!$AH$5:$AH$178,'2024'!$AG$5:$AG$178,">="&DATE(2027,9,1),'2024'!$AG$5:$AG$178,"<"&EDATE(DATE(2027,9,1),1)))/D75) | J75: =IF(N(D75)=0,"",(SUMIFS('2024'!$AI$5:$AI$178,'2024'!$AG$5:$AG$178,">="&DATE(2027,9,1),'2024'!$AG$5:$AG$178,"<"&EDATE(DATE(2027,9,1),1)))/D75)
B76: =IF(DATE(2027,10,1)>TODAY(),"",DATE(2027,10,1)) | C76: =IF(DATE(2027,10,1)>TODAY(),"",COUNTIFS('2024'!$AD$5:$AD$178,">="&DATE(2027,10,1),'2024'!$AD$5:$AD$178,"<"&EDATE(DATE(2027,10,1),1))) | D76: =IF(DATE(2027,10,1)>TODAY(),"",COUNTIFS('2024'!$AG$5:$AG$178,">="&DATE(2027,10,1),'2024'!$AG$5:$AG$178,"<"&EDATE(DATE(2027,10,1),1))) | E76: =IF(DATE(2027,10,1)>TODAY(),"",SUMIFS('2024'!$X$5:$X$178,'2024'!$AG$5:$AG$178,">="&DATE(2027,10,1),'2024'!$AG$5:$AG$178,"<"&EDATE(DATE(2027,10,1),1))) | F76: =IF(N(D76)=0,"",E76/D76) | G76: =IF(E76="","",E76/2) | H76: =IF(DATE(2027,10,1)>TODAY(),"",SUMIFS('2024'!$V$5:$V$178,'2024'!$AG$5:$AG$178,">="&DATE(2027,10,1),'2024'!$AG$5:$AG$178,"<"&EDATE(DATE(2027,10,1),1))) | I76: =IF(N(D76)=0,"",(SUMIFS('2024'!$AH$5:$AH$178,'2024'!$AG$5:$AG$178,">="&DATE(2027,10,1),'2024'!$AG$5:$AG$178,"<"&EDATE(DATE(2027,10,1),1)))/D76) | J76: =IF(N(D76)=0,"",(SUMIFS('2024'!$AI$5:$AI$178,'2024'!$AG$5:$AG$178,">="&DATE(2027,10,1),'2024'!$AG$5:$AG$178,"<"&EDATE(DATE(2027,10,1),1)))/D76)
B77: =IF(DATE(2027,11,1)>TODAY(),"",DATE(2027,11,1)) | C77: =IF(DATE(2027,11,1)>TODAY(),"",COUNTIFS('2024'!$AD$5:$AD$178,">="&DATE(2027,11,1),'2024'!$AD$5:$AD$178,"<"&EDATE(DATE(2027,11,1),1))) | D77: =IF(DATE(2027,11,1)>TODAY(),"",COUNTIFS('2024'!$AG$5:$AG$178,">="&DATE(2027,11,1),'2024'!$AG$5:$AG$178,"<"&EDATE(DATE(2027,11,1),1))) | E77: =IF(DATE(2027,11,1)>TODAY(),"",SUMIFS('2024'!$X$5:$X$178,'2024'!$AG$5:$AG$178,">="&DATE(2027,11,1),'2024'!$AG$5:$AG$178,"<"&EDATE(DATE(2027,11,1),1))) | F77: =IF(N(D77)=0,"",E77/D77) | G77: =IF(E77="","",E77/2) | H77: =IF(DATE(2027,11,1)>TODAY(),"",SUMIFS('2024'!$V$5:$V$178,'2024'!$AG$5:$AG$178,">="&DATE(2027,11,1),'2024'!$AG$5:$AG$178,"<"&EDATE(DATE(2027,11,1),1))) | I77: =IF(N(D77)=0,"",(SUMIFS('2024'!$AH$5:$AH$178,'2024'!$AG$5:$AG$178,">="&DATE(2027,11,1),'2024'!$AG$5:$AG$178,"<"&EDATE(DATE(2027,11,1),1)))/D77) | J77: =IF(N(D77)=0,"",(SUMIFS('2024'!$AI$5:$AI$178,'2024'!$AG$5:$AG$178,">="&DATE(2027,11,1),'2024'!$AG$5:$AG$178,"<"&EDATE(DATE(2027,11,1),1)))/D77)
B78: =IF(DATE(2027,12,1)>TODAY(),"",DATE(2027,12,1)) | C78: =IF(DATE(2027,12,1)>TODAY(),"",COUNTIFS('2024'!$AD$5:$AD$178,">="&DATE(2027,12,1),'2024'!$AD$5:$AD$178,"<"&EDATE(DATE(2027,12,1),1))) | D78: =IF(DATE(2027,12,1)>TODAY(),"",COUNTIFS('2024'!$AG$5:$AG$178,">="&DATE(2027,12,1),'2024'!$AG$5:$AG$178,"<"&EDATE(DATE(2027,12,1),1))) | E78: =IF(DATE(2027,12,1)>TODAY(),"",SUMIFS('2024'!$X$5:$X$178,'2024'!$AG$5:$AG$178,">="&DATE(2027,12,1),'2024'!$AG$5:$AG$178,"<"&EDATE(DATE(2027,12,1),1))) | F78: =IF(N(D78)=0,"",E78/D78) | G78: =IF(E78="","",E78/2) | H78: =IF(DATE(2027,12,1)>TODAY(),"",SUMIFS('2024'!$V$5:$V$178,'2024'!$AG$5:$AG$178,">="&DATE(2027,12,1),'2024'!$AG$5:$AG$178,"<"&EDATE(DATE(2027,12,1),1))) | I78: =IF(N(D78)=0,"",(SUMIFS('2024'!$AH$5:$AH$178,'2024'!$AG$5:$AG$178,">="&DATE(2027,12,1),'2024'!$AG$5:$AG$178,"<"&EDATE(DATE(2027,12,1),1)))/D78) | J78: =IF(N(D78)=0,"",(SUMIFS('2024'!$AI$5:$AI$178,'2024'!$AG$5:$AG$178,">="&DATE(2027,12,1),'2024'!$AG$5:$AG$178,"<"&EDATE(DATE(2027,12,1),1)))/D78)
B79: =IF(DATE(2028,1,1)>TODAY(),"",DATE(2028,1,1)) | C79: =IF(DATE(2028,1,1)>TODAY(),"",COUNTIFS('2024'!$AD$5:$AD$178,">="&DATE(2028,1,1),'2024'!$AD$5:$AD$178,"<"&EDATE(DATE(2028,1,1),1))) | D79: =IF(DATE(2028,1,1)>TODAY(),"",COUNTIFS('2024'!$AG$5:$AG$178,">="&DATE(2028,1,1),'2024'!$AG$5:$AG$178,"<"&EDATE(DATE(2028,1,1),1))) | E79: =IF(DATE(2028,1,1)>TODAY(),"",SUMIFS('2024'!$X$5:$X$178,'2024'!$AG$5:$AG$178,">="&DATE(2028,1,1),'2024'!$AG$5:$AG$178,"<"&EDATE(DATE(2028,1,1),1))) | F79: =IF(N(D79)=0,"",E79/D79) | G79: =IF(E79="","",E79/2) | H79: =IF(DATE(2028,1,1)>TODAY(),"",SUMIFS('2024'!$V$5:$V$178,'2024'!$AG$5:$AG$178,">="&DATE(2028,1,1),'2024'!$AG$5:$AG$178,"<"&EDATE(DATE(2028,1,1),1))) | I79: =IF(N(D79)=0,"",(SUMIFS('2024'!$AH$5:$AH$178,'2024'!$AG$5:$AG$178,">="&DATE(2028,1,1),'2024'!$AG$5:$AG$178,"<"&EDATE(DATE(2028,1,1),1)))/D79) | J79: =IF(N(D79)=0,"",(SUMIFS('2024'!$AI$5:$AI$178,'2024'!$AG$5:$AG$178,">="&DATE(2028,1,1),'2024'!$AG$5:$AG$178,"<"&EDATE(DATE(2028,1,1),1)))/D79)
B80: =IF(DATE(2028,2,1)>TODAY(),"",DATE(2028,2,1)) | C80: =IF(DATE(2028,2,1)>TODAY(),"",COUNTIFS('2024'!$AD$5:$AD$178,">="&DATE(2028,2,1),'2024'!$AD$5:$AD$178,"<"&EDATE(DATE(2028,2,1),1))) | D80: =IF(DATE(2028,2,1)>TODAY(),"",COUNTIFS('2024'!$AG$5:$AG$178,">="&DATE(2028,2,1),'2024'!$AG$5:$AG$178,"<"&EDATE(DATE(2028,2,1),1))) | E80: =IF(DATE(2028,2,1)>TODAY(),"",SUMIFS('2024'!$X$5:$X$178,'2024'!$AG$5:$AG$178,">="&DATE(2028,2,1),'2024'!$AG$5:$AG$178,"<"&EDATE(DATE(2028,2,1),1))) | F80: =IF(N(D80)=0,"",E80/D80) | G80: =IF(E80="","",E80/2) | H80: =IF(DATE(2028,2,1)>TODAY(),"",SUMIFS('2024'!$V$5:$V$178,'2024'!$AG$5:$AG$178,">="&DATE(2028,2,1),'2024'!$AG$5:$AG$178,"<"&EDATE(DATE(2028,2,1),1))) | I80: =IF(N(D80)=0,"",(SUMIFS('2024'!$AH$5:$AH$178,'2024'!$AG$5:$AG$178,">="&DATE(2028,2,1),'2024'!$AG$5:$AG$178,"<"&EDATE(DATE(2028,2,1),1)))/D80) | J80: =IF(N(D80)=0,"",(SUMIFS('2024'!$AI$5:$AI$178,'2024'!$AG$5:$AG$178,">="&DATE(2028,2,1),'2024'!$AG$5:$AG$178,"<"&EDATE(DATE(2028,2,1),1)))/D80)
B81: =IF(DATE(2028,3,1)>TODAY(),"",DATE(2028,3,1)) | C81: =IF(DATE(2028,3,1)>TODAY(),"",COUNTIFS('2024'!$AD$5:$AD$178,">="&DATE(2028,3,1),'2024'!$AD$5:$AD$178,"<"&EDATE(DATE(2028,3,1),1))) | D81: =IF(DATE(2028,3,1)>TODAY(),"",COUNTIFS('2024'!$AG$5:$AG$178,">="&DATE(2028,3,1),'2024'!$AG$5:$AG$178,"<"&EDATE(DATE(2028,3,1),1))) | E81: =IF(DATE(2028,3,1)>TODAY(),"",SUMIFS('2024'!$X$5:$X$178,'2024'!$AG$5:$AG$178,">="&DATE(2028,3,1),'2024'!$AG$5:$AG$178,"<"&EDATE(DATE(2028,3,1),1))) | F81: =IF(N(D81)=0,"",E81/D81) | G81: =IF(E81="","",E81/2) | H81: =IF(DATE(2028,3,1)>TODAY(),"",SUMIFS('2024'!$V$5:$V$178,'2024'!$AG$5:$AG$178,">="&DATE(2028,3,1),'2024'!$AG$5:$AG$178,"<"&EDATE(DATE(2028,3,1),1))) | I81: =IF(N(D81)=0,"",(SUMIFS('2024'!$AH$5:$AH$178,'2024'!$AG$5:$AG$178,">="&DATE(2028,3,1),'2024'!$AG$5:$AG$178,"<"&EDATE(DATE(2028,3,1),1)))/D81) | J81: =IF(N(D81)=0,"",(SUMIFS('2024'!$AI$5:$AI$178,'2024'!$AG$5:$AG$178,">="&DATE(2028,3,1),'2024'!$AG$5:$AG$178,"<"&EDATE(DATE(2028,3,1),1)))/D81)
B82: =IF(DATE(2028,4,1)>TODAY(),"",DATE(2028,4,1)) | C82: =IF(DATE(2028,4,1)>TODAY(),"",COUNTIFS('2024'!$AD$5:$AD$178,">="&DATE(2028,4,1),'2024'!$AD$5:$AD$178,"<"&EDATE(DATE(2028,4,1),1))) | D82: =IF(DATE(2028,4,1)>TODAY(),"",COUNTIFS('2024'!$AG$5:$AG$178,">="&DATE(2028,4,1),'2024'!$AG$5:$AG$178,"<"&EDATE(DATE(2028,4,1),1))) | E82: =IF(DATE(2028,4,1)>TODAY(),"",SUMIFS('2024'!$X$5:$X$178,'2024'!$AG$5:$AG$178,">="&DATE(2028,4,1),'2024'!$AG$5:$AG$178,"<"&EDATE(DATE(2028,4,1),1))) | F82: =IF(N(D82)=0,"",E82/D82) | G82: =IF(E82="","",E82/2) | H82: =IF(DATE(2028,4,1)>TODAY(),"",SUMIFS('2024'!$V$5:$V$178,'2024'!$AG$5:$AG$178,">="&DATE(2028,4,1),'2024'!$AG$5:$AG$178,"<"&EDATE(DATE(2028,4,1),1))) | I82: =IF(N(D82)=0,"",(SUMIFS('2024'!$AH$5:$AH$178,'2024'!$AG$5:$AG$178,">="&DATE(2028,4,1),'2024'!$AG$5:$AG$178,"<"&EDATE(DATE(2028,4,1),1)))/D82) | J82: =IF(N(D82)=0,"",(SUMIFS('2024'!$AI$5:$AI$178,'2024'!$AG$5:$AG$178,">="&DATE(2028,4,1),'2024'!$AG$5:$AG$178,"<"&EDATE(DATE(2028,4,1),1)))/D82)
B83: =IF(DATE(2028,5,1)>TODAY(),"",DATE(2028,5,1)) | C83: =IF(DATE(2028,5,1)>TODAY(),"",COUNTIFS('2024'!$AD$5:$AD$178,">="&DATE(2028,5,1),'2024'!$AD$5:$AD$178,"<"&EDATE(DATE(2028,5,1),1))) | D83: =IF(DATE(2028,5,1)>TODAY(),"",COUNTIFS('2024'!$AG$5:$AG$178,">="&DATE(2028,5,1),'2024'!$AG$5:$AG$178,"<"&EDATE(DATE(2028,5,1),1))) | E83: =IF(DATE(2028,5,1)>TODAY(),"",SUMIFS('2024'!$X$5:$X$178,'2024'!$AG$5:$AG$178,">="&DATE(2028,5,1),'2024'!$AG$5:$AG$178,"<"&EDATE(DATE(2028,5,1),1))) | F83: =IF(N(D83)=0,"",E83/D83) | G83: =IF(E83="","",E83/2) | H83: =IF(DATE(2028,5,1)>TODAY(),"",SUMIFS('2024'!$V$5:$V$178,'2024'!$AG$5:$AG$178,">="&DATE(2028,5,1),'2024'!$AG$5:$AG$178,"<"&EDATE(DATE(2028,5,1),1))) | I83: =IF(N(D83)=0,"",(SUMIFS('2024'!$AH$5:$AH$178,'2024'!$AG$5:$AG$178,">="&DATE(2028,5,1),'2024'!$AG$5:$AG$178,"<"&EDATE(DATE(2028,5,1),1)))/D83) | J83: =IF(N(D83)=0,"",(SUMIFS('2024'!$AI$5:$AI$178,'2024'!$AG$5:$AG$178,">="&DATE(2028,5,1),'2024'!$AG$5:$AG$178,"<"&EDATE(DATE(2028,5,1),1)))/D83)
B84: =IF(DATE(2028,6,1)>TODAY(),"",DATE(2028,6,1)) | C84: =IF(DATE(2028,6,1)>TODAY(),"",COUNTIFS('2024'!$AD$5:$AD$178,">="&DATE(2028,6,1),'2024'!$AD$5:$AD$178,"<"&EDATE(DATE(2028,6,1),1))) | D84: =IF(DATE(2028,6,1)>TODAY(),"",COUNTIFS('2024'!$AG$5:$AG$178,">="&DATE(2028,6,1),'2024'!$AG$5:$AG$178,"<"&EDATE(DATE(2028,6,1),1))) | E84: =IF(DATE(2028,6,1)>TODAY(),"",SUMIFS('2024'!$X$5:$X$178,'2024'!$AG$5:$AG$178,">="&DATE(2028,6,1),'2024'!$AG$5:$AG$178,"<"&EDATE(DATE(2028,6,1),1))) | F84: =IF(N(D84)=0,"",E84/D84) | G84: =IF(E84="","",E84/2) | H84: =IF(DATE(2028,6,1)>TODAY(),"",SUMIFS('2024'!$V$5:$V$178,'2024'!$AG$5:$AG$178,">="&DATE(2028,6,1),'2024'!$AG$5:$AG$178,"<"&EDATE(DATE(2028,6,1),1))) | I84: =IF(N(D84)=0,"",(SUMIFS('2024'!$AH$5:$AH$178,'2024'!$AG$5:$AG$178,">="&DATE(2028,6,1),'2024'!$AG$5:$AG$178,"<"&EDATE(DATE(2028,6,1),1)))/D84) | J84: =IF(N(D84)=0,"",(SUMIFS('2024'!$AI$5:$AI$178,'2024'!$AG$5:$AG$178,">="&DATE(2028,6,1),'2024'!$AG$5:$AG$178,"<"&EDATE(DATE(2028,6,1),1)))/D84)
B85: =IF(DATE(2028,7,1)>TODAY(),"",DATE(2028,7,1)) | C85: =IF(DATE(2028,7,1)>TODAY(),"",COUNTIFS('2024'!$AD$5:$AD$178,">="&DATE(2028,7,1),'2024'!$AD$5:$AD$178,"<"&EDATE(DATE(2028,7,1),1))) | D85: =IF(DATE(2028,7,1)>TODAY(),"",COUNTIFS('2024'!$AG$5:$AG$178,">="&DATE(2028,7,1),'2024'!$AG$5:$AG$178,"<"&EDATE(DATE(2028,7,1),1))) | E85: =IF(DATE(2028,7,1)>TODAY(),"",SUMIFS('2024'!$X$5:$X$178,'2024'!$AG$5:$AG$178,">="&DATE(2028,7,1),'2024'!$AG$5:$AG$178,"<"&EDATE(DATE(2028,7,1),1))) | F85: =IF(N(D85)=0,"",E85/D85) | G85: =IF(E85="","",E85/2) | H85: =IF(DATE(2028,7,1)>TODAY(),"",SUMIFS('2024'!$V$5:$V$178,'2024'!$AG$5:$AG$178,">="&DATE(2028,7,1),'2024'!$AG$5:$AG$178,"<"&EDATE(DATE(2028,7,1),1))) | I85: =IF(N(D85)=0,"",(SUMIFS('2024'!$AH$5:$AH$178,'2024'!$AG$5:$AG$178,">="&DATE(2028,7,1),'2024'!$AG$5:$AG$178,"<"&EDATE(DATE(2028,7,1),1)))/D85) | J85: =IF(N(D85)=0,"",(SUMIFS('2024'!$AI$5:$AI$178,'2024'!$AG$5:$AG$178,">="&DATE(2028,7,1),'2024'!$AG$5:$AG$178,"<"&EDATE(DATE(2028,7,1),1)))/D85)
B86: =IF(DATE(2028,8,1)>TODAY(),"",DATE(2028,8,1)) | C86: =IF(DATE(2028,8,1)>TODAY(),"",COUNTIFS('2024'!$AD$5:$AD$178,">="&DATE(2028,8,1),'2024'!$AD$5:$AD$178,"<"&EDATE(DATE(2028,8,1),1))) | D86: =IF(DATE(2028,8,1)>TODAY(),"",COUNTIFS('2024'!$AG$5:$AG$178,">="&DATE(2028,8,1),'2024'!$AG$5:$AG$178,"<"&EDATE(DATE(2028,8,1),1))) | E86: =IF(DATE(2028,8,1)>TODAY(),"",SUMIFS('2024'!$X$5:$X$178,'2024'!$AG$5:$AG$178,">="&DATE(2028,8,1),'2024'!$AG$5:$AG$178,"<"&EDATE(DATE(2028,8,1),1))) | F86: =IF(N(D86)=0,"",E86/D86) | G86: =IF(E86="","",E86/2) | H86: =IF(DATE(2028,8,1)>TODAY(),"",SUMIFS('2024'!$V$5:$V$178,'2024'!$AG$5:$AG$178,">="&DATE(2028,8,1),'2024'!$AG$5:$AG$178,"<"&EDATE(DATE(2028,8,1),1))) | I86: =IF(N(D86)=0,"",(SUMIFS('2024'!$AH$5:$AH$178,'2024'!$AG$5:$AG$178,">="&DATE(2028,8,1),'2024'!$AG$5:$AG$178,"<"&EDATE(DATE(2028,8,1),1)))/D86) | J86: =IF(N(D86)=0,"",(SUMIFS('2024'!$AI$5:$AI$178,'2024'!$AG$5:$AG$178,">="&DATE(2028,8,1),'2024'!$AG$5:$AG$178,"<"&EDATE(DATE(2028,8,1),1)))/D86)
B87: =IF(DATE(2028,9,1)>TODAY(),"",DATE(2028,9,1)) | C87: =IF(DATE(2028,9,1)>TODAY(),"",COUNTIFS('2024'!$AD$5:$AD$178,">="&DATE(2028,9,1),'2024'!$AD$5:$AD$178,"<"&EDATE(DATE(2028,9,1),1))) | D87: =IF(DATE(2028,9,1)>TODAY(),"",COUNTIFS('2024'!$AG$5:$AG$178,">="&DATE(2028,9,1),'2024'!$AG$5:$AG$178,"<"&EDATE(DATE(2028,9,1),1))) | E87: =IF(DATE(2028,9,1)>TODAY(),"",SUMIFS('2024'!$X$5:$X$178,'2024'!$AG$5:$AG$178,">="&DATE(2028,9,1),'2024'!$AG$5:$AG$178,"<"&EDATE(DATE(2028,9,1),1))) | F87: =IF(N(D87)=0,"",E87/D87) | G87: =IF(E87="","",E87/2) | H87: =IF(DATE(2028,9,1)>TODAY(),"",SUMIFS('2024'!$V$5:$V$178,'2024'!$AG$5:$AG$178,">="&DATE(2028,9,1),'2024'!$AG$5:$AG$178,"<"&EDATE(DATE(2028,9,1),1))) | I87: =IF(N(D87)=0,"",(SUMIFS('2024'!$AH$5:$AH$178,'2024'!$AG$5:$AG$178,">="&DATE(2028,9,1),'2024'!$AG$5:$AG$178,"<"&EDATE(DATE(2028,9,1),1)))/D87) | J87: =IF(N(D87)=0,"",(SUMIFS('2024'!$AI$5:$AI$178,'2024'!$AG$5:$AG$178,">="&DATE(2028,9,1),'2024'!$AG$5:$AG$178,"<"&EDATE(DATE(2028,9,1),1)))/D87)
B88: =IF(DATE(2028,10,1)>TODAY(),"",DATE(2028,10,1)) | C88: =IF(DATE(2028,10,1)>TODAY(),"",COUNTIFS('2024'!$AD$5:$AD$178,">="&DATE(2028,10,1),'2024'!$AD$5:$AD$178,"<"&EDATE(DATE(2028,10,1),1))) | D88: =IF(DATE(2028,10,1)>TODAY(),"",COUNTIFS('2024'!$AG$5:$AG$178,">="&DATE(2028,10,1),'2024'!$AG$5:$AG$178,"<"&EDATE(DATE(2028,10,1),1))) | E88: =IF(DATE(2028,10,1)>TODAY(),"",SUMIFS('2024'!$X$5:$X$178,'2024'!$AG$5:$AG$178,">="&DATE(2028,10,1),'2024'!$AG$5:$AG$178,"<"&EDATE(DATE(2028,10,1),1))) | F88: =IF(N(D88)=0,"",E88/D88) | G88: =IF(E88="","",E88/2) | H88: =IF(DATE(2028,10,1)>TODAY(),"",SUMIFS('2024'!$V$5:$V$178,'2024'!$AG$5:$AG$178,">="&DATE(2028,10,1),'2024'!$AG$5:$AG$178,"<"&EDATE(DATE(2028,10,1),1))) | I88: =IF(N(D88)=0,"",(SUMIFS('2024'!$AH$5:$AH$178,'2024'!$AG$5:$AG$178,">="&DATE(2028,10,1),'2024'!$AG$5:$AG$178,"<"&EDATE(DATE(2028,10,1),1)))/D88) | J88: =IF(N(D88)=0,"",(SUMIFS('2024'!$AI$5:$AI$178,'2024'!$AG$5:$AG$178,">="&DATE(2028,10,1),'2024'!$AG$5:$AG$178,"<"&EDATE(DATE(2028,10,1),1)))/D88)
B89: =IF(DATE(2028,11,1)>TODAY(),"",DATE(2028,11,1)) | C89: =IF(DATE(2028,11,1)>TODAY(),"",COUNTIFS('2024'!$AD$5:$AD$178,">="&DATE(2028,11,1),'2024'!$AD$5:$AD$178,"<"&EDATE(DATE(2028,11,1),1))) | D89: =IF(DATE(2028,11,1)>TODAY(),"",COUNTIFS('2024'!$AG$5:$AG$178,">="&DATE(2028,11,1),'2024'!$AG$5:$AG$178,"<"&EDATE(DATE(2028,11,1),1))) | E89: =IF(DATE(2028,11,1)>TODAY(),"",SUMIFS('2024'!$X$5:$X$178,'2024'!$AG$5:$AG$178,">="&DATE(2028,11,1),'2024'!$AG$5:$AG$178,"<"&EDATE(DATE(2028,11,1),1))) | F89: =IF(N(D89)=0,"",E89/D89) | G89: =IF(E89="","",E89/2) | H89: =IF(DATE(2028,11,1)>TODAY(),"",SUMIFS('2024'!$V$5:$V$178,'2024'!$AG$5:$AG$178,">="&DATE(2028,11,1),'2024'!$AG$5:$AG$178,"<"&EDATE(DATE(2028,11,1),1))) | I89: =IF(N(D89)=0,"",(SUMIFS('2024'!$AH$5:$AH$178,'2024'!$AG$5:$AG$178,">="&DATE(2028,11,1),'2024'!$AG$5:$AG$178,"<"&EDATE(DATE(2028,11,1),1)))/D89) | J89: =IF(N(D89)=0,"",(SUMIFS('2024'!$AI$5:$AI$178,'2024'!$AG$5:$AG$178,">="&DATE(2028,11,1),'2024'!$AG$5:$AG$178,"<"&EDATE(DATE(2028,11,1),1)))/D89)
B90: =IF(DATE(2028,12,1)>TODAY(),"",DATE(2028,12,1)) | C90: =IF(DATE(2028,12,1)>TODAY(),"",COUNTIFS('2024'!$AD$5:$AD$178,">="&DATE(2028,12,1),'2024'!$AD$5:$AD$178,"<"&EDATE(DATE(2028,12,1),1))) | D90: =IF(DATE(2028,12,1)>TODAY(),"",COUNTIFS('2024'!$AG$5:$AG$178,">="&DATE(2028,12,1),'2024'!$AG$5:$AG$178,"<"&EDATE(DATE(2028,12,1),1))) | E90: =IF(DATE(2028,12,1)>TODAY(),"",SUMIFS('2024'!$X$5:$X$178,'2024'!$AG$5:$AG$178,">="&DATE(2028,12,1),'2024'!$AG$5:$AG$178,"<"&EDATE(DATE(2028,12,1),1))) | F90: =IF(N(D90)=0,"",E90/D90) | G90: =IF(E90="","",E90/2) | H90: =IF(DATE(2028,12,1)>TODAY(),"",SUMIFS('2024'!$V$5:$V$178,'2024'!$AG$5:$AG$178,">="&DATE(2028,12,1),'2024'!$AG$5:$AG$178,"<"&EDATE(DATE(2028,12,1),1))) | I90: =IF(N(D90)=0,"",(SUMIFS('2024'!$AH$5:$AH$178,'2024'!$AG$5:$AG$178,">="&DATE(2028,12,1),'2024'!$AG$5:$AG$178,"<"&EDATE(DATE(2028,12,1),1)))/D90) | J90: =IF(N(D90)=0,"",(SUMIFS('2024'!$AI$5:$AI$178,'2024'!$AG$5:$AG$178,">="&DATE(2028,12,1),'2024'!$AG$5:$AG$178,"<"&EDATE(DATE(2028,12,1),1)))/D90)
B91: =IF(DATE(2029,1,1)>TODAY(),"",DATE(2029,1,1)) | C91: =IF(DATE(2029,1,1)>TODAY(),"",COUNTIFS('2024'!$AD$5:$AD$178,">="&DATE(2029,1,1),'2024'!$AD$5:$AD$178,"<"&EDATE(DATE(2029,1,1),1))) | D91: =IF(DATE(2029,1,1)>TODAY(),"",COUNTIFS('2024'!$AG$5:$AG$178,">="&DATE(2029,1,1),'2024'!$AG$5:$AG$178,"<"&EDATE(DATE(2029,1,1),1))) | E91: =IF(DATE(2029,1,1)>TODAY(),"",SUMIFS('2024'!$X$5:$X$178,'2024'!$AG$5:$AG$178,">="&DATE(2029,1,1),'2024'!$AG$5:$AG$178,"<"&EDATE(DATE(2029,1,1),1))) | F91: =IF(N(D91)=0,"",E91/D91) | G91: =IF(E91="","",E91/2) | H91: =IF(DATE(2029,1,1)>TODAY(),"",SUMIFS('2024'!$V$5:$V$178,'2024'!$AG$5:$AG$178,">="&DATE(2029,1,1),'2024'!$AG$5:$AG$178,"<"&EDATE(DATE(2029,1,1),1))) | I91: =IF(N(D91)=0,"",(SUMIFS('2024'!$AH$5:$AH$178,'2024'!$AG$5:$AG$178,">="&DATE(2029,1,1),'2024'!$AG$5:$AG$178,"<"&EDATE(DATE(2029,1,1),1)))/D91) | J91: =IF(N(D91)=0,"",(SUMIFS('2024'!$AI$5:$AI$178,'2024'!$AG$5:$AG$178,">="&DATE(2029,1,1),'2024'!$AG$5:$AG$178,"<"&EDATE(DATE(2029,1,1),1)))/D91)
B92: =IF(DATE(2029,2,1)>TODAY(),"",DATE(2029,2,1)) | C92: =IF(DATE(2029,2,1)>TODAY(),"",COUNTIFS('2024'!$AD$5:$AD$178,">="&DATE(2029,2,1),'2024'!$AD$5:$AD$178,"<"&EDATE(DATE(2029,2,1),1))) | D92: =IF(DATE(2029,2,1)>TODAY(),"",COUNTIFS('2024'!$AG$5:$AG$178,">="&DATE(2029,2,1),'2024'!$AG$5:$AG$178,"<"&EDATE(DATE(2029,2,1),1))) | E92: =IF(DATE(2029,2,1)>TODAY(),"",SUMIFS('2024'!$X$5:$X$178,'2024'!$AG$5:$AG$178,">="&DATE(2029,2,1),'2024'!$AG$5:$AG$178,"<"&EDATE(DATE(2029,2,1),1))) | F92: =IF(N(D92)=0,"",E92/D92) | G92: =IF(E92="","",E92/2) | H92: =IF(DATE(2029,2,1)>TODAY(),"",SUMIFS('2024'!$V$5:$V$178,'2024'!$AG$5:$AG$178,">="&DATE(2029,2,1),'2024'!$AG$5:$AG$178,"<"&EDATE(DATE(2029,2,1),1))) | I92: =IF(N(D92)=0,"",(SUMIFS('2024'!$AH$5:$AH$178,'2024'!$AG$5:$AG$178,">="&DATE(2029,2,1),'2024'!$AG$5:$AG$178,"<"&EDATE(DATE(2029,2,1),1)))/D92) | J92: =IF(N(D92)=0,"",(SUMIFS('2024'!$AI$5:$AI$178,'2024'!$AG$5:$AG$178,">="&DATE(2029,2,1),'2024'!$AG$5:$AG$178,"<"&EDATE(DATE(2029,2,1),1)))/D92)
B93: =IF(DATE(2029,3,1)>TODAY(),"",DATE(2029,3,1)) | C93: =IF(DATE(2029,3,1)>TODAY(),"",COUNTIFS('2024'!$AD$5:$AD$178,">="&DATE(2029,3,1),'2024'!$AD$5:$AD$178,"<"&EDATE(DATE(2029,3,1),1))) | D93: =IF(DATE(2029,3,1)>TODAY(),"",COUNTIFS('2024'!$AG$5:$AG$178,">="&DATE(2029,3,1),'2024'!$AG$5:$AG$178,"<"&EDATE(DATE(2029,3,1),1))) | E93: =IF(DATE(2029,3,1)>TODAY(),"",SUMIFS('2024'!$X$5:$X$178,'2024'!$AG$5:$AG$178,">="&DATE(2029,3,1),'2024'!$AG$5:$AG$178,"<"&EDATE(DATE(2029,3,1),1))) | F93: =IF(N(D93)=0,"",E93/D93) | G93: =IF(E93="","",E93/2) | H93: =IF(DATE(2029,3,1)>TODAY(),"",SUMIFS('2024'!$V$5:$V$178,'2024'!$AG$5:$AG$178,">="&DATE(2029,3,1),'2024'!$AG$5:$AG$178,"<"&EDATE(DATE(2029,3,1),1))) | I93: =IF(N(D93)=0,"",(SUMIFS('2024'!$AH$5:$AH$178,'2024'!$AG$5:$AG$178,">="&DATE(2029,3,1),'2024'!$AG$5:$AG$178,"<"&EDATE(DATE(2029,3,1),1)))/D93) | J93: =IF(N(D93)=0,"",(SUMIFS('2024'!$AI$5:$AI$178,'2024'!$AG$5:$AG$178,">="&DATE(2029,3,1),'2024'!$AG$5:$AG$178,"<"&EDATE(DATE(2029,3,1),1)))/D93)
B94: =IF(DATE(2029,4,1)>TODAY(),"",DATE(2029,4,1)) | C94: =IF(DATE(2029,4,1)>TODAY(),"",COUNTIFS('2024'!$AD$5:$AD$178,">="&DATE(2029,4,1),'2024'!$AD$5:$AD$178,"<"&EDATE(DATE(2029,4,1),1))) | D94: =IF(DATE(2029,4,1)>TODAY(),"",COUNTIFS('2024'!$AG$5:$AG$178,">="&DATE(2029,4,1),'2024'!$AG$5:$AG$178,"<"&EDATE(DATE(2029,4,1),1))) | E94: =IF(DATE(2029,4,1)>TODAY(),"",SUMIFS('2024'!$X$5:$X$178,'2024'!$AG$5:$AG$178,">="&DATE(2029,4,1),'2024'!$AG$5:$AG$178,"<"&EDATE(DATE(2029,4,1),1))) | F94: =IF(N(D94)=0,"",E94/D94) | G94: =IF(E94="","",E94/2) | H94: =IF(DATE(2029,4,1)>TODAY(),"",SUMIFS('2024'!$V$5:$V$178,'2024'!$AG$5:$AG$178,">="&DATE(2029,4,1),'2024'!$AG$5:$AG$178,"<"&EDATE(DATE(2029,4,1),1))) | I94: =IF(N(D94)=0,"",(SUMIFS('2024'!$AH$5:$AH$178,'2024'!$AG$5:$AG$178,">="&DATE(2029,4,1),'2024'!$AG$5:$AG$178,"<"&EDATE(DATE(2029,4,1),1)))/D94) | J94: =IF(N(D94)=0,"",(SUMIFS('2024'!$AI$5:$AI$178,'2024'!$AG$5:$AG$178,">="&DATE(2029,4,1),'2024'!$AG$5:$AG$178,"<"&EDATE(DATE(2029,4,1),1)))/D94)
B95: =IF(DATE(2029,5,1)>TODAY(),"",DATE(2029,5,1)) | C95: =IF(DATE(2029,5,1)>TODAY(),"",COUNTIFS('2024'!$AD$5:$AD$178,">="&DATE(2029,5,1),'2024'!$AD$5:$AD$178,"<"&EDATE(DATE(2029,5,1),1))) | D95: =IF(DATE(2029,5,1)>TODAY(),"",COUNTIFS('2024'!$AG$5:$AG$178,">="&DATE(2029,5,1),'2024'!$AG$5:$AG$178,"<"&EDATE(DATE(2029,5,1),1))) | E95: =IF(DATE(2029,5,1)>TODAY(),"",SUMIFS('2024'!$X$5:$X$178,'2024'!$AG$5:$AG$178,">="&DATE(2029,5,1),'2024'!$AG$5:$AG$178,"<"&EDATE(DATE(2029,5,1),1))) | F95: =IF(N(D95)=0,"",E95/D95) | G95: =IF(E95="","",E95/2) | H95: =IF(DATE(2029,5,1)>TODAY(),"",SUMIFS('2024'!$V$5:$V$178,'2024'!$AG$5:$AG$178,">="&DATE(2029,5,1),'2024'!$AG$5:$AG$178,"<"&EDATE(DATE(2029,5,1),1))) | I95: =IF(N(D95)=0,"",(SUMIFS('2024'!$AH$5:$AH$178,'2024'!$AG$5:$AG$178,">="&DATE(2029,5,1),'2024'!$AG$5:$AG$178,"<"&EDATE(DATE(2029,5,1),1)))/D95) | J95: =IF(N(D95)=0,"",(SUMIFS('2024'!$AI$5:$AI$178,'2024'!$AG$5:$AG$178,">="&DATE(2029,5,1),'2024'!$AG$5:$AG$178,"<"&EDATE(DATE(2029,5,1),1)))/D95)
B96: =IF(DATE(2029,6,1)>TODAY(),"",DATE(2029,6,1)) | C96: =IF(DATE(2029,6,1)>TODAY(),"",COUNTIFS('2024'!$AD$5:$AD$178,">="&DATE(2029,6,1),'2024'!$AD$5:$AD$178,"<"&EDATE(DATE(2029,6,1),1))) | D96: =IF(DATE(2029,6,1)>TODAY(),"",COUNTIFS('2024'!$AG$5:$AG$178,">="&DATE(2029,6,1),'2024'!$AG$5:$AG$178,"<"&EDATE(DATE(2029,6,1),1))) | E96: =IF(DATE(2029,6,1)>TODAY(),"",SUMIFS('2024'!$X$5:$X$178,'2024'!$AG$5:$AG$178,">="&DATE(2029,6,1),'2024'!$AG$5:$AG$178,"<"&EDATE(DATE(2029,6,1),1))) | F96: =IF(N(D96)=0,"",E96/D96) | G96: =IF(E96="","",E96/2) | H96: =IF(DATE(2029,6,1)>TODAY(),"",SUMIFS('2024'!$V$5:$V$178,'2024'!$AG$5:$AG$178,">="&DATE(2029,6,1),'2024'!$AG$5:$AG$178,"<"&EDATE(DATE(2029,6,1),1))) | I96: =IF(N(D96)=0,"",(SUMIFS('2024'!$AH$5:$AH$178,'2024'!$AG$5:$AG$178,">="&DATE(2029,6,1),'2024'!$AG$5:$AG$178,"<"&EDATE(DATE(2029,6,1),1)))/D96) | J96: =IF(N(D96)=0,"",(SUMIFS('2024'!$AI$5:$AI$178,'2024'!$AG$5:$AG$178,">="&DATE(2029,6,1),'2024'!$AG$5:$AG$178,"<"&EDATE(DATE(2029,6,1),1)))/D96)
B97: =IF(DATE(2029,7,1)>TODAY(),"",DATE(2029,7,1)) | C97: =IF(DATE(2029,7,1)>TODAY(),"",COUNTIFS('2024'!$AD$5:$AD$178,">="&DATE(2029,7,1),'2024'!$AD$5:$AD$178,"<"&EDATE(DATE(2029,7,1),1))) | D97: =IF(DATE(2029,7,1)>TODAY(),"",COUNTIFS('2024'!$AG$5:$AG$178,">="&DATE(2029,7,1),'2024'!$AG$5:$AG$178,"<"&EDATE(DATE(2029,7,1),1))) | E97: =IF(DATE(2029,7,1)>TODAY(),"",SUMIFS('2024'!$X$5:$X$178,'2024'!$AG$5:$AG$178,">="&DATE(2029,7,1),'2024'!$AG$5:$AG$178,"<"&EDATE(DATE(2029,7,1),1))) | F97: =IF(N(D97)=0,"",E97/D97) | G97: =IF(E97="","",E97/2) | H97: =IF(DATE(2029,7,1)>TODAY(),"",SUMIFS('2024'!$V$5:$V$178,'2024'!$AG$5:$AG$178,">="&DATE(2029,7,1),'2024'!$AG$5:$AG$178,"<"&EDATE(DATE(2029,7,1),1))) | I97: =IF(N(D97)=0,"",(SUMIFS('2024'!$AH$5:$AH$178,'2024'!$AG$5:$AG$178,">="&DATE(2029,7,1),'2024'!$AG$5:$AG$178,"<"&EDATE(DATE(2029,7,1),1)))/D97) | J97: =IF(N(D97)=0,"",(SUMIFS('2024'!$AI$5:$AI$178,'2024'!$AG$5:$AG$178,">="&DATE(2029,7,1),'2024'!$AG$5:$AG$178,"<"&EDATE(DATE(2029,7,1),1)))/D97)
B98: =IF(DATE(2029,8,1)>TODAY(),"",DATE(2029,8,1)) | C98: =IF(DATE(2029,8,1)>TODAY(),"",COUNTIFS('2024'!$AD$5:$AD$178,">="&DATE(2029,8,1),'2024'!$AD$5:$AD$178,"<"&EDATE(DATE(2029,8,1),1))) | D98: =IF(DATE(2029,8,1)>TODAY(),"",COUNTIFS('2024'!$AG$5:$AG$178,">="&DATE(2029,8,1),'2024'!$AG$5:$AG$178,"<"&EDATE(DATE(2029,8,1),1))) | E98: =IF(DATE(2029,8,1)>TODAY(),"",SUMIFS('2024'!$X$5:$X$178,'2024'!$AG$5:$AG$178,">="&DATE(2029,8,1),'2024'!$AG$5:$AG$178,"<"&EDATE(DATE(2029,8,1),1))) | F98: =IF(N(D98)=0,"",E98/D98) | G98: =IF(E98="","",E98/2) | H98: =IF(DATE(2029,8,1)>TODAY(),"",SUMIFS('2024'!$V$5:$V$178,'2024'!$AG$5:$AG$178,">="&DATE(2029,8,1),'2024'!$AG$5:$AG$178,"<"&EDATE(DATE(2029,8,1),1))) | I98: =IF(N(D98)=0,"",(SUMIFS('2024'!$AH$5:$AH$178,'2024'!$AG$5:$AG$178,">="&DATE(2029,8,1),'2024'!$AG$5:$AG$178,"<"&EDATE(DATE(2029,8,1),1)))/D98) | J98: =IF(N(D98)=0,"",(SUMIFS('2024'!$AI$5:$AI$178,'2024'!$AG$5:$AG$178,">="&DATE(2029,8,1),'2024'!$AG$5:$AG$178,"<"&EDATE(DATE(2029,8,1),1)))/D98)
B99: =IF(DATE(2029,9,1)>TODAY(),"",DATE(2029,9,1)) | C99: =IF(DATE(2029,9,1)>TODAY(),"",COUNTIFS('2024'!$AD$5:$AD$178,">="&DATE(2029,9,1),'2024'!$AD$5:$AD$178,"<"&EDATE(DATE(2029,9,1),1))) | D99: =IF(DATE(2029,9,1)>TODAY(),"",COUNTIFS('2024'!$AG$5:$AG$178,">="&DATE(2029,9,1),'2024'!$AG$5:$AG$178,"<"&EDATE(DATE(2029,9,1),1))) | E99: =IF(DATE(2029,9,1)>TODAY(),"",SUMIFS('2024'!$X$5:$X$178,'2024'!$AG$5:$AG$178,">="&DATE(2029,9,1),'2024'!$AG$5:$AG$178,"<"&EDATE(DATE(2029,9,1),1))) | F99: =IF(N(D99)=0,"",E99/D99) | G99: =IF(E99="","",E99/2) | H99: =IF(DATE(2029,9,1)>TODAY(),"",SUMIFS('2024'!$V$5:$V$178,'2024'!$AG$5:$AG$178,">="&DATE(2029,9,1),'2024'!$AG$5:$AG$178,"<"&EDATE(DATE(2029,9,1),1))) | I99: =IF(N(D99)=0,"",(SUMIFS('2024'!$AH$5:$AH$178,'2024'!$AG$5:$AG$178,">="&DATE(2029,9,1),'2024'!$AG$5:$AG$178,"<"&EDATE(DATE(2029,9,1),1)))/D99) | J99: =IF(N(D99)=0,"",(SUMIFS('2024'!$AI$5:$AI$178,'2024'!$AG$5:$AG$178,">="&DATE(2029,9,1),'2024'!$AG$5:$AG$178,"<"&EDATE(DATE(2029,9,1),1)))/D99)
B100: =IF(DATE(2029,10,1)>TODAY(),"",DATE(2029,10,1)) | C100: =IF(DATE(2029,10,1)>TODAY(),"",COUNTIFS('2024'!$AD$5:$AD$178,">="&DATE(2029,10,1),'2024'!$AD$5:$AD$178,"<"&EDATE(DATE(2029,10,1),1))) | D100: =IF(DATE(2029,10,1)>TODAY(),"",COUNTIFS('2024'!$AG$5:$AG$178,">="&DATE(2029,10,1),'2024'!$AG$5:$AG$178,"<"&EDATE(DATE(2029,10,1),1))) | E100: =IF(DATE(2029,10,1)>TODAY(),"",SUMIFS('2024'!$X$5:$X$178,'2024'!$AG$5:$AG$178,">="&DATE(2029,10,1),'2024'!$AG$5:$AG$178,"<"&EDATE(DATE(2029,10,1),1))) | F100: =IF(N(D100)=0,"",E100/D100) | G100: =IF(E100="","",E100/2) | H100: =IF(DATE(2029,10,1)>TODAY(),"",SUMIFS('2024'!$V$5:$V$178,'2024'!$AG$5:$AG$178,">="&DATE(2029,10,1),'2024'!$AG$5:$AG$178,"<"&EDATE(DATE(2029,10,1),1))) | I100: =IF(N(D100)=0,"",(SUMIFS('2024'!$AH$5:$AH$178,'2024'!$AG$5:$AG$178,">="&DATE(2029,10,1),'2024'!$AG$5:$AG$178,"<"&EDATE(DATE(2029,10,1),1)))/D100) | J100: =IF(N(D100)=0,"",(SUMIFS('2024'!$AI$5:$AI$178,'2024'!$AG$5:$AG$178,">="&DATE(2029,10,1),'2024'!$AG$5:$AG$178,"<"&EDATE(DATE(2029,10,1),1)))/D100)
B101: =IF(DATE(2029,11,1)>TODAY(),"",DATE(2029,11,1)) | C101: =IF(DATE(2029,11,1)>TODAY(),"",COUNTIFS('2024'!$AD$5:$AD$178,">="&DATE(2029,11,1),'2024'!$AD$5:$AD$178,"<"&EDATE(DATE(2029,11,1),1))) | D101: =IF(DATE(2029,11,1)>TODAY(),"",COUNTIFS('2024'!$AG$5:$AG$178,">="&DATE(2029,11,1),'2024'!$AG$5:$AG$178,"<"&EDATE(DATE(2029,11,1),1))) | E101: =IF(DATE(2029,11,1)>TODAY(),"",SUMIFS('2024'!$X$5:$X$178,'2024'!$AG$5:$AG$178,">="&DATE(2029,11,1),'2024'!$AG$5:$AG$178,"<"&EDATE(DATE(2029,11,1),1))) | F101: =IF(N(D101)=0,"",E101/D101) | G101: =IF(E101="","",E101/2) | H101: =IF(DATE(2029,11,1)>TODAY(),"",SUMIFS('2024'!$V$5:$V$178,'2024'!$AG$5:$AG$178,">="&DATE(2029,11,1),'2024'!$AG$5:$AG$178,"<"&EDATE(DATE(2029,11,1),1))) | I101: =IF(N(D101)=0,"",(SUMIFS('2024'!$AH$5:$AH$178,'2024'!$AG$5:$AG$178,">="&DATE(2029,11,1),'2024'!$AG$5:$AG$178,"<"&EDATE(DATE(2029,11,1),1)))/D101) | J101: =IF(N(D101)=0,"",(SUMIFS('2024'!$AI$5:$AI$178,'2024'!$AG$5:$AG$178,">="&DATE(2029,11,1),'2024'!$AG$5:$AG$178,"<"&EDATE(DATE(2029,11,1),1)))/D101)
B102: =IF(DATE(2029,12,1)>TODAY(),"",DATE(2029,12,1)) | C102: =IF(DATE(2029,12,1)>TODAY(),"",COUNTIFS('2024'!$AD$5:$AD$178,">="&DATE(2029,12,1),'2024'!$AD$5:$AD$178,"<"&EDATE(DATE(2029,12,1),1))) | D102: =IF(DATE(2029,12,1)>TODAY(),"",COUNTIFS('2024'!$AG$5:$AG$178,">="&DATE(2029,12,1),'2024'!$AG$5:$AG$178,"<"&EDATE(DATE(2029,12,1),1))) | E102: =IF(DATE(2029,12,1)>TODAY(),"",SUMIFS('2024'!$X$5:$X$178,'2024'!$AG$5:$AG$178,">="&DATE(2029,12,1),'2024'!$AG$5:$AG$178,"<"&EDATE(DATE(2029,12,1),1))) | F102: =IF(N(D102)=0,"",E102/D102) | G102: =IF(E102="","",E102/2) | H102: =IF(DATE(2029,12,1)>TODAY(),"",SUMIFS('2024'!$V$5:$V$178,'2024'!$AG$5:$AG$178,">="&DATE(2029,12,1),'2024'!$AG$5:$AG$178,"<"&EDATE(DATE(2029,12,1),1))) | I102: =IF(N(D102)=0,"",(SUMIFS('2024'!$AH$5:$AH$178,'2024'!$AG$5:$AG$178,">="&DATE(2029,12,1),'2024'!$AG$5:$AG$178,"<"&EDATE(DATE(2029,12,1),1)))/D102) | J102: =IF(N(D102)=0,"",(SUMIFS('2024'!$AI$5:$AI$178,'2024'!$AG$5:$AG$178,">="&DATE(2029,12,1),'2024'!$AG$5:$AG$178,"<"&EDATE(DATE(2029,12,1),1)))/D102)
B103: =IF(DATE(2030,1,1)>TODAY(),"",DATE(2030,1,1)) | C103: =IF(DATE(2030,1,1)>TODAY(),"",COUNTIFS('2024'!$AD$5:$AD$178,">="&DATE(2030,1,1),'2024'!$AD$5:$AD$178,"<"&EDATE(DATE(2030,1,1),1))) | D103: =IF(DATE(2030,1,1)>TODAY(),"",COUNTIFS('2024'!$AG$5:$AG$178,">="&DATE(2030,1,1),'2024'!$AG$5:$AG$178,"<"&EDATE(DATE(2030,1,1),1))) | E103: =IF(DATE(2030,1,1)>TODAY(),"",SUMIFS('2024'!$X$5:$X$178,'2024'!$AG$5:$AG$178,">="&DATE(2030,1,1),'2024'!$AG$5:$AG$178,"<"&EDATE(DATE(2030,1,1),1))) | F103: =IF(N(D103)=0,"",E103/D103) | G103: =IF(E103="","",E103/2) | H103: =IF(DATE(2030,1,1)>TODAY(),"",SUMIFS('2024'!$V$5:$V$178,'2024'!$AG$5:$AG$178,">="&DATE(2030,1,1),'2024'!$AG$5:$AG$178,"<"&EDATE(DATE(2030,1,1),1))) | I103: =IF(N(D103)=0,"",(SUMIFS('2024'!$AH$5:$AH$178,'2024'!$AG$5:$AG$178,">="&DATE(2030,1,1),'2024'!$AG$5:$AG$178,"<"&EDATE(DATE(2030,1,1),1)))/D103) | J103: =IF(N(D103)=0,"",(SUMIFS('2024'!$AI$5:$AI$178,'2024'!$AG$5:$AG$178,">="&DATE(2030,1,1),'2024'!$AG$5:$AG$178,"<"&EDATE(DATE(2030,1,1),1)))/D103)
B104: =IF(DATE(2030,2,1)>TODAY(),"",DATE(2030,2,1)) | C104: =IF(DATE(2030,2,1)>TODAY(),"",COUNTIFS('2024'!$AD$5:$AD$178,">="&DATE(2030,2,1),'2024'!$AD$5:$AD$178,"<"&EDATE(DATE(2030,2,1),1))) | D104: =IF(DATE(2030,2,1)>TODAY(),"",COUNTIFS('2024'!$AG$5:$AG$178,">="&DATE(2030,2,1),'2024'!$AG$5:$AG$178,"<"&EDATE(DATE(2030,2,1),1))) | E104: =IF(DATE(2030,2,1)>TODAY(),"",SUMIFS('2024'!$X$5:$X$178,'2024'!$AG$5:$AG$178,">="&DATE(2030,2,1),'2024'!$AG$5:$AG$178,"<"&EDATE(DATE(2030,2,1),1))) | F104: =IF(N(D104)=0,"",E104/D104) | G104: =IF(E104="","",E104/2) | H104: =IF(DATE(2030,2,1)>TODAY(),"",SUMIFS('2024'!$V$5:$V$178,'2024'!$AG$5:$AG$178,">="&DATE(2030,2,1),'2024'!$AG$5:$AG$178,"<"&EDATE(DATE(2030,2,1),1))) | I104: =IF(N(D104)=0,"",(SUMIFS('2024'!$AH$5:$AH$178,'2024'!$AG$5:$AG$178,">="&DATE(2030,2,1),'2024'!$AG$5:$AG$178,"<"&EDATE(DATE(2030,2,1),1)))/D104) | J104: =IF(N(D104)=0,"",(SUMIFS('2024'!$AI$5:$AI$178,'2024'!$AG$5:$AG$178,">="&DATE(2030,2,1),'2024'!$AG$5:$AG$178,"<"&EDATE(DATE(2030,2,1),1)))/D104)
...

Sheet 2024
A1: Empty placeholder. Copy the Statistics tab into your AUTOBONO sheet (right-click the tab → Copy to → Existing spreadsheet); there it reads your real 2024 tab.
