Workbook

Sheet Read me
B2: AUTOBONO — Car database (clean version)
B3: Built 07.10.2026 from your AUTOBONO Google Sheet ("2023" + "2024" tabs, data as of 25.07.2026). 148 cars imported. Your original sheet is not changed.
B5: THE TABS
B6: Summary — stock, money tied up, profit per year and brand, per-partner split. Fully automatic.
B7: Cars — ONE row per car, ever. Never start a new tab for a new year; filter by date instead.
B8: Expenses — ONE row per bill (transport, repair, tyres, ads…), with the Car ID. Adds up into "Extra costs" on Cars.
B9: Check these — problems I found in the old data (missing dates, profits that do not add up). Fix them, then delete the line.
B10: Lists — the values for every dropdown. Add a new brand or country here, never type it freely.
B12: HOW TO USE THE CARS TAB
B13: • Dark-blue headers = you type. Grey headers / grey cells = automatic formulas — never type over them.
B14: • New car bought: next free row, next Car ID (last is 149, so next is 150), Status = STOCK, fill purchase date and price.
B15: • Car sold: change Status to SOLD, fill Sale date, Sale price and "VAT & deductions" (VAT you pay on the sale). Profit appears automatically.
... B32: Because the data is now one clean table per thing, Google AppSheet (appsheet.com, sign in with Google) can turn this sheet into a phone app with forms, photos and dropdowns — without moving the data anywhere.

Sheet Summary
B2: AUTOBONO — Summary
B3: Everything on this tab is calculated from the Cars and Expenses tabs. Do not type here.
B5: Right now
B6: Cars in stock | C6: =COUNTIF(Cars!$B$2:$B$1000,"STOCK") -> 19
B7: Cars reserved | C7: =COUNTIF(Cars!$B$2:$B$1000,"RESERVED") -> 0
B8: Money tied up in stock (total cost, own purchases) | C8: =SUMIFS(Cars!$R$2:$R$1000,Cars!$B$2:$B$1000,"<>SOLD",Cars!$C$2:$C$1000,"Own purchase",Cars!$A$2:$A$1000,"<>") -> 173167.06
B9: Stock cars older than 90 days | C9: =COUNTIFS(Cars!$B$2:$B$1000,"<>SOLD",Cars!$A$2:$A$1000,"<>",Cars!$Z$2:$Z$1000,">90") -> 16
B10: Average days in stock (cars not yet sold) | C10: =IFERROR(AVERAGEIFS(Cars!$Z$2:$Z$1000,Cars!$B$2:$B$1000,"<>SOLD",Cars!$A$2:$A$1000,"<>"),"") -> 181.11111
B11: Cars with missing purchase date | C11: =COUNTIFS(Cars!$A$2:$A$1000,"<>",Cars!$O$2:$O$1000,"") -> 9
B13: Sold cars by year (by sale date)
B14: Year | C14: Cars sold | D14: Profit (€) | E14: Avg profit / car (€) | F14: Avg days in stock | G14: Per partner (€)
B15: 2023 | C15: =COUNTIFS(Cars!$B$2:$B$1000,"SOLD",Cars!$T$2:$T$1000,">="&DATE(2023,1,1),Cars!$T$2:$T$1000,"<"&DATE(2024,1,1)) -> 8 | D15: =SUMIFS(Cars!$X$2:$X$1000,Cars!$B$2:$B$1000,"SOLD",Cars!$T$2:$T$1000,">="&DATE(2023,1,1),Cars!$T$2:$T$1000,"<"&DATE(2024,1,1)) -> 11232.12 | E15: =IF(C15=0,"",D15/C15) -> 1404.015 | F15: =IFERROR(AVERAGEIFS(Cars!$Z$2:$Z$1000,Cars!$B$2:$B$1000,"SOLD",Cars!$T$2:$T$1000,">="&DATE(2023,1,1),Cars!$T$2:$T$1000,"<"&DATE(2024,1,1)),"") | G15: =D15/2 -> 5616.06
B16: 2024 | C16: =COUNTIFS(Cars!$B$2:$B$1000,"SOLD",Cars!$T$2:$T$1000,">="&DATE(2024,1,1),Cars!$T$2:$T$1000,"<"&DATE(2025,1,1)) -> 40 | D16: =SUMIFS(Cars!$X$2:$X$1000,Cars!$B$2:$B$1000,"SOLD",Cars!$T$2:$T$1000,">="&DATE(2024,1,1),Cars!$T$2:$T$1000,"<"&DATE(2025,1,1)) -> 72612 | E16: =IF(C16=0,"",D16/C16) -> 1815.3 | F16: =IFERROR(AVERAGEIFS(Cars!$Z$2:$Z$1000,Cars!$B$2:$B$1000,"SOLD",Cars!$T$2:$T$1000,">="&DATE(2024,1,1),Cars!$T$2:$T$1000,"<"&DATE(2025,1,1)),"") -> 71.775 | G16: =D16/2 -> 36306
B17: 2025 | C17: =COUNTIFS(Cars!$B$2:$B$1000,"SOLD",Cars!$T$2:$T$1000,">="&DATE(2025,1,1),Cars!$T$2:$T$1000,"<"&DATE(2026,1,1)) -> 52 | D17: =SUMIFS(Cars!$X$2:$X$1000,Cars!$B$2:$B$1000,"SOLD",Cars!$T$2:$T$1000,">="&DATE(2025,1,1),Cars!$T$2:$T$1000,"<"&DATE(2026,1,1)) -> 90415 | E17: =IF(C17=0,"",D17/C17) -> 1738.75 | F17: =IFERROR(AVERAGEIFS(Cars!$Z$2:$Z$1000,Cars!$B$2:$B$1000,"SOLD",Cars!$T$2:$T$1000,">="&DATE(2025,1,1),Cars!$T$2:$T$1000,"<"&DATE(2026,1,1)),"") -> 79.480769 | G17: =D17/2 -> 45207.5
B18: 2026 | C18: =COUNTIFS(Cars!$B$2:$B$1000,"SOLD",Cars!$T$2:$T$1000,">="&DATE(2026,1,1),Cars!$T$2:$T$1000,"<"&DATE(2027,1,1)) -> 29 | D18: =SUMIFS(Cars!$X$2:$X$1000,Cars!$B$2:$B$1000,"SOLD",Cars!$T$2:$T$1000,">="&DATE(2026,1,1),Cars!$T$2:$T$1000,"<"&DATE(2027,1,1)) -> 43659 | E18: =IF(C18=0,"",D18/C18) -> 1505.4828 | F18: =IFERROR(AVERAGEIFS(Cars!$Z$2:$Z$1000,Cars!$B$2:$B$1000,"SOLD",Cars!$T$2:$T$1000,">="&DATE(2026,1,1),Cars!$T$2:$T$1000,"<"&DATE(2027,1,1)),"") -> 110.96552 | G18: =D18/2 -> 21829.5
B19: 2027 | C19: =COUNTIFS(Cars!$B$2:$B$1000,"SOLD",Cars!$T$2:$T$1000,">="&DATE(2027,1,1),Cars!$T$2:$T$1000,"<"&DATE(2028,1,1)) -> 0 | D19: =SUMIFS(Cars!$X$2:$X$1000,Cars!$B$2:$B$1000,"SOLD",Cars!$T$2:$T$1000,">="&DATE(2027,1,1),Cars!$T$2:$T$1000,"<"&DATE(2028,1,1)) -> 0 | E19: =IF(C19=0,"",D19/C19) | F19: =IFERROR(AVERAGEIFS(Cars!$Z$2:$Z$1000,Cars!$B$2:$B$1000,"SOLD",Cars!$T$2:$T$1000,">="&DATE(2027,1,1),Cars!$T$2:$T$1000,"<"&DATE(2028,1,1)),"") | G19: =D19/2 -> 0
B20: All years | C20: =SUM(C15:C19) -> 129 | D20: =SUM(D15:D19) -> 217918.12 | E20: =IF(C20=0,"",D20/C20) -> 1689.2878 | G20: =D20/2 -> 108959.06
B22: Sold cars by brand (all years)
B23: Brand | C23: Cars sold | D23: Profit (€) | E23: Avg profit / car (€) | F23: Avg days in stock | G23: In stock now
B24: VW | C24: =COUNTIFS(Cars!$B$2:$B$1000,"SOLD",Cars!$D$2:$D$1000,B24) -> 41 | D24: =SUMIFS(Cars!$X$2:$X$1000,Cars!$B$2:$B$1000,"SOLD",Cars!$D$2:$D$1000,B24) -> 66335 | E24: =IF(C24=0,"",D24/C24) -> 1617.9268 | F24: =IFERROR(AVERAGEIFS(Cars!$Z$2:$Z$1000,Cars!$B$2:$B$1000,"SOLD",Cars!$D$2:$D$1000,B24),"") -> 76.538462 | G24: =COUNTIFS(Cars!$B$2:$B$1000,"<>SOLD",Cars!$D$2:$D$1000,B24) -> 6
B25: Škoda | C25: =COUNTIFS(Cars!$B$2:$B$1000,"SOLD",Cars!$D$2:$D$1000,B25) -> 33 | D25: =SUMIFS(Cars!$X$2:$X$1000,Cars!$B$2:$B$1000,"SOLD",Cars!$D$2:$D$1000,B25) -> 53948.99 | E25: =IF(C25=0,"",D25/C25) -> 1634.8179 | F25: =IFERROR(AVERAGEIFS(Cars!$Z$2:$Z$1000,Cars!$B$2:$B$1000,"SOLD",Cars!$D$2:$D$1000,B25),"") -> 97.6 | G25: =COUNTIFS(Cars!$B$2:$B$1000,"<>SOLD",Cars!$D$2:$D$1000,B25) -> 2
B26: Seat | C26: =COUNTIFS(Cars!$B$2:$B$1000,"SOLD",Cars!$D$2:$D$1000,B26) -> 18 | D26: =SUMIFS(Cars!$X$2:$X$1000,Cars!$B$2:$B$1000,"SOLD",Cars!$D$2:$D$1000,B26) -> 33098 | E26: =IF(C26=0,"",D26/C26) -> 1838.7778 | F26: =IFERROR(AVERAGEIFS(Cars!$Z$2:$Z$1000,Cars!$B$2:$B$1000,"SOLD",Cars!$D$2:$D$1000,B26),"") -> 91.5 | G26: =COUNTIFS(Cars!$B$2:$B$1000,"<>SOLD",Cars!$D$2:$D$1000,B26) -> 4
B27: Audi | C27: =COUNTIFS(Cars!$B$2:$B$1000,"SOLD",Cars!$D$2:$D$1000,B27) -> 12 | D27: =SUMIFS(Cars!$X$2:$X$1000,Cars!$B$2:$B$1000,"SOLD",Cars!$D$2:$D$1000,B27) -> 26413 | E27: =IF(C27=0,"",D27/C27) -> 2201.0833 | F27: =IFERROR(AVERAGEIFS(Cars!$Z$2:$Z$1000,Cars!$B$2:$B$1000,"SOLD",Cars!$D$2:$D$1000,B27),"") -> 60.833333 | G27: =COUNTIFS(Cars!$B$2:$B$1000,"<>SOLD",Cars!$D$2:$D$1000,B27) -> 1
B28: Mercedes-Benz | C28: =COUNTIFS(Cars!$B$2:$B$1000,"SOLD",Cars!$D$2:$D$1000,B28) -> 3 | D28: =SUMIFS(Cars!$X$2:$X$1000,Cars!$B$2:$B$1000,"SOLD",Cars!$D$2:$D$1000,B28) -> 5831 | E28: =IF(C28=0,"",D28/C28) -> 1943.6667 | F28: =IFERROR(AVERAGEIFS(Cars!$Z$2:$Z$1000,Cars!$B$2:$B$1000,"SOLD",Cars!$D$2:$D$1000,B28),"") -> 83.333333 | G28: =COUNTIFS(Cars!$B$2:$B$1000,"<>SOLD",Cars!$D$2:$D$1000,B28) -> 2
B29: Mazda | C29: =COUNTIFS(Cars!$B$2:$B$1000,"SOLD",Cars!$D$2:$D$1000,B29) -> 3 | D29: =SUMIFS(Cars!$X$2:$X$1000,Cars!$B$2:$B$1000,"SOLD",Cars!$D$2:$D$1000,B29) -> 6047.21 | E29: =IF(C29=0,"",D29/C29) -> 2015.7367 | F29: =IFERROR(AVERAGEIFS(Cars!$Z$2:$Z$1000,Cars!$B$2:$B$1000,"SOLD",Cars!$D$2:$D$1000,B29),"") -> 301.5 | G29: =COUNTIFS(Cars!$B$2:$B$1000,"<>SOLD",Cars!$D$2:$D$1000,B29) -> 1
B30: Alfa Romeo | C30: =COUNTIFS(Cars!$B$2:$B$1000,"SOLD",Cars!$D$2:$D$1000,B30) -> 3 | D30: =SUMIFS(Cars!$X$2:$X$1000,Cars!$B$2:$B$1000,"SOLD",Cars!$D$2:$D$1000,B30) -> 3807 | E30: =IF(C30=0,"",D30/C30) -> 1269 | F30: =IFERROR(AVERAGEIFS(Cars!$Z$2:$Z$1000,Cars!$B$2:$B$1000,"SOLD",Cars!$D$2:$D$1000,B30),"") -> 86.666667 | G30: =COUNTIFS(Cars!$B$2:$B$1000,"<>SOLD",Cars!$D$2:$D$1000,B30) -> 2
B31: BMW | C31: =COUNTIFS(Cars!$B$2:$B$1000,"SOLD",Cars!$D$2:$D$1000,B31) -> 3 | D31: =SUMIFS(Cars!$X$2:$X$1000,Cars!$B$2:$B$1000,"SOLD",Cars!$D$2:$D$1000,B31) -> 2270 | E31: =IF(C31=0,"",D31/C31) -> 756.66667 | F31: =IFERROR(AVERAGEIFS(Cars!$Z$2:$Z$1000,Cars!$B$2:$B$1000,"SOLD",Cars!$D$2:$D$1000,B31),"") -> 58.333333 | G31: =COUNTIFS(Cars!$B$2:$B$1000,"<>SOLD",Cars!$D$2:$D$1000,B31) -> 0
B32: Citroën | C32: =COUNTIFS(Cars!$B$2:$B$1000,"SOLD",Cars!$D$2:$D$1000,B32) -> 3 | D32: =SUMIFS(Cars!$X$2:$X$1000,Cars!$B$2:$B$1000,"SOLD",Cars!$D$2:$D$1000,B32) -> 5930 | E32: =IF(C32=0,"",D32/C32) -> 1976.6667 | F32: =IFERROR(AVERAGEIFS(Cars!$Z$2:$Z$1000,Cars!$B$2:$B$1000,"SOLD",Cars!$D$2:$D$1000,B32),"") -> 93.333333 | G32: =COUNTIFS(Cars!$B$2:$B$1000,"<>SOLD",Cars!$D$2:$D$1000,B32) -> 0
B33: Hyundai | C33: =COUNTIFS(Cars!$B$2:$B$1000,"SOLD",Cars!$D$2:$D$1000,B33) -> 2 | D33: =SUMIFS(Cars!$X$2:$X$1000,Cars!$B$2:$B$1000,"SOLD",Cars!$D$2:$D$1000,B33) -> 2496.21 | E33: =IF(C33=0,"",D33/C33) -> 1248.105 | F33: =IFERROR(AVERAGEIFS(Cars!$Z$2:$Z$1000,Cars!$B$2:$B$1000,"SOLD",Cars!$D$2:$D$1000,B33),"") -> 19 | G33: =COUNTIFS(Cars!$B$2:$B$1000,"<>SOLD",Cars!$D$2:$D$1000,B33) -> 0
B34: Kia | C34: =COUNTIFS(Cars!$B$2:$B$1000,"SOLD",Cars!$D$2:$D$1000,B34) -> 2 | D34: =SUMIFS(Cars!$X$2:$X$1000,Cars!$B$2:$B$1000,"SOLD",Cars!$D$2:$D$1000,B34) -> 2264.71 | E34: =IF(C34=0,"",D34/C34) -> 1132.355 | F34: =IFERROR(AVERAGEIFS(Cars!$Z$2:$Z$1000,Cars!$B$2:$B$1000,"SOLD",Cars!$D$2:$D$1000,B34),"") -> 35 | G34: =COUNTIFS(Cars!$B$2:$B$1000,"<>SOLD",Cars!$D$2:$D$1000,B34) -> 0
B35: Maserati | C35: =COUNTIFS(Cars!$B$2:$B$1000,"SOLD",Cars!$D$2:$D$1000,B35) -> 1 | D35: =SUMIFS(Cars!$X$2:$X$1000,Cars!$B$2:$B$1000,"SOLD",Cars!$D$2:$D$1000,B35) -> 1250 | E35: =IF(C35=0,"",D35/C35) -> 1250 | F35: =IFERROR(AVERAGEIFS(Cars!$Z$2:$Z$1000,Cars!$B$2:$B$1000,"SOLD",Cars!$D$2:$D$1000,B35),"") -> 6 | G35: =COUNTIFS(Cars!$B$2:$B$1000,"<>SOLD",Cars!$D$2:$D$1000,B35) -> 0
... B39: Volvo | C39: =COUNTIFS(Cars!$B$2:$B$1000,"SOLD",Cars!$D$2:$D$1000,B39) -> 2 | D39: =SUMIFS(Cars!$X$2:$X$1000,Cars!$B$2:$B$1000,"SOLD",Cars!$D$2:$D$1000,B39) -> 1954 | E39: =IF(C39=0,"",D39/C39) -> 977 | F39: =IFERROR(AVERAGEIFS(Cars!$Z$2:$Z$1000,Cars!$B$2:$B$1000,"SOLD",Cars!$D$2:$D$1000,B39),"") -> 126 | G39: =COUNTIFS(Cars!$B$2:$B$1000,"<>SOLD",Cars!$D$2:$D$1000,B39) -> 0
B41: Expenses — who paid (to settle between partners)
B42: Paid by | C42: Total (€)
B43: Partner 1 | C43: =SUMIFS(Expenses!$E$2:$E$3000,Expenses!$F$2:$F$3000,B43,Expenses!$B$2:$B$3000,"<>EXAMPLE") -> 0
B44: Partner 2 | C44: =SUMIFS(Expenses!$E$2:$E$3000,Expenses!$F$2:$F$3000,B44,Expenses!$B$2:$B$3000,"<>EXAMPLE") -> 0
B45: Company account | C45: =SUMIFS(Expenses!$E$2:$E$3000,Expenses!$F$2:$F$3000,B45,Expenses!$B$2:$B$3000,"<>EXAMPLE") -> 0

Sheet Cars
A1: Car ID | B1: Status | C1: Deal type | D1: Brand | E1: Model | F1: Trim | G1: First registration | H1: Engine | I1: Gearbox | J1: Drive | K1: Mileage (km) | L1: VIN | M1: Bought in (country) | N1: VAT scheme (M/D) | O1: Purchase date | P1: Purchase price (€) | Q1: Extra costs (€) [from Expenses] | R1: Total cost (€) | S1: Asking price (€) | T1: Sale date | U1: Sale price (€) | V1: VAT & deductions (€) | W1: Commission (€) [consignment only] | X1: Profit (€) | Y1: Margin % of cost | Z1: Days in stock | AA1: Sale month | AB1: Profit per partner (€) [50/50] | AC1: Notes
A2: 1 | B2: SOLD | C2: Own purchase | D2: Hyundai | E2: i40 CW | F2: Business | H2: 1.7 CRDi 104 kW | I2: DCT7 | K2: 159713 | M2: CZ | N2: M | P2: 11103.79 | Q2: =IF(A2="","",SUMIF(Expenses!$B$2:$B$3000,A2,Expenses!$E$2:$E$3000)) -> 0 | R2: =IF(A2="","",N(P2)+N(Q2)) -> 11103.79 | T2: 45034 | U2: 12800 | V2: 0 | X2: =IF(B2<>"SOLD","",IF(C2="Consignment",N(W2)-R2,N(U2)-R2-N(V2))) -> 1696.21 | Y2: =IF(OR(X2="",N(R2)=0),"",X2/R2) -> 0.15275955 | Z2: =IF(O2="","",IF(T2="",TODAY(),T2)-O2) | AA2: =IF(T2="","",TEXT(T2,"YYYY-MM")) -> 2023-04 | AB2: =IF(X2="","",X2/2) -> 848.105
A3: 2 | B3: SOLD | C3: Own purchase | D3: Kia | E3: Cee'd SW | F3: Gold | G3: 43678 | H3: 1.6 CRDi 85 kW | I3: MT6 | K3: 118900 | M3: BE | N3: D | P3: 12942.29 | Q3: =IF(A3="","",SUMIF(Expenses!$B$2:$B$3000,A3,Expenses!$E$2:$E$3000)) -> 0 | R3: =IF(A3="","",N(P3)+N(Q3)) -> 12942.29 | T3: 45115 | U3: 14350 | V3: 0 | X3: =IF(B3<>"SOLD","",IF(C3="Consignment",N(W3)-R3,N(U3)-R3-N(V3))) -> 1407.71 | Y3: =IF(OR(X3="",N(R3)=0),"",X3/R3) -> 0.10876823 | Z3: =IF(O3="","",IF(T3="",TODAY(),T3)-O3) | AA3: =IF(T3="","",TEXT(T3,"YYYY-MM")) -> 2023-07 | AB3: =IF(X3="","",X3/2) -> 703.855
A4: 3 | B4: SOLD | C4: Own purchase | D4: Škoda | E4: Superb Combi | F4: Style | G4: 42461 | H4: 2.0 TDI 110 kW | I4: DSG6 | K4: 194400 | M4: BE | N4: M | P4: 12955.84 | Q4: =IF(A4="","",SUMIF(Expenses!$B$2:$B$3000,A4,Expenses!$E$2:$E$3000)) -> 0 | R4: =IF(A4="","",N(P4)+N(Q4)) -> 12955.84 | T4: 45236 | U4: 15400 | V4: 477.57 | X4: =IF(B4<>"SOLD","",IF(C4="Consignment",N(W4)-R4,N(U4)-R4-N(V4))) -> 1966.59 | Y4: =IF(OR(X4="",N(R4)=0),"",X4/R4) -> 0.15179178 | Z4: =IF(O4="","",IF(T4="",TODAY(),T4)-O4) | AA4: =IF(T4="","",TEXT(T4,"YYYY-MM")) -> 2023-11 | AB4: =IF(X4="","",X4/2) -> 983.295
A5: 4 | B5: SOLD | C5: Own purchase | D5: Mazda | E5: 6 | F5: Revolution | G5: 41395 | H5: 2.5 Skyactiv-G192 | I5: AT6 | K5: 146187 | M5: DE | N5: M | P5: 12873.79 | Q5: =IF(A5="","",SUMIF(Expenses!$B$2:$B$3000,A5,Expenses!$E$2:$E$3000)) -> 0 | R5: =IF(A5="","",N(P5)+N(Q5)) -> 12873.79 | T5: 45120 | U5: 13950 | V5: 0 | X5: =IF(B5<>"SOLD","",IF(C5="Consignment",N(W5)-R5,N(U5)-R5-N(V5))) -> 1076.21 | Y5: =IF(OR(X5="",N(R5)=0),"",X5/R5) -> 0.083596983 | Z5: =IF(O5="","",IF(T5="",TODAY(),T5)-O5) | AA5: =IF(T5="","",TEXT(T5,"YYYY-MM")) -> 2023-07 | AB5: =IF(X5="","",X5/2) -> 538.105
A6: 5 | B6: SOLD | C6: Own purchase | D6: Škoda | E6: Kodiaq | F6: Ambition | G6: 43009 | H6: 1.4 TSI 92 kW | I6: MT6 | K6: 178383 | M6: NL | N6: D | P6: 15569 | Q6: =IF(A6="","",SUMIF(Expenses!$B$2:$B$3000,A6,Expenses!$E$2:$E$3000)) -> 0 | R6: =IF(A6="","",N(P6)+N(Q6)) -> 15569 | T6: 45215 | U6: 17000 | V6: 0 | X6: =IF(B6<>"SOLD","",IF(C6="Consignment",N(W6)-R6,N(U6)-R6-N(V6))) -> 1431 | Y6: =IF(OR(X6="",N(R6)=0),"",X6/R6) -> 0.091913418 | Z6: =IF(O6="","",IF(T6="",TODAY(),T6)-O6) | AA6: =IF(T6="","",TEXT(T6,"YYYY-MM")) -> 2023-10 | AB6: =IF(X6="","",X6/2) -> 715.5
A7: 6 | B7: SOLD | C7: Own purchase | D7: VW | E7: Touran | F7: Highline | G7: 43678 | H7: 2.0 TDI 110 kW | I7: DSG7 | K7: 188761 | M7: DE | N7: D | P7: 14594 | Q7: =IF(A7="","",SUMIF(Expenses!$B$2:$B$3000,A7,Expenses!$E$2:$E$3000)) -> 0 | R7: =IF(A7="","",N(P7)+N(Q7)) -> 14594 | T7: 45209 | U7: 16050 | V7: 0 | X7: =IF(B7<>"SOLD","",IF(C7="Consignment",N(W7)-R7,N(U7)-R7-N(V7))) -> 1456 | Y7: =IF(OR(X7="",N(R7)=0),"",X7/R7) -> 0.099767028 | Z7: =IF(O7="","",IF(T7="",TODAY(),T7)-O7) | AA7: =IF(T7="","",TEXT(T7,"YYYY-MM")) -> 2023-10 | AB7: =IF(X7="","",X7/2) -> 728
A8: 7 | B8: STOCK | C8: Own purchase | D8: Audi | E8: A4 Avant | F8: Basis | G8: 43282 | H8: 2.0 TDI 110 kW | I8: DSG7 | K8: 177534 | M8: IT | N8: D | P8: 12945 | Q8: =IF(A8="","",SUMIF(Expenses!$B$2:$B$3000,A8,Expenses!$E$2:$E$3000)) -> 0 | R8: =IF(A8="","",N(P8)+N(Q8)) -> 12945 | X8: =IF(B8<>"SOLD","",IF(C8="Consignment",N(W8)-R8,N(U8)-R8-N(V8))) | Y8: =IF(OR(X8="",N(R8)=0),"",X8/R8) | Z8: =IF(O8="","",IF(T8="",TODAY(),T8)-O8) | AA8: =IF(T8="","",TEXT(T8,"YYYY-MM")) | AB8: =IF(X8="","",X8/2)
A9: 8 | B9: SOLD | C9: Own purchase | D9: Škoda | E9: Octavia Combi | F9: Ambition | G9: 43160 | H9: 1.0 TSI 85 kW | I9: DSG7 | K9: 188436 | M9: NL | N9: D | P9: 10029.6 | Q9: =IF(A9="","",SUMIF(Expenses!$B$2:$B$3000,A9,Expenses!$E$2:$E$3000)) -> 0 | R9: =IF(A9="","",N(P9)+N(Q9)) -> 10029.6 | T9: 45238 | U9: 11000 | V9: 0 | X9: =IF(B9<>"SOLD","",IF(C9="Consignment",N(W9)-R9,N(U9)-R9-N(V9))) -> 970.4 | Y9: =IF(OR(X9="",N(R9)=0),"",X9/R9) -> 0.096753609 | Z9: =IF(O9="","",IF(T9="",TODAY(),T9)-O9) | AA9: =IF(T9="","",TEXT(T9,"YYYY-MM")) -> 2023-11 | AB9: =IF(X9="","",X9/2) -> 485.2
A10: 9 | B10: SOLD | C10: Own purchase | D10: VW | E10: Passat | F10: Comfortline | G10: 42767 | H10: 2.0 TDI 110 kW | I10: DSG6 | K10: 185900 | M10: SK | N10: D | P10: 13622 | Q10: =IF(A10="","",SUMIF(Expenses!$B$2:$B$3000,A10,Expenses!$E$2:$E$3000)) -> 0 | R10: =IF(A10="","",N(P10)+N(Q10)) -> 13622 | T10: 45289 | U10: 14850 | V10: 0 | X10: =IF(B10<>"SOLD","",IF(C10="Consignment",N(W10)-R10,N(U10)-R10-N(V10))) -> 1228 | Y10: =IF(OR(X10="",N(R10)=0),"",X10/R10) -> 0.09014829 | Z10: =IF(O10="","",IF(T10="",TODAY(),T10)-O10) | AA10: =IF(T10="","",TEXT(T10,"YYYY-MM")) -> 2023-12 | AB10: =IF(X10="","",X10/2) -> 614
A11: 10 | B11: SOLD | C11: Own purchase | D11: VW | E11: Passat Variant R-line | F11: Highline Business | G11: 42248 | H11: 1.8 TSI 132 kW | I11: DSG7 | K11: 187200 | M11: NL | N11: D | O11: 45232 | P11: 12362.56 | Q11: =IF(A11="","",SUMIF(Expenses!$B$2:$B$3000,A11,Expenses!$E$2:$E$3000)) -> 0 | R11: =IF(A11="","",N(P11)+N(Q11)) -> 12362.56 | T11: 45449 | U11: 12900 | V11: 2066.44 | X11: =IF(B11<>"SOLD","",IF(C11="Consignment",N(W11)-R11,N(U11)-R11-N(V11))) -> -1529 | Y11: =IF(OR(X11="",N(R11)=0),"",X11/R11) -> -0.12367989 | Z11: =IF(O11="","",IF(T11="",TODAY(),T11)-O11) -> 217 | AA11: =IF(T11="","",TEXT(T11,"YYYY-MM")) -> 2024-06 | AB11: =IF(X11="","",X11/2) -> -764.5
A12: 11 | B12: SOLD | C12: Own purchase | D12: VW | E12: Touran R-line | F12: Highline | G12: 43101 | H12: 1.8 TSI 132 kW | I12: DSG7 | K12: 151400 | M12: NL | N12: M | O12: 45236 | P12: 17778.05 | Q12: =IF(A12="","",SUMIF(Expenses!$B$2:$B$3000,A12,Expenses!$E$2:$E$3000)) -> 0 | R12: =IF(A12="","",N(P12)+N(Q12)) -> 17778.05 | T12: 45400 | U12: 18390 | V12: -0.05 | X12: =IF(B12<>"SOLD","",IF(C12="Consignment",N(W12)-R12,N(U12)-R12-N(V12))) -> 612 | Y12: =IF(OR(X12="",N(R12)=0),"",X12/R12) -> 0.034424473 | Z12: =IF(O12="","",IF(T12="",TODAY(),T12)-O12) -> 164 | AA12: =IF(T12="","",TEXT(T12,"YYYY-MM")) -> 2024-04 | AB12: =IF(X12="","",X12/2) -> 306
A13: 12 | B13: SOLD | C13: Own purchase | D13: Škoda | E13: Kodiaq | F13: Style | G13: 42887 | H13: 1.4 TSI 110 kW | I13: DSG6 | K13: 154100 | M13: FR | N13: M | O13: 45233 | P13: 18000.19 | Q13: =IF(A13="","",SUMIF(Expenses!$B$2:$B$3000,A13,Expenses!$E$2:$E$3000)) -> 0 | R13: =IF(A13="","",N(P13)+N(Q13)) -> 18000.19 | T13: 45380 | U13: 20500 | V13: -0.19 | X13: =IF(B13<>"SOLD","",IF(C13="Consignment",N(W13)-R13,N(U13)-R13-N(V13))) -> 2500 | Y13: =IF(OR(X13="",N(R13)=0),"",X13/R13) -> 0.13888742 | Z13: =IF(O13="","",IF(T13="",TODAY(),T13)-O13) -> 147 | AA13: =IF(T13="","",TEXT(T13,"YYYY-MM")) -> 2024-03 | AB13: =IF(X13="","",X13/2) -> 1250
A14: 13 | B14: SOLD | C14: Own purchase | D14: Seat | E14: Ateca | F14: Style | G14: 43862 | H14: 1.0 TSI 85 kW | I14: MT6 | K14: 176499 | M14: NL | N14: D | O14: 45243 | P14: 13424 | Q14: =IF(A14="","",SUMIF(Expenses!$B$2:$B$3000,A14,Expenses!$E$2:$E$3000)) -> 0 | R14: =IF(A14="","",N(P14)+N(Q14)) -> 13424 | T14: 45386 | U14: 13990 | V14: -10 | X14: =IF(B14<>"SOLD","",IF(C14="Consignment",N(W14)-R14,N(U14)-R14-N(V14))) -> 576 | Y14: =IF(OR(X14="",N(R14)=0),"",X14/R14) -> 0.042908224 | Z14: =IF(O14="","",IF(T14="",TODAY(),T14)-O14) -> 143 | AA14: =IF(T14="","",TEXT(T14,"YYYY-MM")) -> 2024-04 | AB14: =IF(X14="","",X14/2) -> 288
A15: 15 | B15: SOLD | C15: Own purchase | D15: Seat | E15: Arona | F15: Style | G15: 43497 | H15: 1.6 TDI 70 kW | I15: MT6 | K15: 67396 | M15: BE | N15: M | O15: 45251 | P15: 12564.68 | Q15: =IF(A15="","",SUMIF(Expenses!$B$2:$B$3000,A15,Expenses!$E$2:$E$3000)) -> 0 | R15: =IF(A15="","",N(P15)+N(Q15)) -> 12564.68 | T15: 45339 | U15: 14500 | V15: 0.32 | X15: =IF(B15<>"SOLD","",IF(C15="Consignment",N(W15)-R15,N(U15)-R15-N(V15))) -> 1935 | Y15: =IF(OR(X15="",N(R15)=0),"",X15/R15) -> 0.15400313 | Z15: =IF(O15="","",IF(T15="",TODAY(),T15)-O15) -> 88 | AA15: =IF(T15="","",TEXT(T15,"YYYY-MM")) -> 2024-02 | AB15: =IF(X15="","",X15/2) -> 967.5
A16: 16 | B16: SOLD | C16: Own purchase | D16: Audi | E16: A4 Avant | F16: Basis | G16: 42370 | H16: 2.0 TDI 110 kW | I16: DSG7 | K16: 211000 | M16: DK | N16: D | O16: 45352 | P16: 9898.67 | Q16: =IF(A16="","",SUMIF(Expenses!$B$2:$B$3000,A16,Expenses!$E$2:$E$3000)) -> 0 | R16: =IF(A16="","",N(P16)+N(Q16)) -> 9898.67 | T16: 45384 | U16: 14000 | V16: 2333.33 | X16: =IF(B16<>"SOLD","",IF(C16="Consignment",N(W16)-R16,N(U16)-R16-N(V16))) -> 1768 | Y16: =IF(OR(X16="",N(R16)=0),"",X16/R16) -> 0.17860985 | Z16: =IF(O16="","",IF(T16="",TODAY(),T16)-O16) -> 32 | AA16: =IF(T16="","",TEXT(T16,"YYYY-MM")) -> 2024-04 | AB16: =IF(X16="","",X16/2) -> 884
A17: 17 | B17: SOLD | C17: Own purchase | D17: Volvo | E17: V60 | F17: Cross Country | G17: 43009 | H17: 2.0 D4 140 kW | I17: AT8 | K17: 196000 | M17: DE | N17: M | O17: 45380 | P17: 13305 | Q17: =IF(A17="","",SUMIF(Expenses!$B$2:$B$3000,A17,Expenses!$E$2:$E$3000)) -> 0 | R17: =IF(A17="","",N(P17)+N(Q17)) -> 13305 | T17: 45418 | U17: 13900 | V17: 0 | X17: =IF(B17<>"SOLD","",IF(C17="Consignment",N(W17)-R17,N(U17)-R17-N(V17))) -> 595 | Y17: =IF(OR(X17="",N(R17)=0),"",X17/R17) -> 0.04472003 | Z17: =IF(O17="","",IF(T17="",TODAY(),T17)-O17) -> 38 | AA17: =IF(T17="","",TEXT(T17,"YYYY-MM")) -> 2024-05 | AB17: =IF(X17="","",X17/2) -> 297.5
A18: 18 | B18: SOLD | C18: Own purchase | D18: Mercedes-Benz | E18: C 220d T-Modell | F18: Business Plus | G18: 43009 | H18: 2.2d 125 kW | I18: AT9 | K18: 212000 | M18: DK | N18: D | O18: 45394 | P18: 11629 | Q18: =IF(A18="","",SUMIF(Expenses!$B$2:$B$3000,A18,Expenses!$E$2:$E$3000)) -> 0 | R18: =IF(A18="","",N(P18)+N(Q18)) -> 11629 | T18: 45537 | U18: 14900 | V18: 2483 | X18: =IF(B18<>"SOLD","",IF(C18="Consignment",N(W18)-R18,N(U18)-R18-N(V18))) -> 788 | Y18: =IF(OR(X18="",N(R18)=0),"",X18/R18) -> 0.06776163 | Z18: =IF(O18="","",IF(T18="",TODAY(),T18)-O18) -> 143 | AA18: =IF(T18="","",TEXT(T18,"YYYY-MM")) -> 2024-09 | AB18: =IF(X18="","",X18/2) -> 394
A19: 19 | B19: SOLD | C19: Own purchase | D19: Škoda | E19: Octavia Combi | F19: Style | G19: 43405 | H19: 1.0 TSI 85 kW | I19: MT6 | K19: 201000 | M19: NL | N19: D | O19: 45412 | P19: 8067 | Q19: =IF(A19="","",SUMIF(Expenses!$B$2:$B$3000,A19,Expenses!$E$2:$E$3000)) -> 0 | R19: =IF(A19="","",N(P19)+N(Q19)) -> 8067 | T19: 45451 | U19: 10500 | V19: 0 | X19: =IF(B19<>"SOLD","",IF(C19="Consignment",N(W19)-R19,N(U19)-R19-N(V19))) -> 2433 | Y19: =IF(OR(X19="",N(R19)=0),"",X19/R19) -> 0.30159911 | Z19: =IF(O19="","",IF(T19="",TODAY(),T19)-O19) -> 39 | AA19: =IF(T19="","",TEXT(T19,"YYYY-MM")) -> 2024-06 | AB19: =IF(X19="","",X19/2) -> 1216.5
A20: 20 | B20: SOLD | C20: Own purchase | D20: Škoda | E20: Octavia Combi | F20: Style | G20: 43891 | H20: 2.0 TDI 110 kW | I20: DSG7 | K20: 193000 | M20: DK | N20: D | O20: 45415 | P20: 10345 | Q20: =IF(A20="","",SUMIF(Expenses!$B$2:$B$3000,A20,Expenses!$E$2:$E$3000)) -> 0 | R20: =IF(A20="","",N(P20)+N(Q20)) -> 10345 | T20: 45471 | U20: 14490 | V20: 2415 | X20: =IF(B20<>"SOLD","",IF(C20="Consignment",N(W20)-R20,N(U20)-R20-N(V20))) -> 1730 | Y20: =IF(OR(X20="",N(R20)=0),"",X20/R20) -> 0.16723055 | Z20: =IF(O20="","",IF(T20="",TODAY(),T20)-O20) -> 56 | AA20: =IF(T20="","",TEXT(T20,"YYYY-MM")) -> 2024-06 | AB20: =IF(X20="","",X20/2) -> 865
A21: 21 | B21: SOLD | C21: Own purchase | D21: Audi | E21: A4 Avant | F21: S-line | G21: 42430 | H21: 2.0 TDI 140 kW | I21: DSG7 | K21: 160000 | M21: DK | N21: D | O21: 45422 | P21: 12529 | Q21: =IF(A21="","",SUMIF(Expenses!$B$2:$B$3000,A21,Expenses!$E$2:$E$3000)) -> 0 | R21: =IF(A21="","",N(P21)+N(Q21)) -> 12529 | T21: 45443 | U21: 18700 | V21: 3117 | X21: =IF(B21<>"SOLD","",IF(C21="Consignment",N(W21)-R21,N(U21)-R21-N(V21))) -> 3054 | Y21: =IF(OR(X21="",N(R21)=0),"",X21/R21) -> 0.24375449 | Z21: =IF(O21="","",IF(T21="",TODAY(),T21)-O21) -> 21 | AA21: =IF(T21="","",TEXT(T21,"YYYY-MM")) -> 2024-05 | AB21: =IF(X21="","",X21/2) -> 1527
A22: 22 | B22: SOLD | C22: Own purchase | D22: Audi | E22: Q5 quattro | F22: Basis | G22: 40787 | H22: 3.0 TDI 176 kW 4x4 | I22: DSG7 | J22: 4x4 | K22: 182000 | M22: IT | N22: D | O22: 45444 | P22: 9024 | Q22: =IF(A22="","",SUMIF(Expenses!$B$2:$B$3000,A22,Expenses!$E$2:$E$3000)) -> 0 | R22: =IF(A22="","",N(P22)+N(Q22)) -> 9024 | T22: 45508 | U22: 13100 | V22: 2183 | X22: =IF(B22<>"SOLD","",IF(C22="Consignment",N(W22)-R22,N(U22)-R22-N(V22))) -> 1893 | Y22: =IF(OR(X22="",N(R22)=0),"",X22/R22) -> 0.20977394 | Z22: =IF(O22="","",IF(T22="",TODAY(),T22)-O22) -> 64 | AA22: =IF(T22="","",TEXT(T22,"YYYY-MM")) -> 2024-08 | AB22: =IF(X22="","",X22/2) -> 946.5
A23: 23 | B23: SOLD | C23: Own purchase | D23: Mazda | E23: 6 | F23: Revolution | G23: 43009 | H23: 2.5i 141 kW | I23: AT6 | K23: 159000 | M23: DK | N23: M | O23: 45429 | P23: 14215 | Q23: =IF(A23="","",SUMIF(Expenses!$B$2:$B$3000,A23,Expenses!$E$2:$E$3000)) -> 0 | R23: =IF(A23="","",N(P23)+N(Q23)) -> 14215 | T23: 45519 | U23: 16300 | V23: 0 | X23: =IF(B23<>"SOLD","",IF(C23="Consignment",N(W23)-R23,N(U23)-R23-N(V23))) -> 2085 | Y23: =IF(OR(X23="",N(R23)=0),"",X23/R23) -> 0.14667605 | Z23: =IF(O23="","",IF(T23="",TODAY(),T23)-O23) -> 90 | AA23: =IF(T23="","",TEXT(T23,"YYYY-MM")) -> 2024-08 | AB23: =IF(X23="","",X23/2) -> 1042.5
A24: 24 | B24: SOLD | C24: Own purchase | D24: Škoda | E24: Octavia Combi | F24: Style | G24: 43891 | H24: 2.0 TDI 110 kW | I24: DSG7 | K24: 259000 | M24: DK | N24: D | O24: 45429 | P24: 8387 | Q24: =IF(A24="","",SUMIF(Expenses!$B$2:$B$3000,A24,Expenses!$E$2:$E$3000)) -> 0 | R24: =IF(A24="","",N(P24)+N(Q24)) -> 8387 | T24: 45470 | U24: 10750 | V24: 1792 | X24: =IF(B24<>"SOLD","",IF(C24="Consignment",N(W24)-R24,N(U24)-R24-N(V24))) -> 571 | Y24: =IF(OR(X24="",N(R24)=0),"",X24/R24) -> 0.068081555 | Z24: =IF(O24="","",IF(T24="",TODAY(),T24)-O24) -> 41 | AA24: =IF(T24="","",TEXT(T24,"YYYY-MM")) -> 2024-06 | AB24: =IF(X24="","",X24/2) -> 285.5
A25: 25 | B25: SOLD | C25: Own purchase | D25: Škoda | E25: Octavia Combi | F25: Style | G25: 42887 | H25: 1.0 TSI 85 kW | I25: DSG7 | K25: 188000 | M25: DE | N25: M | O25: 45453 | P25: 8221 | Q25: =IF(A25="","",SUMIF(Expenses!$B$2:$B$3000,A25,Expenses!$E$2:$E$3000)) -> 0 | R25: =IF(A25="","",N(P25)+N(Q25)) -> 8221 | T25: 45526 | U25: 10000 | V25: 0 | X25: =IF(B25<>"SOLD","",IF(C25="Consignment",N(W25)-R25,N(U25)-R25-N(V25))) -> 1779 | Y25: =IF(OR(X25="",N(R25)=0),"",X25/R25) -> 0.21639703 | Z25: =IF(O25="","",IF(T25="",TODAY(),T25)-O25) -> 73 | AA25: =IF(T25="","",TEXT(T25,"YYYY-MM")) -> 2024-08 | AB25: =IF(X25="","",X25/2) -> 889.5
A26: 26 | B26: SOLD | C26: Own purchase | D26: VW | E26: Passat Variant | F26: Highline | G26: 43800 | H26: 1.5 TSI 110 kW | I26: MT6 | K26: 144000 | M26: DE | N26: D | O26: 45456 | P26: 18813.42 | Q26: =IF(A26="","",SUMIF(Expenses!$B$2:$B$3000,A26,Expenses!$E$2:$E$3000)) -> 0 | R26: =IF(A26="","",N(P26)+N(Q26)) -> 18813.42 | T26: 45476 | U26: 20800 | V26: -0.42 | X26: =IF(B26<>"SOLD","",IF(C26="Consignment",N(W26)-R26,N(U26)-R26-N(V26))) -> 1987 | Y26: =IF(OR(X26="",N(R26)=0),"",X26/R26) -> 0.1056161 | Z26: =IF(O26="","",IF(T26="",TODAY(),T26)-O26) -> 20 | AA26: =IF(T26="","",TEXT(T26,"YYYY-MM")) -> 2024-07 | AB26: =IF(X26="","",X26/2) -> 993.5
A27: 27 | B27: SOLD | C27: Own purchase | D27: Škoda | E27: Superb Combi | F27: Style | G27: 43374 | H27: 2.0 TDI 110 kW | I27: MT6 | K27: 186000 | M27: BE | N27: D | O27: 45457 | P27: 9880.5 | Q27: =IF(A27="","",SUMIF(Expenses!$B$2:$B$3000,A27,Expenses!$E$2:$E$3000)) -> 0 | R27: =IF(A27="","",N(P27)+N(Q27)) -> 9880.5 | T27: 45527 | U27: 16200 | V27: 2249.5 | X27: =IF(B27<>"SOLD","",IF(C27="Consignment",N(W27)-R27,N(U27)-R27-N(V27))) -> 4070 | Y27: =IF(OR(X27="",N(R27)=0),"",X27/R27) -> 0.41192247 | Z27: =IF(O27="","",IF(T27="",TODAY(),T27)-O27) -> 70 | AA27: =IF(T27="","",TEXT(T27,"YYYY-MM")) -> 2024-08 | AB27: =IF(X27="","",X27/2) -> 2035
A28: 28 | B28: SOLD | C28: Own purchase | D28: Seat | E28: Arona | F28: Style | G28: 43282 | H28: 1.6 TDI 70 kW | I28: MT5 | K28: 155000 | M28: FR | N28: M | O28: 45462 | P28: 10145 | Q28: =IF(A28="","",SUMIF(Expenses!$B$2:$B$3000,A28,Expenses!$E$2:$E$3000)) -> 0 | R28: =IF(A28="","",N(P28)+N(Q28)) -> 10145 | T28: 45514 | U28: 12700 | V28: 0 | X28: =IF(B28<>"SOLD","",IF(C28="Consignment",N(W28)-R28,N(U28)-R28-N(V28))) -> 2555 | Y28: =IF(OR(X28="",N(R28)=0),"",X28/R28) -> 0.2518482 | Z28: =IF(O28="","",IF(T28="",TODAY(),T28)-O28) -> 52 | AA28: =IF(T28="","",TEXT(T28,"YYYY-MM")) -> 2024-08 | AB28: =IF(X28="","",X28/2) -> 1277.5
A29: 29 | B29: SOLD | C29: Own purchase | D29: Audi | E29: A4 Avant | F29: Basis | G29: 42401 | H29: 2.0 TDI 110 kW | I29: DSG7 | K29: 163000 | M29: IT | N29: M | O29: 45467 | P29: 12482.5 | Q29: =IF(A29="","",SUMIF(Expenses!$B$2:$B$3000,A29,Expenses!$E$2:$E$3000)) -> 0 | R29: =IF(A29="","",N(P29)+N(Q29)) -> 12482.5 | T29: 45523 | U29: 16000 | V29: -0.5 | X29: =IF(B29<>"SOLD","",IF(C29="Consignment",N(W29)-R29,N(U29)-R29-N(V29))) -> 3518 | Y29: =IF(OR(X29="",N(R29)=0),"",X29/R29) -> 0.28183457 | Z29: =IF(O29="","",IF(T29="",TODAY(),T29)-O29) -> 56 | AA29: =IF(T29="","",TEXT(T29,"YYYY-MM")) -> 2024-08 | AB29: =IF(X29="","",X29/2) -> 1759
A30: 30 | B30: SOLD | C30: Own purchase | D30: Škoda | E30: Octavia Combi | F30: Ambition | G30: 43132 | H30: 1.0 TSI 85 kW | I30: MT6 | K30: 166700 | M30: BE | N30: D | O30: 45476 | P30: 8750.67 | Q30: =IF(A30="","",SUMIF(Expenses!$B$2:$B$3000,A30,Expenses!$E$2:$E$3000)) -> 0 | R30: =IF(A30="","",N(P30)+N(Q30)) -> 8750.67 | T30: 45605 | U30: 9700 | V30: 199.33 | X30: =IF(B30<>"SOLD","",IF(C30="Consignment",N(W30)-R30,N(U30)-R30-N(V30))) -> 750 | Y30: =IF(OR(X30="",N(R30)=0),"",X30/R30) -> 0.085707723 | Z30: =IF(O30="","",IF(T30="",TODAY(),T30)-O30) -> 129 | AA30: =IF(T30="","",TEXT(T30,"YYYY-MM")) -> 2024-11 | AB30: =IF(X30="","",X30/2) -> 375
A31: 31 | B31: SOLD | C31: Own purchase | D31: Alfa Romeo | E31: Stelvio | F31: Executive | G31: 43040 | H31: 2.2d 154 kW | I31: AT8 | J31: 4x4 | K31: 157200 | M31: IT | N31: D | O31: 45484 | P31: 14740 | Q31: =IF(A31="","",SUMIF(Expenses!$B$2:$B$3000,A31,Expenses!$E$2:$E$3000)) -> 0 | R31: =IF(A31="","",N(P31)+N(Q31)) -> 14740 | T31: 45706 | U31: 20750 | V31: 3880 | X31: =IF(B31<>"SOLD","",IF(C31="Consignment",N(W31)-R31,N(U31)-R31-N(V31))) -> 2130 | Y31: =IF(OR(X31="",N(R31)=0),"",X31/R31) -> 0.14450475 | Z31: =IF(O31="","",IF(T31="",TODAY(),T31)-O31) -> 222 | AA31: =IF(T31="","",TEXT(T31,"YYYY-MM")) -> 2025-02 | AB31: =IF(X31="","",X31/2) -> 1065
A32: 32 | B32: SOLD | C32: Own purchase | D32: Audi | E32: A4 Avant | F32: Basis | G32: 42522 | H32: 2.0 TDI 110 kW | I32: DSG7 | K32: 174500 | M32: DE | N32: M | O32: 45483 | P32: 13121.67 | Q32: =IF(A32="","",SUMIF(Expenses!$B$2:$B$3000,A32,Expenses!$E$2:$E$3000)) -> 0 | R32: =IF(A32="","",N(P32)+N(Q32)) -> 13121.67 | T32: 45527 | U32: 15700 | V32: 0.33 | X32: =IF(B32<>"SOLD","",IF(C32="Consignment",N(W32)-R32,N(U32)-R32-N(V32))) -> 2578 | Y32: =IF(OR(X32="",N(R32)=0),"",X32/R32) -> 0.19646889 | Z32: =IF(O32="","",IF(T32="",TODAY(),T32)-O32) -> 44 | AA32: =IF(T32="","",TEXT(T32,"YYYY-MM")) -> 2024-08 | AB32: =IF(X32="","",X32/2) -> 1289
A33: 33 | B33: SOLD | C33: Own purchase | D33: VW | E33: Touareg | F33: Exclusive | G33: 39630 | H33: 3.0 TDI 176 kW | I33: AT6 | J33: 4x4 | K33: 208900 | M33: IT | N33: M | O33: 45514 | P33: 7780.83 | Q33: =IF(A33="","",SUMIF(Expenses!$B$2:$B$3000,A33,Expenses!$E$2:$E$3000)) -> 0 | R33: =IF(A33="","",N(P33)+N(Q33)) -> 7780.83 | T33: 45580 | U33: 9300 | V33: 0.17 | X33: =IF(B33<>"SOLD","",IF(C33="Consignment",N(W33)-R33,N(U33)-R33-N(V33))) -> 1519 | Y33: =IF(OR(X33="",N(R33)=0),"",X33/R33) -> 0.19522339 | Z33: =IF(O33="","",IF(T33="",TODAY(),T33)-O33) -> 66 | AA33: =IF(T33="","",TEXT(T33,"YYYY-MM")) -> 2024-10 | AB33: =IF(X33="","",X33/2) -> 759.5
A34: 34 | B34: SOLD | C34: Own purchase | D34: VW | E34: Golf Variant | F34: Comfortline | G34: 42948 | H34: 2.0 TDI 110 kW | I34: MT6 | K34: 139300 | M34: BE | N34: D | O34: 45517 | P34: 9470 | Q34: =IF(A34="","",SUMIF(Expenses!$B$2:$B$3000,A34,Expenses!$E$2:$E$3000)) -> 0 | R34: =IF(A34="","",N(P34)+N(Q34)) -> 9470 | T34: 45596 | U34: 14100 | V34: 2350 | X34: =IF(B34<>"SOLD","",IF(C34="Consignment",N(W34)-R34,N(U34)-R34-N(V34))) -> 2280 | Y34: =IF(OR(X34="",N(R34)=0),"",X34/R34) -> 0.2407603 | Z34: =IF(O34="","",IF(T34="",TODAY(),T34)-O34) -> 79 | AA34: =IF(T34="","",TEXT(T34,"YYYY-MM")) -> 2024-10 | AB34: =IF(X34="","",X34/2) -> 1140
A35: 35 | B35: SOLD | C35: Own purchase | D35: Škoda | E35: Superb Combi | F35: Style | G35: 42736 | H35: 1.4 TSI 110 kW | I35: MT6 | K35: 148700 | M35: AT | N35: M | O35: 45518 | P35: 13751 | Q35: =IF(A35="","",SUMIF(Expenses!$B$2:$B$3000,A35,Expenses!$E$2:$E$3000)) -> 0 | R35: =IF(A35="","",N(P35)+N(Q35)) -> 13751 | T35: 45532 | U35: 15300 | V35: 0 | X35: =IF(B35<>"SOLD","",IF(C35="Consignment",N(W35)-R35,N(U35)-R35-N(V35))) -> 1549 | Y35: =IF(OR(X35="",N(R35)=0),"",X35/R35) -> 0.11264635 | Z35: =IF(O35="","",IF(T35="",TODAY(),T35)-O35) -> 14 | AA35: =IF(T35="","",TEXT(T35,"YYYY-MM")) -> 2024-08 | AB35: =IF(X35="","",X35/2) -> 774.5
A36: 36 | B36: SOLD | C36: Own purchase | D36: VW | E36: Passat Variant | F36: Comfortline | G36: 42248 | H36: 2.0 TDI 110 kW | I36: DSG7 | K36: 195700 | M36: DE | N36: M | O36: 45530 | P36: 11606.67 | Q36: =IF(A36="","",SUMIF(Expenses!$B$2:$B$3000,A36,Expenses!$E$2:$E$3000)) -> 0 | R36: =IF(A36="","",N(P36)+N(Q36)) -> 11606.67 | T36: 45593 | U36: 13850 | V36: 0.33 | X36: =IF(B36<>"SOLD","",IF(C36="Consignment",N(W36)-R36,N(U36)-R36-N(V36))) -> 2243 | Y36: =IF(OR(X36="",N(R36)=0),"",X36/R36) -> 0.19325095 | Z36: =IF(O36="","",IF(T36="",TODAY(),T36)-O36) -> 63 | AA36: =IF(T36="","",TEXT(T36,"YYYY-MM")) -> 2024-10 | AB36: =IF(X36="","",X36/2) -> 1121.5
A37: 37 | B37: SOLD | C37: Own purchase | D37: Škoda | E37: Octavia Combi | F37: Ambition | G37: 43221 | H37: 1.6 TDI 85 kW | I37: MT5 | K37: 176100 | M37: DE | N37: D | O37: 45532 | P37: 7566 | Q37: =IF(A37="","",SUMIF(Expenses!$B$2:$B$3000,A37,Expenses!$E$2:$E$3000)) -> 0 | R37: =IF(A37="","",N(P37)+N(Q37)) -> 7566 | T37: 45639 | U37: 9980 | V37: 1450 | X37: =IF(B37<>"SOLD","",IF(C37="Consignment",N(W37)-R37,N(U37)-R37-N(V37))) -> 964 | Y37: =IF(OR(X37="",N(R37)=0),"",X37/R37) -> 0.12741211 | Z37: =IF(O37="","",IF(T37="",TODAY(),T37)-O37) -> 107 | AA37: =IF(T37="","",TEXT(T37,"YYYY-MM")) -> 2024-12 | AB37: =IF(X37="","",X37/2) -> 482
A38: 38 | B38: SOLD | C38: Own purchase | D38: Škoda | E38: Octavia Combi | F38: Ambition | G38: 43040 | H38: 1.6 TDI 85 kW | I38: MT6 | K38: 113100 | M38: IT | N38: M | O38: 45534 | P38: 9985 | Q38: =IF(A38="","",SUMIF(Expenses!$B$2:$B$3000,A38,Expenses!$E$2:$E$3000)) -> 0 | R38: =IF(A38="","",N(P38)+N(Q38)) -> 9985 | T38: 45615 | U38: 12000 | V38: 0 | X38: =IF(B38<>"SOLD","",IF(C38="Consignment",N(W38)-R38,N(U38)-R38-N(V38))) -> 2015 | Y38: =IF(OR(X38="",N(R38)=0),"",X38/R38) -> 0.2018027 | Z38: =IF(O38="","",IF(T38="",TODAY(),T38)-O38) -> 81 | AA38: =IF(T38="","",TEXT(T38,"YYYY-MM")) -> 2024-11 | AB38: =IF(X38="","",X38/2) -> 1007.5
A39: 39 | B39: SOLD | C39: Own purchase | D39: Seat | E39: Leon ST | F39: Stylance | G39: 43709 | H39: 2.0 TDI 110 kW | I39: MT6 | K39: 197800 | M39: LU | N39: D | O39: 45537 | P39: 7180 | Q39: =IF(A39="","",SUMIF(Expenses!$B$2:$B$3000,A39,Expenses!$E$2:$E$3000)) -> 0 | R39: =IF(A39="","",N(P39)+N(Q39)) -> 7180 | T39: 45640 | U39: 10500 | V39: 1750 | X39: =IF(B39<>"SOLD","",IF(C39="Consignment",N(W39)-R39,N(U39)-R39-N(V39))) -> 1570 | Y39: =IF(OR(X39="",N(R39)=0),"",X39/R39) -> 0.21866295 | Z39: =IF(O39="","",IF(T39="",TODAY(),T39)-O39) -> 103 | AA39: =IF(T39="","",TEXT(T39,"YYYY-MM")) -> 2024-12 | AB39: =IF(X39="","",X39/2) -> 785
A40: 40 | B40: SOLD | C40: Own purchase | D40: Audi | E40: A4 Avant | F40: Basis | G40: 42401 | H40: 2.0 TDI 110 kW | I40: DSG7 | K40: 175900 | M40: IT | N40: M | O40: 45537 | P40: 12454.17 | Q40: =IF(A40="","",SUMIF(Expenses!$B$2:$B$3000,A40,Expenses!$E$2:$E$3000)) -> 0 | R40: =IF(A40="","",N(P40)+N(Q40)) -> 12454.17 | T40: 45640 | U40: 14000 | V40: -0.17 | X40: =IF(B40<>"SOLD","",IF(C40="Consignment",N(W40)-R40,N(U40)-R40-N(V40))) -> 1546 | Y40: =IF(OR(X40="",N(R40)=0),"",X40/R40) -> 0.12413513 | Z40: =IF(O40="","",IF(T40="",TODAY(),T40)-O40) -> 103 | AA40: =IF(T40="","",TEXT(T40,"YYYY-MM")) -> 2024-12 | AB40: =IF(X40="","",X40/2) -> 773
A41: 41 | B41: SOLD | C41: Own purchase | D41: VW | E41: Passat Variant | F41: Comfortline | G41: 42644 | H41: 2.0 TDI 110 kW | I41: DSG6 | K41: 178900 | M41: DK | N41: D | O41: 45541 | P41: 9275 | Q41: =IF(A41="","",SUMIF(Expenses!$B$2:$B$3000,A41,Expenses!$E$2:$E$3000)) -> 0 | R41: =IF(A41="","",N(P41)+N(Q41)) -> 9275 | T41: 45668 | U41: 12999 | V41: 2431 | X41: =IF(B41<>"SOLD","",IF(C41="Consignment",N(W41)-R41,N(U41)-R41-N(V41))) -> 1293 | Y41: =IF(OR(X41="",N(R41)=0),"",X41/R41) -> 0.13940701 | Z41: =IF(O41="","",IF(T41="",TODAY(),T41)-O41) -> 127 | AA41: =IF(T41="","",TEXT(T41,"YYYY-MM")) -> 2025-01 | AB41: =IF(X41="","",X41/2) -> 646.5
A42: 42 | B42: SOLD | C42: Own purchase | D42: Škoda | E42: Superb Combi | F42: Style | G42: 42309 | H42: 2.0 TDI 110 kW | I42: DSG6 | K42: 185200 | M42: IT | N42: M | O42: 45539 | P42: 12314.67 | Q42: =IF(A42="","",SUMIF(Expenses!$B$2:$B$3000,A42,Expenses!$E$2:$E$3000)) -> 0 | R42: =IF(A42="","",N(P42)+N(Q42)) -> 12314.67 | T42: 45657 | U42: 14300 | V42: 0.33 | X42: =IF(B42<>"SOLD","",IF(C42="Consignment",N(W42)-R42,N(U42)-R42-N(V42))) -> 1985 | Y42: =IF(OR(X42="",N(R42)=0),"",X42/R42) -> 0.16118987 | Z42: =IF(O42="","",IF(T42="",TODAY(),T42)-O42) -> 118 | AA42: =IF(T42="","",TEXT(T42,"YYYY-MM")) -> 2024-12 | AB42: =IF(X42="","",X42/2) -> 992.5
A43: 43 | B43: SOLD | C43: Own purchase | D43: Mercedes-Benz | E43: CLA 220 d Shooting Brake | F43: AMG line | G43: 43160 | H43: 2.2d 130 kW | I43: DCT7 | K43: 169600 | M43: DK | N43: D | O43: 45548 | P43: 12980 | Q43: =IF(A43="","",SUMIF(Expenses!$B$2:$B$3000,A43,Expenses!$E$2:$E$3000)) -> 0 | R43: =IF(A43="","",N(P43)+N(Q43)) -> 12980 | T43: 45639 | U43: 18800 | V43: 2833 | X43: =IF(B43<>"SOLD","",IF(C43="Consignment",N(W43)-R43,N(U43)-R43-N(V43))) -> 2987 | Y43: =IF(OR(X43="",N(R43)=0),"",X43/R43) -> 0.23012327 | Z43: =IF(O43="","",IF(T43="",TODAY(),T43)-O43) -> 91 | AA43: =IF(T43="","",TEXT(T43,"YYYY-MM")) -> 2024-12 | AB43: =IF(X43="","",X43/2) -> 1493.5
A44: 44 | B44: SOLD | C44: Own purchase | D44: Audi | E44: Q5 quattro | F44: Basis | G44: 40969 | H44: 3.0 TDI 176 kW | I44: DSG7 | J44: 4x4 | K44: 197800 | M44: DE | N44: M | O44: 45554 | P44: 10681.67 | Q44: =IF(A44="","",SUMIF(Expenses!$B$2:$B$3000,A44,Expenses!$E$2:$E$3000)) -> 0 | R44: =IF(A44="","",N(P44)+N(Q44)) -> 10681.67 | T44: 45607 | U44: 13190 | V44: 0.33 | X44: =IF(B44<>"SOLD","",IF(C44="Consignment",N(W44)-R44,N(U44)-R44-N(V44))) -> 2508 | Y44: =IF(OR(X44="",N(R44)=0),"",X44/R44) -> 0.23479475 | Z44: =IF(O44="","",IF(T44="",TODAY(),T44)-O44) -> 53 | AA44: =IF(T44="","",TEXT(T44,"YYYY-MM")) -> 2024-11 | AB44: =IF(X44="","",X44/2) -> 1254
A45: 45 | B45: SOLD | C45: Own purchase | D45: Seat | E45: Ateca | F45: Style | G45: 42979 | H45: 2.0 TDI 110 kW | I45: MT6 | J45: 4x4 | K45: 163600 | M45: DE | N45: M | O45: 45566 | P45: 14120.83 | Q45: =IF(A45="","",SUMIF(Expenses!$B$2:$B$3000,A45,Expenses!$E$2:$E$3000)) -> 0 | R45: =IF(A45="","",N(P45)+N(Q45)) -> 14120.83 | T45: 45619 | U45: 17000 | V45: 0.17 | X45: =IF(B45<>"SOLD","",IF(C45="Consignment",N(W45)-R45,N(U45)-R45-N(V45))) -> 2879 | Y45: =IF(OR(X45="",N(R45)=0),"",X45/R45) -> 0.2038832 | Z45: =IF(O45="","",IF(T45="",TODAY(),T45)-O45) -> 53 | AA45: =IF(T45="","",TEXT(T45,"YYYY-MM")) -> 2024-11 | AB45: =IF(X45="","",X45/2) -> 1439.5
A46: 46 | B46: SOLD | C46: Own purchase | D46: Alfa Romeo | E46: Giulietta | F46: Distinctive | G46: 40391 | H46: 1.4 TB 125 kW | I46: MT6 | K46: 169700 | M46: AT | N46: M | O46: 45572 | P46: 4975 | Q46: =IF(A46="","",SUMIF(Expenses!$B$2:$B$3000,A46,Expenses!$E$2:$E$3000)) -> 0 | R46: =IF(A46="","",N(P46)+N(Q46)) -> 4975 | T46: 45610 | U46: 6650 | V46: 0 | X46: =IF(B46<>"SOLD","",IF(C46="Consignment",N(W46)-R46,N(U46)-R46-N(V46))) -> 1675 | Y46: =IF(OR(X46="",N(R46)=0),"",X46/R46) -> 0.33668342 | Z46: =IF(O46="","",IF(T46="",TODAY(),T46)-O46) -> 38 | AA46: =IF(T46="","",TEXT(T46,"YYYY-MM")) -> 2024-11 | AB46: =IF(X46="","",X46/2) -> 837.5
A47: 47 | B47: SOLD | C47: Own purchase | D47: Škoda | E47: Octavia Combi | F47: Style | G47: 43070 | H47: 2.0 TDI 110 kW | I47: MT6 | K47: 188600 | M47: AT | N47: M | O47: 45582 | P47: 11332.67 | Q47: =IF(A47="","",SUMIF(Expenses!$B$2:$B$3000,A47,Expenses!$E$2:$E$3000)) -> 0 | R47: =IF(A47="","",N(P47)+N(Q47)) -> 11332.67 | T47: 45620 | U47: 13100 | V47: 0.33 | X47: =IF(B47<>"SOLD","",IF(C47="Consignment",N(W47)-R47,N(U47)-R47-N(V47))) -> 1767 | Y47: =IF(OR(X47="",N(R47)=0),"",X47/R47) -> 0.15592089 | Z47: =IF(O47="","",IF(T47="",TODAY(),T47)-O47) -> 38 | AA47: =IF(T47="","",TEXT(T47,"YYYY-MM")) -> 2024-11 | AB47: =IF(X47="","",X47/2) -> 883.5
A48: 48 | B48: SOLD | C48: Own purchase | D48: Audi | E48: A4 Avant | F48: Design | G48: 42705 | H48: 2.0 TDI | I48: DSG7 | K48: 185800 | M48: BE | N48: M | O48: 45597 | P48: 12498.33 | Q48: =IF(A48="","",SUMIF(Expenses!$B$2:$B$3000,A48,Expenses!$E$2:$E$3000)) -> 0 | R48: =IF(A48="","",N(P48)+N(Q48)) -> 12498.33 | T48: 45634 | U48: 14750 | V48: -0.33 | X48: =IF(B48<>"SOLD","",IF(C48="Consignment",N(W48)-R48,N(U48)-R48-N(V48))) -> 2252 | Y48: =IF(OR(X48="",N(R48)=0),"",X48/R48) -> 0.18018407 | Z48: =IF(O48="","",IF(T48="",TODAY(),T48)-O48) -> 37 | AA48: =IF(T48="","",TEXT(T48,"YYYY-MM")) -> 2024-12 | AB48: =IF(X48="","",X48/2) -> 1126
A49: 49 | B49: SOLD | C49: Own purchase | D49: Škoda | E49: Octavia Combi | F49: Ambition | G49: 43101 | H49: 1.4 TSI 110 kW | I49: MT6 | K49: 185200 | M49: BE | N49: M | O49: 45600 | P49: 9410 | Q49: =IF(A49="","",SUMIF(Expenses!$B$2:$B$3000,A49,Expenses!$E$2:$E$3000)) -> 0 | R49: =IF(A49="","",N(P49)+N(Q49)) -> 9410 | T49: 45649 | U49: 12000 | V49: 0 | X49: =IF(B49<>"SOLD","",IF(C49="Consignment",N(W49)-R49,N(U49)-R49-N(V49))) -> 2590 | Y49: =IF(OR(X49="",N(R49)=0),"",X49/R49) -> 0.27523911 | Z49: =IF(O49="","",IF(T49="",TODAY(),T49)-O49) -> 49 | AA49: =IF(T49="","",TEXT(T49,"YYYY-MM")) -> 2024-12 | AB49: =IF(X49="","",X49/2) -> 1295
A50: 50 | B50: SOLD | C50: Own purchase | D50: Citroën | E50: Jumpy | F50: L2H1 | G50: 43040 | H50: 2.0 HDI 130 kW | I50: AT6 | K50: 166200 | M50: DK | N50: D | O50: 45611 | P50: 9640 | Q50: =IF(A50="","",SUMIF(Expenses!$B$2:$B$3000,A50,Expenses!$E$2:$E$3000)) -> 0 | R50: =IF(A50="","",N(P50)+N(Q50)) -> 9640 | T50: 45701 | U50: 13990 | V50: 2498 | X50: =IF(B50<>"SOLD","",IF(C50="Consignment",N(W50)-R50,N(U50)-R50-N(V50))) -> 1852 | Y50: =IF(OR(X50="",N(R50)=0),"",X50/R50) -> 0.19211618 | Z50: =IF(O50="","",IF(T50="",TODAY(),T50)-O50) -> 90 | AA50: =IF(T50="","",TEXT(T50,"YYYY-MM")) -> 2025-02 | AB50: =IF(X50="","",X50/2) -> 926
A51: 51 | B51: SOLD | C51: Own purchase | D51: VW | E51: Tiguan 4Motion | F51: Sport & Style | G51: 40848 | H51: 1.4 TSI 118 kW | I51: MT6 | J51: 4x4 | K51: 186200 | M51: SE | N51: M | O51: 45616 | P51: 6907.5 | Q51: =IF(A51="","",SUMIF(Expenses!$B$2:$B$3000,A51,Expenses!$E$2:$E$3000)) -> 0 | R51: =IF(A51="","",N(P51)+N(Q51)) -> 6907.5 | T51: 45756 | U51: 8850 | V51: -0.5 | X51: =IF(B51<>"SOLD","",IF(C51="Consignment",N(W51)-R51,N(U51)-R51-N(V51))) -> 1943 | Y51: =IF(OR(X51="",N(R51)=0),"",X51/R51) -> 0.28128845 | Z51: =IF(O51="","",IF(T51="",TODAY(),T51)-O51) -> 140 | AA51: =IF(T51="","",TEXT(T51,"YYYY-MM")) -> 2025-04 | AB51: =IF(X51="","",X51/2) -> 971.5
A52: 52 | B52: SOLD | C52: Own purchase | D52: VW | E52: Touran | F52: Comfortline | G52: 40483 | H52: 1.6 TDI | I52: MT6 | K52: 139800 | M52: DE | N52: M | O52: 45616 | P52: 9084.59 | Q52: =IF(A52="","",SUMIF(Expenses!$B$2:$B$3000,A52,Expenses!$E$2:$E$3000)) -> 0 | R52: =IF(A52="","",N(P52)+N(Q52)) -> 9084.59 | T52: 45638 | U52: 9800 | V52: 0.41 | X52: =IF(B52<>"SOLD","",IF(C52="Consignment",N(W52)-R52,N(U52)-R52-N(V52))) -> 715 | Y52: =IF(OR(X52="",N(R52)=0),"",X52/R52) -> 0.078704708 | Z52: =IF(O52="","",IF(T52="",TODAY(),T52)-O52) -> 22 | AA52: =IF(T52="","",TEXT(T52,"YYYY-MM")) -> 2024-12 | AB52: =IF(X52="","",X52/2) -> 357.5
A53: 53 | B53: SOLD | C53: Own purchase | D53: VW | E53: Golf Variant | F53: Comfortline | G53: 43405 | H53: 1.0 TSI | I53: MT6 | K53: 181500 | M53: NL | N53: D | O53: 45624 | P53: 7515.33 | Q53: =IF(A53="","",SUMIF(Expenses!$B$2:$B$3000,A53,Expenses!$E$2:$E$3000)) -> 0 | R53: =IF(A53="","",N(P53)+N(Q53)) -> 7515.33 | T53: 45674 | U53: 9500 | V53: -0.33 | X53: =IF(B53<>"SOLD","",IF(C53="Consignment",N(W53)-R53,N(U53)-R53-N(V53))) -> 1985 | Y53: =IF(OR(X53="",N(R53)=0),"",X53/R53) -> 0.26412679 | Z53: =IF(O53="","",IF(T53="",TODAY(),T53)-O53) -> 50 | AA53: =IF(T53="","",TEXT(T53,"YYYY-MM")) -> 2025-01 | AB53: =IF(X53="","",X53/2) -> 992.5
A54: 54 | B54: SOLD | C54: Own purchase | D54: Renault | E54: Espace | F54: Zen | G54: 44197 | H54: 2.0 dCi 118 kW | I54: EDC6 | K54: 191300 | M54: FR | N54: D | O54: 45628 | P54: 11099 | Q54: =IF(A54="","",SUMIF(Expenses!$B$2:$B$3000,A54,Expenses!$E$2:$E$3000)) -> 0 | R54: =IF(A54="","",N(P54)+N(Q54)) -> 11099 | T54: 45657 | U54: 17300 | V54: 2883 | X54: =IF(B54<>"SOLD","",IF(C54="Consignment",N(W54)-R54,N(U54)-R54-N(V54))) -> 3318 | Y54: =IF(OR(X54="",N(R54)=0),"",X54/R54) -> 0.29894585 | Z54: =IF(O54="","",IF(T54="",TODAY(),T54)-O54) -> 29 | AA54: =IF(T54="","",TEXT(T54,"YYYY-MM")) -> 2024-12 | AB54: =IF(X54="","",X54/2) -> 1659
A55: 55 | B55: SOLD | C55: Own purchase | D55: Škoda | E55: Superb Combi | F55: Style | G55: 42614 | H55: 1.6 TDI 88 kW | I55: MT6 | K55: 157400 | M55: BE | N55: M | O55: 45629 | P55: 11585.54 | Q55: =IF(A55="","",SUMIF(Expenses!$B$2:$B$3000,A55,Expenses!$E$2:$E$3000)) -> 0 | R55: =IF(A55="","",N(P55)+N(Q55)) -> 11585.54 | T55: 45849 | U55: 12690 | V55: 0.46 | X55: =IF(B55<>"SOLD","",IF(C55="Consignment",N(W55)-R55,N(U55)-R55-N(V55))) -> 1104 | Y55: =IF(OR(X55="",N(R55)=0),"",X55/R55) -> 0.095291199 | Z55: =IF(O55="","",IF(T55="",TODAY(),T55)-O55) -> 220 | AA55: =IF(T55="","",TEXT(T55,"YYYY-MM")) -> 2025-07 | AB55: =IF(X55="","",X55/2) -> 552
A56: 56 | B56: SOLD | C56: Own purchase | D56: VW | E56: Golf Variant | F56: Comfortline | G56: 43221 | H56: 2.0 TDI | I56: MT6 | K56: 168000 | M56: DE | N56: M | O56: 45636 | P56: 9849.59 | Q56: =IF(A56="","",SUMIF(Expenses!$B$2:$B$3000,A56,Expenses!$E$2:$E$3000)) -> 0 | R56: =IF(A56="","",N(P56)+N(Q56)) -> 9849.59 | T56: 45716 | U56: 12800 | V56: 0.41 | X56: =IF(B56<>"SOLD","",IF(C56="Consignment",N(W56)-R56,N(U56)-R56-N(V56))) -> 2950 | Y56: =IF(OR(X56="",N(R56)=0),"",X56/R56) -> 0.29950485 | Z56: =IF(O56="","",IF(T56="",TODAY(),T56)-O56) -> 80 | AA56: =IF(T56="","",TEXT(T56,"YYYY-MM")) -> 2025-02 | AB56: =IF(X56="","",X56/2) -> 1475
A57: 57 | B57: SOLD | C57: Own purchase | D57: Seat | E57: Ateca | F57: Style | G57: 42644 | H57: 1.6 TDI 85 kW | I57: MT6 | K57: 182200 | M57: FR | N57: M | O57: 45638 | P57: 11360.24 | Q57: =IF(A57="","",SUMIF(Expenses!$B$2:$B$3000,A57,Expenses!$E$2:$E$3000)) -> 0 | R57: =IF(A57="","",N(P57)+N(Q57)) -> 11360.24 | T57: 45806 | U57: 12150 | V57: -0.24 | X57: =IF(B57<>"SOLD","",IF(C57="Consignment",N(W57)-R57,N(U57)-R57-N(V57))) -> 790 | Y57: =IF(OR(X57="",N(R57)=0),"",X57/R57) -> 0.069540784 | Z57: =IF(O57="","",IF(T57="",TODAY(),T57)-O57) -> 168 | AA57: =IF(T57="","",TEXT(T57,"YYYY-MM")) -> 2025-05 | AB57: =IF(X57="","",X57/2) -> 395
A58: 58 | B58: SOLD | C58: Own purchase | D58: Audi | E58: A4 Avant | F58: Sport | G58: 42917 | H58: 2.0 TDI 140 kW | I58: DSG7 | K58: 196170 | M58: DE | N58: M | O58: 45641 | P58: 12846.5 | Q58: =IF(A58="","",SUMIF(Expenses!$B$2:$B$3000,A58,Expenses!$E$2:$E$3000)) -> 0 | R58: =IF(A58="","",N(P58)+N(Q58)) -> 12846.5 | T58: 45690 | U58: 15990 | V58: 0.5 | X58: =IF(B58<>"SOLD","",IF(C58="Consignment",N(W58)-R58,N(U58)-R58-N(V58))) -> 3143 | Y58: =IF(OR(X58="",N(R58)=0),"",X58/R58) -> 0.24465808 | Z58: =IF(O58="","",IF(T58="",TODAY(),T58)-O58) -> 49 | AA58: =IF(T58="","",TEXT(T58,"YYYY-MM")) -> 2025-02 | AB58: =IF(X58="","",X58/2) -> 1571.5
A59: 59 | B59: SOLD | C59: Consignment | D59: Škoda | E59: Kodiaq | F59: Style | G59: 42705 | H59: 2.0 TDI 140 kW | I59: DSG7 | J59: 4x4 | K59: 221950 | M59: CZ | N59: M | O59: 45643 | P59: 90 | Q59: =IF(A59="","",SUMIF(Expenses!$B$2:$B$3000,A59,Expenses!$E$2:$E$3000)) -> 0 | R59: =IF(A59="","",N(P59)+N(Q59)) -> 90 | T59: 45688 | U59: 18800 | W59: 790 | X59: =IF(B59<>"SOLD","",IF(C59="Consignment",N(W59)-R59,N(U59)-R59-N(V59))) -> 700 | Y59: =IF(OR(X59="",N(R59)=0),"",X59/R59) -> 7.7777778 | Z59: =IF(O59="","",IF(T59="",TODAY(),T59)-O59) -> 45 | AA59: =IF(T59="","",TEXT(T59,"YYYY-MM")) -> 2025-01 | AB59: =IF(X59="","",X59/2) -> 350
A60: 60 | B60: SOLD | C60: Own purchase | D60: Audi | E60: A4 Avant | F60: Basis | G60: 42491 | H60: 2.0 TDI 140 kW | I60: DSG7 | K60: 196700 | M60: BE | N60: M | O60: 45653 | P60: 12236.75 | Q60: =IF(A60="","",SUMIF(Expenses!$B$2:$B$3000,A60,Expenses!$E$2:$E$3000)) -> 0 | R60: =IF(A60="","",N(P60)+N(Q60)) -> 12236.75 | T60: 45773 | U60: 14000 | V60: 0.25 | X60: =IF(B60<>"SOLD","",IF(C60="Consignment",N(W60)-R60,N(U60)-R60-N(V60))) -> 1763 | Y60: =IF(OR(X60="",N(R60)=0),"",X60/R60) -> 0.1440742 | Z60: =IF(O60="","",IF(T60="",TODAY(),T60)-O60) -> 120 | AA60: =IF(T60="","",TEXT(T60,"YYYY-MM")) -> 2025-04 | AB60: =IF(X60="","",X60/2) -> 881.5
A61: 61 | B61: SOLD | C61: Own purchase | D61: Seat | E61: Ateca | F61: Style | G61: 42795 | H61: 1.4 TSI 110 kW | I61: MT6 | K61: 191400 | M61: DE | N61: M | O61: 45653 | P61: 11746.65 | Q61: =IF(A61="","",SUMIF(Expenses!$B$2:$B$3000,A61,Expenses!$E$2:$E$3000)) -> 0 | R61: =IF(A61="","",N(P61)+N(Q61)) -> 11746.65 | T61: 45751 | U61: 14350 | V61: 0.35 | X61: =IF(B61<>"SOLD","",IF(C61="Consignment",N(W61)-R61,N(U61)-R61-N(V61))) -> 2603 | Y61: =IF(OR(X61="",N(R61)=0),"",X61/R61) -> 0.22159509 | Z61: =IF(O61="","",IF(T61="",TODAY(),T61)-O61) -> 98 | AA61: =IF(T61="","",TEXT(T61,"YYYY-MM")) -> 2025-04 | AB61: =IF(X61="","",X61/2) -> 1301.5
A62: 62 | B62: SOLD | C62: Own purchase | D62: Škoda | E62: Octavia Combi | F62: Ambition | G62: 43160 | H62: 1.0 TSI 85 kW | I62: MT6 | K62: 201400 | M62: DE | N62: M | O62: 45653 | P62: 7322.09 | Q62: =IF(A62="","",SUMIF(Expenses!$B$2:$B$3000,A62,Expenses!$E$2:$E$3000)) -> 0 | R62: =IF(A62="","",N(P62)+N(Q62)) -> 7322.09 | T62: 45777 | U62: 8500 | V62: -0.09 | X62: =IF(B62<>"SOLD","",IF(C62="Consignment",N(W62)-R62,N(U62)-R62-N(V62))) -> 1178 | Y62: =IF(OR(X62="",N(R62)=0),"",X62/R62) -> 0.16088303 | Z62: =IF(O62="","",IF(T62="",TODAY(),T62)-O62) -> 124 | AA62: =IF(T62="","",TEXT(T62,"YYYY-MM")) -> 2025-04 | AB62: =IF(X62="","",X62/2) -> 589
A63: 63 | B63: SOLD | C63: Own purchase | D63: Seat | E63: Leon ST | F63: Style | G63: 42217 | H63: 2.0 TDI 110 kW | I63: MT6 | K63: 198300 | M63: DE | N63: M | O63: 45653 | P63: 8776.34 | Q63: =IF(A63="","",SUMIF(Expenses!$B$2:$B$3000,A63,Expenses!$E$2:$E$3000)) -> 0 | R63: =IF(A63="","",N(P63)+N(Q63)) -> 8776.34 | T63: 45746 | U63: 10350 | V63: -0.34 | X63: =IF(B63<>"SOLD","",IF(C63="Consignment",N(W63)-R63,N(U63)-R63-N(V63))) -> 1574 | Y63: =IF(OR(X63="",N(R63)=0),"",X63/R63) -> 0.17934583 | Z63: =IF(O63="","",IF(T63="",TODAY(),T63)-O63) -> 93 | AA63: =IF(T63="","",TEXT(T63,"YYYY-MM")) -> 2025-03 | AB63: =IF(X63="","",X63/2) -> 787
A64: 64 | B64: SOLD | C64: Own purchase | D64: Alfa Romeo | E64: Mito | F64: Distinctive | G64: 39965 | H64: 1.4 T-Jet 114 kW | I64: MT6 | K64: 213940 | M64: IT | N64: M | O64: 45655 | P64: 1798 | Q64: =IF(A64="","",SUMIF(Expenses!$B$2:$B$3000,A64,Expenses!$E$2:$E$3000)) -> 0 | R64: =IF(A64="","",N(P64)+N(Q64)) -> 1798 | T64: 45655 | U64: 1800 | V64: 0 | X64: =IF(B64<>"SOLD","",IF(C64="Consignment",N(W64)-R64,N(U64)-R64-N(V64))) -> 2 | Y64: =IF(OR(X64="",N(R64)=0),"",X64/R64) -> 0.0011123471 | Z64: =IF(O64="","",IF(T64="",TODAY(),T64)-O64) -> 0 | AA64: =IF(T64="","",TEXT(T64,"YYYY-MM")) -> 2024-12 | AB64: =IF(X64="","",X64/2) -> 1
A65: 65 | B65: SOLD | C65: Own purchase | D65: VW | E65: Tiguan | F65: Trend & Fun | G65: 41609 | H65: 2.0 TDI 103 kW | I65: MT6 | K65: 180200 | M65: DE | N65: M | O65: 45655 | P65: 7404.88 | Q65: =IF(A65="","",SUMIF(Expenses!$B$2:$B$3000,A65,Expenses!$E$2:$E$3000)) -> 0 | R65: =IF(A65="","",N(P65)+N(Q65)) -> 7404.88 | T65: 45675 | U65: 9700 | V65: 395.12 | X65: =IF(B65<>"SOLD","",IF(C65="Consignment",N(W65)-R65,N(U65)-R65-N(V65))) -> 1900 | Y65: =IF(OR(X65="",N(R65)=0),"",X65/R65) -> 0.25658755 | Z65: =IF(O65="","",IF(T65="",TODAY(),T65)-O65) -> 20 | AA65: =IF(T65="","",TEXT(T65,"YYYY-MM")) -> 2025-01 | AB65: =IF(X65="","",X65/2) -> 950
A66: 66 | B66: SOLD | C66: Own purchase | D66: Audi | E66: Q5 quattro | F66: Basis | G66: 39995 | H66: 3.0 TDI 176 kW | I66: DSG7 | J66: 4x4 | K66: 183500 | M66: DE | N66: M | O66: 45657 | P66: 9560 | Q66: =IF(A66="","",SUMIF(Expenses!$B$2:$B$3000,A66,Expenses!$E$2:$E$3000)) -> 0 | R66: =IF(A66="","",N(P66)+N(Q66)) -> 9560 | T66: 45793 | U66: 11000 | V66: 0 | X66: =IF(B66<>"SOLD","",IF(C66="Consignment",N(W66)-R66,N(U66)-R66-N(V66))) -> 1440 | Y66: =IF(OR(X66="",N(R66)=0),"",X66/R66) -> 0.15062762 | Z66: =IF(O66="","",IF(T66="",TODAY(),T66)-O66) -> 136 | AA66: =IF(T66="","",TEXT(T66,"YYYY-MM")) -> 2025-05 | AB66: =IF(X66="","",X66/2) -> 720
A67: 67 | B67: SOLD | C67: Own purchase | D67: Mazda | E67: MX-5 | F67: Revolution | G67: 42491 | H67: 2.0 Skyactiv-G 118 kW | I67: MT6 | K67: 185700 | M67: DE | N67: D | O67: 45664 | P67: 11145.56 | Q67: =IF(A67="","",SUMIF(Expenses!$B$2:$B$3000,A67,Expenses!$E$2:$E$3000)) -> 0 | R67: =IF(A67="","",N(P67)+N(Q67)) -> 11145.56 | T67: 46177 | U67: 13200 | V67: -831.56 | X67: =IF(B67<>"SOLD","",IF(C67="Consignment",N(W67)-R67,N(U67)-R67-N(V67))) -> 2886 | Y67: =IF(OR(X67="",N(R67)=0),"",X67/R67) -> 0.25893719 | Z67: =IF(O67="","",IF(T67="",TODAY(),T67)-O67) -> 513 | AA67: =IF(T67="","",TEXT(T67,"YYYY-MM")) -> 2026-06 | AB67: =IF(X67="","",X67/2) -> 1443
A68: 68 | B68: SOLD | C68: Consignment | D68: Mercedes-Benz | E68: E53 AMG | F68: AMG | G68: 44958 | H68: 3.0i 320 kW | I68: AT9 | J68: 4x4 | K68: 7860 | M68: DE | N68: D | O68: 45677 | P68: 1708.42 | Q68: =IF(A68="","",SUMIF(Expenses!$B$2:$B$3000,A68,Expenses!$E$2:$E$3000)) -> 0 | R68: =IF(A68="","",N(P68)+N(Q68)) -> 1708.42 | T68: 45693 | U68: 72390 | W68: 3764.42 | X68: =IF(B68<>"SOLD","",IF(C68="Consignment",N(W68)-R68,N(U68)-R68-N(V68))) -> 2056 | Y68: =IF(OR(X68="",N(R68)=0),"",X68/R68) -> 1.2034511 | Z68: =IF(O68="","",IF(T68="",TODAY(),T68)-O68) -> 16 | AA68: =IF(T68="","",TEXT(T68,"YYYY-MM")) -> 2025-02 | AB68: =IF(X68="","",X68/2) -> 1028
A69: 69 | B69: SOLD | C69: Own purchase | D69: VW | E69: Golf Variant | F69: Comfortline | G69: 42614 | H69: 2.0 TDI 110 kW | I69: MT6 | K69: 197900 | M69: DE | N69: M | O69: 45681 | P69: 9156.5 | Q69: =IF(A69="","",SUMIF(Expenses!$B$2:$B$3000,A69,Expenses!$E$2:$E$3000)) -> 0 | R69: =IF(A69="","",N(P69)+N(Q69)) -> 9156.5 | T69: 45748 | U69: 10850 | V69: 0.5 | X69: =IF(B69<>"SOLD","",IF(C69="Consignment",N(W69)-R69,N(U69)-R69-N(V69))) -> 1693 | Y69: =IF(OR(X69="",N(R69)=0),"",X69/R69) -> 0.18489598 | Z69: =IF(O69="","",IF(T69="",TODAY(),T69)-O69) -> 67 | AA69: =IF(T69="","",TEXT(T69,"YYYY-MM")) -> 2025-04 | AB69: =IF(X69="","",X69/2) -> 846.5
A70: 70 | B70: SOLD | C70: Own purchase | D70: Škoda | E70: Octavia Combi | F70: Ambition | G70: 43770 | H70: 1.5 TSI 110 kW | I70: MT6 | K70: 187900 | M70: NL | N70: D | O70: 45681 | P70: 7835 | Q70: =IF(A70="","",SUMIF(Expenses!$B$2:$B$3000,A70,Expenses!$E$2:$E$3000)) -> 0 | R70: =IF(A70="","",N(P70)+N(Q70)) -> 7835 | T70: 45746 | U70: 12250 | V70: 2291 | X70: =IF(B70<>"SOLD","",IF(C70="Consignment",N(W70)-R70,N(U70)-R70-N(V70))) -> 2124 | Y70: =IF(OR(X70="",N(R70)=0),"",X70/R70) -> 0.27109126 | Z70: =IF(O70="","",IF(T70="",TODAY(),T70)-O70) -> 65 | AA70: =IF(T70="","",TEXT(T70,"YYYY-MM")) -> 2025-03 | AB70: =IF(X70="","",X70/2) -> 1062
A71: 71 | B71: SOLD | C71: Own purchase | D71: Škoda | E71: Karoq | F71: Style | G71: 44075 | H71: 1.5 TSI 110 kW | I71: MT6 | K71: 171000 | M71: DK | N71: D | O71: 45684 | P71: 11747 | Q71: =IF(A71="","",SUMIF(Expenses!$B$2:$B$3000,A71,Expenses!$E$2:$E$3000)) -> 0 | R71: =IF(A71="","",N(P71)+N(Q71)) -> 11747 | T71: 45709 | U71: 17300 | V71: 2805 | X71: =IF(B71<>"SOLD","",IF(C71="Consignment",N(W71)-R71,N(U71)-R71-N(V71))) -> 2748 | Y71: =IF(OR(X71="",N(R71)=0),"",X71/R71) -> 0.23393207 | Z71: =IF(O71="","",IF(T71="",TODAY(),T71)-O71) -> 25 | AA71: =IF(T71="","",TEXT(T71,"YYYY-MM")) -> 2025-02 | AB71: =IF(X71="","",X71/2) -> 1374
A72: 72 | B72: STOCK | C72: Own purchase | D72: Opel | E72: Vivaro | F72: L2H1 | G72: 44044 | H72: 2.0 HDI 90 kW | I72: MT6 | K72: 136400 | M72: IT | N72: D | O72: 45698 | P72: 8739 | Q72: =IF(A72="","",SUMIF(Expenses!$B$2:$B$3000,A72,Expenses!$E$2:$E$3000)) -> 0 | R72: =IF(A72="","",N(P72)+N(Q72)) -> 8739 | X72: =IF(B72<>"SOLD","",IF(C72="Consignment",N(W72)-R72,N(U72)-R72-N(V72))) | Y72: =IF(OR(X72="",N(R72)=0),"",X72/R72) | Z72: =IF(O72="","",IF(T72="",TODAY(),T72)-O72) -> 604 | AA72: =IF(T72="","",TEXT(T72,"YYYY-MM")) | AB72: =IF(X72="","",X72/2)
A73: 73 | B73: SOLD | C73: Own purchase | D73: Volvo | E73: V90 | F73: Inscription | G73: 43070 | H73: 2.0 D5 173 kW AWD | I73: AT8 | K73: 166500 | M73: FR | N73: M | O73: 45705 | P73: 20190.81 | Q73: =IF(A73="","",SUMIF(Expenses!$B$2:$B$3000,A73,Expenses!$E$2:$E$3000)) -> 0 | R73: =IF(A73="","",N(P73)+N(Q73)) -> 20190.81 | T73: 45919 | U73: 21550 | V73: 0.19 | X73: =IF(B73<>"SOLD","",IF(C73="Consignment",N(W73)-R73,N(U73)-R73-N(V73))) -> 1359 | Y73: =IF(OR(X73="",N(R73)=0),"",X73/R73) -> 0.067307849 | Z73: =IF(O73="","",IF(T73="",TODAY(),T73)-O73) -> 214 | AA73: =IF(T73="","",TEXT(T73,"YYYY-MM")) -> 2025-09 | AB73: =IF(X73="","",X73/2) -> 679.5
A74: 74 | B74: SOLD | C74: Own purchase | D74: BMW | E74: 530i xDrive Touring | F74: M Sport | G74: 43709 | H74: 2.0i 185 kW xDrive | I74: AT8 | J74: 4x4 | K74: 182000 | M74: DE | N74: M | O74: 45706 | P74: 24341.45 | Q74: =IF(A74="","",SUMIF(Expenses!$B$2:$B$3000,A74,Expenses!$E$2:$E$3000)) -> 0 | R74: =IF(A74="","",N(P74)+N(Q74)) -> 24341.45 | T74: 45707 | U74: 25500 | V74: 158.55 | X74: =IF(B74<>"SOLD","",IF(C74="Consignment",N(W74)-R74,N(U74)-R74-N(V74))) -> 1000 | Y74: =IF(OR(X74="",N(R74)=0),"",X74/R74) -> 0.041082187 | Z74: =IF(O74="","",IF(T74="",TODAY(),T74)-O74) -> 1 | AA74: =IF(T74="","",TEXT(T74,"YYYY-MM")) -> 2025-02 | AB74: =IF(X74="","",X74/2) -> 500
A75: 75 | B75: SOLD | C75: Own purchase | D75: Citroën | E75: Jumpy | F75: L2H1 | G75: 44075 | H75: 2.0 HDI 90 kW | I75: MT6 | K75: 73300 | M75: DK | N75: D | O75: 45708 | P75: 16047.93 | Q75: =IF(A75="","",SUMIF(Expenses!$B$2:$B$3000,A75,Expenses!$E$2:$E$3000)) -> 0 | R75: =IF(A75="","",N(P75)+N(Q75)) -> 16047.93 | T75: 45851 | U75: 17850 | V75: 0.07 | X75: =IF(B75<>"SOLD","",IF(C75="Consignment",N(W75)-R75,N(U75)-R75-N(V75))) -> 1802 | Y75: =IF(OR(X75="",N(R75)=0),"",X75/R75) -> 0.11228863 | Z75: =IF(O75="","",IF(T75="",TODAY(),T75)-O75) -> 143 | AA75: =IF(T75="","",TEXT(T75,"YYYY-MM")) -> 2025-07 | AB75: =IF(X75="","",X75/2) -> 901
A76: 76 | B76: SOLD | C76: Own purchase | D76: Seat | E76: Leon ST | F76: Style | G76: 44682 | H76: 2.0 TDI 85 kW | I76: MT6 | K76: 68100 | M76: IT | N76: D | O76: 45715 | P76: 16011 | Q76: =IF(A76="","",SUMIF(Expenses!$B$2:$B$3000,A76,Expenses!$E$2:$E$3000)) -> 0 | R76: =IF(A76="","",N(P76)+N(Q76)) -> 16011 | T76: 45903 | U76: 16728 | V76: 0 | X76: =IF(B76<>"SOLD","",IF(C76="Consignment",N(W76)-R76,N(U76)-R76-N(V76))) -> 717 | Y76: =IF(OR(X76="",N(R76)=0),"",X76/R76) -> 0.044781713 | Z76: =IF(O76="","",IF(T76="",TODAY(),T76)-O76) -> 188 | AA76: =IF(T76="","",TEXT(T76,"YYYY-MM")) -> 2025-09 | AB76: =IF(X76="","",X76/2) -> 358.5
A77: 77 | B77: SOLD | C77: Own purchase | D77: Škoda | E77: Karoq | F77: Style | G77: 44317 | H77: 2.0 TDI 85 kW | I77: MT6 | K77: 199700 | M77: IT | N77: D | O77: 45715 | P77: 11429 | Q77: =IF(A77="","",SUMIF(Expenses!$B$2:$B$3000,A77,Expenses!$E$2:$E$3000)) -> 0 | R77: =IF(A77="","",N(P77)+N(Q77)) -> 11429 | T77: 45784 | U77: 16300 | V77: 3048 | X77: =IF(B77<>"SOLD","",IF(C77="Consignment",N(W77)-R77,N(U77)-R77-N(V77))) -> 1823 | Y77: =IF(OR(X77="",N(R77)=0),"",X77/R77) -> 0.15950652 | Z77: =IF(O77="","",IF(T77="",TODAY(),T77)-O77) -> 69 | AA77: =IF(T77="","",TEXT(T77,"YYYY-MM")) -> 2025-05 | AB77: =IF(X77="","",X77/2) -> 911.5
A78: 78 | B78: SOLD | C78: Own purchase | D78: Citroën | E78: Jumpy | F78: L2H1 | G78: 43009 | H78: 2.0 HDI 90 kW | I78: MT6 | K78: 195600 | M78: DE | N78: D | O78: 45723 | P78: 6952 | Q78: =IF(A78="","",SUMIF(Expenses!$B$2:$B$3000,A78,Expenses!$E$2:$E$3000)) -> 0 | R78: =IF(A78="","",N(P78)+N(Q78)) -> 6952 | T78: 45770 | U78: 11350 | V78: 2122 | X78: =IF(B78<>"SOLD","",IF(C78="Consignment",N(W78)-R78,N(U78)-R78-N(V78))) -> 2276 | Y78: =IF(OR(X78="",N(R78)=0),"",X78/R78) -> 0.3273878 | Z78: =IF(O78="","",IF(T78="",TODAY(),T78)-O78) -> 47 | AA78: =IF(T78="","",TEXT(T78,"YYYY-MM")) -> 2025-04 | AB78: =IF(X78="","",X78/2) -> 1138
A79: 79 | B79: SOLD | C79: Own purchase | D79: Škoda | E79: Octavia Combi | F79: Ambition | G79: 42856 | H79: 2.0 TDI 110 kW | I79: MT6 | K79: 150400 | M79: DE | N79: M | O79: 45735 | P79: 11856.99 | Q79: =IF(A79="","",SUMIF(Expenses!$B$2:$B$3000,A79,Expenses!$E$2:$E$3000)) -> 0 | R79: =IF(A79="","",N(P79)+N(Q79)) -> 11856.99 | T79: 45773 | U79: 13850 | V79: 0.01 | X79: =IF(B79<>"SOLD","",IF(C79="Consignment",N(W79)-R79,N(U79)-R79-N(V79))) -> 1993 | Y79: =IF(OR(X79="",N(R79)=0),"",X79/R79) -> 0.1680865 | Z79: =IF(O79="","",IF(T79="",TODAY(),T79)-O79) -> 38 | AA79: =IF(T79="","",TEXT(T79,"YYYY-MM")) -> 2025-04 | AB79: =IF(X79="","",X79/2) -> 996.5
A80: 80 | B80: SOLD | C80: Own purchase | D80: VW | E80: Golf Variant | F80: Comfortline | G80: 41974 | H80: 1.4 TSI 92 kW CZCA | I80: DSG7 | K80: 161500 | M80: DE | N80: M | O80: 45756 | P80: 9242 | Q80: =IF(A80="","",SUMIF(Expenses!$B$2:$B$3000,A80,Expenses!$E$2:$E$3000)) -> 0 | R80: =IF(A80="","",N(P80)+N(Q80)) -> 9242 | T80: 46005 | U80: 9500 | V80: 0 | X80: =IF(B80<>"SOLD","",IF(C80="Consignment",N(W80)-R80,N(U80)-R80-N(V80))) -> 258 | Y80: =IF(OR(X80="",N(R80)=0),"",X80/R80) -> 0.027916035 | Z80: =IF(O80="","",IF(T80="",TODAY(),T80)-O80) -> 249 | AA80: =IF(T80="","",TEXT(T80,"YYYY-MM")) -> 2025-12 | AB80: =IF(X80="","",X80/2) -> 129
A81: 81 | B81: SOLD | C81: Own purchase | D81: VW | E81: Touran | F81: Comfortline | G81: 43009 | H81: 2.0 TDI 110 kW DFGA | I81: MT6 | K81: 190800 | M81: FR | N81: M | O81: 45756 | P81: 12351.11 | Q81: =IF(A81="","",SUMIF(Expenses!$B$2:$B$3000,A81,Expenses!$E$2:$E$3000)) -> 0 | R81: =IF(A81="","",N(P81)+N(Q81)) -> 12351.11 | T81: 45834 | U81: 13950 | V81: -0.11 | X81: =IF(B81<>"SOLD","",IF(C81="Consignment",N(W81)-R81,N(U81)-R81-N(V81))) -> 1599 | Y81: =IF(OR(X81="",N(R81)=0),"",X81/R81) -> 0.12946205 | Z81: =IF(O81="","",IF(T81="",TODAY(),T81)-O81) -> 78 | AA81: =IF(T81="","",TEXT(T81,"YYYY-MM")) -> 2025-06 | AB81: =IF(X81="","",X81/2) -> 799.5
A82: 82 | B82: SOLD | C82: Own purchase | D82: Škoda | E82: Octavia Combi | F82: Elegance | G82: 41609 | H82: 1.4 TSI 103 kW | I82: MT6 | K82: 194400 | M82: NL | N82: M | O82: 45765 | P82: 7971.17 | Q82: =IF(A82="","",SUMIF(Expenses!$B$2:$B$3000,A82,Expenses!$E$2:$E$3000)) -> 0 | R82: =IF(A82="","",N(P82)+N(Q82)) -> 7971.17 | T82: 45879 | U82: 9350 | V82: -0.17 | X82: =IF(B82<>"SOLD","",IF(C82="Consignment",N(W82)-R82,N(U82)-R82-N(V82))) -> 1379 | Y82: =IF(OR(X82="",N(R82)=0),"",X82/R82) -> 0.17299844 | Z82: =IF(O82="","",IF(T82="",TODAY(),T82)-O82) -> 114 | AA82: =IF(T82="","",TEXT(T82,"YYYY-MM")) -> 2025-08 | AB82: =IF(X82="","",X82/2) -> 689.5
A83: 83 | B83: SOLD | C83: Own purchase | D83: Seat | E83: Ateca | F83: Style | G83: 42644 | H83: 1.4 TSI 110 kW | I83: MT6 | K83: 147600 | M83: BE | N83: M | O83: 45769 | P83: 13198.16 | Q83: =IF(A83="","",SUMIF(Expenses!$B$2:$B$3000,A83,Expenses!$E$2:$E$3000)) -> 0 | R83: =IF(A83="","",N(P83)+N(Q83)) -> 13198.16 | T83: 45840 | U83: 14900 | V83: -0.16 | X83: =IF(B83<>"SOLD","",IF(C83="Consignment",N(W83)-R83,N(U83)-R83-N(V83))) -> 1702 | Y83: =IF(OR(X83="",N(R83)=0),"",X83/R83) -> 0.12895737 | Z83: =IF(O83="","",IF(T83="",TODAY(),T83)-O83) -> 71 | AA83: =IF(T83="","",TEXT(T83,"YYYY-MM")) -> 2025-07 | AB83: =IF(X83="","",X83/2) -> 851
A84: 84 | B84: SOLD | C84: Own purchase | D84: VW | E84: Tiguan | F84: Trend & Fun | G84: 41609 | H84: 1.4 TSI 90 kW | I84: MT6 | K84: 161600 | M84: DE | N84: M | O84: 45770 | P84: 8134.43 | Q84: =IF(A84="","",SUMIF(Expenses!$B$2:$B$3000,A84,Expenses!$E$2:$E$3000)) -> 0 | R84: =IF(A84="","",N(P84)+N(Q84)) -> 8134.43 | T84: 45871 | U84: 9655 | V84: -0.43 | X84: =IF(B84<>"SOLD","",IF(C84="Consignment",N(W84)-R84,N(U84)-R84-N(V84))) -> 1521 | Y84: =IF(OR(X84="",N(R84)=0),"",X84/R84) -> 0.18698298 | Z84: =IF(O84="","",IF(T84="",TODAY(),T84)-O84) -> 101 | AA84: =IF(T84="","",TEXT(T84,"YYYY-MM")) -> 2025-08 | AB84: =IF(X84="","",X84/2) -> 760.5
A85: 85 | B85: SOLD | C85: Own purchase | D85: Škoda | E85: Octavia Combi | F85: Ambition | G85: 43070 | H85: 1.5 TSI 110 kW | I85: MT6 | K85: 133000 | M85: DE | N85: M | O85: 45777 | P85: 11745.6 | Q85: =IF(A85="","",SUMIF(Expenses!$B$2:$B$3000,A85,Expenses!$E$2:$E$3000)) -> 0 | R85: =IF(A85="","",N(P85)+N(Q85)) -> 11745.6 | T85: 46070 | U85: 12300 | V85: 0.4 | X85: =IF(B85<>"SOLD","",IF(C85="Consignment",N(W85)-R85,N(U85)-R85-N(V85))) -> 554 | Y85: =IF(OR(X85="",N(R85)=0),"",X85/R85) -> 0.047166599 | Z85: =IF(O85="","",IF(T85="",TODAY(),T85)-O85) -> 293 | AA85: =IF(T85="","",TEXT(T85,"YYYY-MM")) -> 2026-02 | AB85: =IF(X85="","",X85/2) -> 277
A86: 86 | B86: SOLD | C86: Own purchase | D86: VW | E86: Tiguan | F86: Comfortline | G86: 42614 | H86: 2.0 TDI 110 kW | I86: MT6 | K86: 173500 | M86: DE | N86: M | O86: 45777 | P86: 14160.7 | Q86: =IF(A86="","",SUMIF(Expenses!$B$2:$B$3000,A86,Expenses!$E$2:$E$3000)) -> 0 | R86: =IF(A86="","",N(P86)+N(Q86)) -> 14160.7 | T86: 45881 | U86: 17350 | V86: 0.3 | X86: =IF(B86<>"SOLD","",IF(C86="Consignment",N(W86)-R86,N(U86)-R86-N(V86))) -> 3189 | Y86: =IF(OR(X86="",N(R86)=0),"",X86/R86) -> 0.22520073 | Z86: =IF(O86="","",IF(T86="",TODAY(),T86)-O86) -> 104 | AA86: =IF(T86="","",TEXT(T86,"YYYY-MM")) -> 2025-08 | AB86: =IF(X86="","",X86/2) -> 1594.5
A87: 87 | B87: SOLD | C87: Own purchase | D87: VW | E87: Passat Variant | F87: Comfortline | G87: 42644 | H87: 2.0 TDI 140 kW 4Motion | I87: DSG6 | J87: 4x4 | K87: 181400 | M87: DE | N87: M | O87: 45782 | P87: 12668 | Q87: =IF(A87="","",SUMIF(Expenses!$B$2:$B$3000,A87,Expenses!$E$2:$E$3000)) -> 0 | R87: =IF(A87="","",N(P87)+N(Q87)) -> 12668 | T87: 45793 | U87: 14900 | V87: 0 | X87: =IF(B87<>"SOLD","",IF(C87="Consignment",N(W87)-R87,N(U87)-R87-N(V87))) -> 2232 | Y87: =IF(OR(X87="",N(R87)=0),"",X87/R87) -> 0.17619198 | Z87: =IF(O87="","",IF(T87="",TODAY(),T87)-O87) -> 11 | AA87: =IF(T87="","",TEXT(T87,"YYYY-MM")) -> 2025-05 | AB87: =IF(X87="","",X87/2) -> 1116
A88: 88 | B88: SOLD | C88: Own purchase | D88: Hyundai | E88: Tucson | F88: Style | G88: 43160 | H88: 1.7 CRDI 104 kW | I88: DCT7 | K88: 187000 | M88: FR | N88: M | O88: 45784 | P88: 11500 | Q88: =IF(A88="","",SUMIF(Expenses!$B$2:$B$3000,A88,Expenses!$E$2:$E$3000)) -> 0 | R88: =IF(A88="","",N(P88)+N(Q88)) -> 11500 | T88: 45803 | U88: 12300 | V88: 0 | X88: =IF(B88<>"SOLD","",IF(C88="Consignment",N(W88)-R88,N(U88)-R88-N(V88))) -> 800 | Y88: =IF(OR(X88="",N(R88)=0),"",X88/R88) -> 0.069565217 | Z88: =IF(O88="","",IF(T88="",TODAY(),T88)-O88) -> 19 | AA88: =IF(T88="","",TEXT(T88,"YYYY-MM")) -> 2025-05 | AB88: =IF(X88="","",X88/2) -> 400
A89: 89 | B89: SOLD | C89: Own purchase | D89: Škoda | E89: Superb Combi | F89: Style | G89: 42552 | H89: 2.0 TDI 140 kW | I89: MT6 | K89: 106100 | M89: AT | N89: M | O89: 45793 | P89: 15334.24 | Q89: =IF(A89="","",SUMIF(Expenses!$B$2:$B$3000,A89,Expenses!$E$2:$E$3000)) -> 0 | R89: =IF(A89="","",N(P89)+N(Q89)) -> 15334.24 | T89: 45890 | U89: 17550 | V89: -0.24 | X89: =IF(B89<>"SOLD","",IF(C89="Consignment",N(W89)-R89,N(U89)-R89-N(V89))) -> 2216 | Y89: =IF(OR(X89="",N(R89)=0),"",X89/R89) -> 0.14451319 | Z89: =IF(O89="","",IF(T89="",TODAY(),T89)-O89) -> 97 | AA89: =IF(T89="","",TEXT(T89,"YYYY-MM")) -> 2025-08 | AB89: =IF(X89="","",X89/2) -> 1108
A90: 90 | B90: SOLD | C90: Own purchase | D90: Seat | E90: Ateca | F90: Xcellence | G90: 42675 | H90: 1.4 TIS 110 kW | I90: MT6 | K90: 150400 | M90: DE | N90: M | O90: 45794 | P90: 12492 | Q90: =IF(A90="","",SUMIF(Expenses!$B$2:$B$3000,A90,Expenses!$E$2:$E$3000)) -> 0 | R90: =IF(A90="","",N(P90)+N(Q90)) -> 12492 | T90: 45852 | U90: 15000 | V90: 0 | X90: =IF(B90<>"SOLD","",IF(C90="Consignment",N(W90)-R90,N(U90)-R90-N(V90))) -> 2508 | Y90: =IF(OR(X90="",N(R90)=0),"",X90/R90) -> 0.20076849 | Z90: =IF(O90="","",IF(T90="",TODAY(),T90)-O90) -> 58 | AA90: =IF(T90="","",TEXT(T90,"YYYY-MM")) -> 2025-07 | AB90: =IF(X90="","",X90/2) -> 1254
A91: 91 | B91: SOLD | C91: Own purchase | D91: Škoda | E91: Octavia Combi | F91: Style | G91: 43678 | H91: 2.0 TDI 110 kW | I91: MT6 | K91: 195400 | M91: AT | N91: M | O91: 45813 | P91: 11716.54 | Q91: =IF(A91="","",SUMIF(Expenses!$B$2:$B$3000,A91,Expenses!$E$2:$E$3000)) -> 0 | R91: =IF(A91="","",N(P91)+N(Q91)) -> 11716.54 | T91: 45848 | U91: 13400 | V91: 0.46 | X91: =IF(B91<>"SOLD","",IF(C91="Consignment",N(W91)-R91,N(U91)-R91-N(V91))) -> 1683 | Y91: =IF(OR(X91="",N(R91)=0),"",X91/R91) -> 0.14364309 | Z91: =IF(O91="","",IF(T91="",TODAY(),T91)-O91) -> 35 | AA91: =IF(T91="","",TEXT(T91,"YYYY-MM")) -> 2025-07 | AB91: =IF(X91="","",X91/2) -> 841.5
A92: 92 | B92: SOLD | C92: Own purchase | D92: VW | E92: Tiguan | F92: Trend & Fun | G92: 41122 | H92: 2.0 TDI 81 kW | I92: MT6 | K92: 197500 | M92: DE | N92: M | O92: 45813 | P92: 8214.9 | Q92: =IF(A92="","",SUMIF(Expenses!$B$2:$B$3000,A92,Expenses!$E$2:$E$3000)) -> 0 | R92: =IF(A92="","",N(P92)+N(Q92)) -> 8214.9 | T92: 45847 | U92: 10000 | V92: 0.1 | X92: =IF(B92<>"SOLD","",IF(C92="Consignment",N(W92)-R92,N(U92)-R92-N(V92))) -> 1785 | Y92: =IF(OR(X92="",N(R92)=0),"",X92/R92) -> 0.2172881 | Z92: =IF(O92="","",IF(T92="",TODAY(),T92)-O92) -> 34 | AA92: =IF(T92="","",TEXT(T92,"YYYY-MM")) -> 2025-07 | AB92: =IF(X92="","",X92/2) -> 892.5
A93: 93 | B93: SOLD | C93: Own purchase | D93: Škoda | E93: Octavia Combi | F93: Ambition | G93: 42917 | H93: 2.0 TDI 110 kW | I93: DSG6 | K93: 180200 | M93: DE | N93: M | O93: 45828 | P93: 10565 | Q93: =IF(A93="","",SUMIF(Expenses!$B$2:$B$3000,A93,Expenses!$E$2:$E$3000)) -> 0 | R93: =IF(A93="","",N(P93)+N(Q93)) -> 10565 | T93: 46056 | U93: 11600 | V93: 0 | X93: =IF(B93<>"SOLD","",IF(C93="Consignment",N(W93)-R93,N(U93)-R93-N(V93))) -> 1035 | Y93: =IF(OR(X93="",N(R93)=0),"",X93/R93) -> 0.097964979 | Z93: =IF(O93="","",IF(T93="",TODAY(),T93)-O93) -> 228 | AA93: =IF(T93="","",TEXT(T93,"YYYY-MM")) -> 2026-02 | AB93: =IF(X93="","",X93/2) -> 517.5
A94: 94 | B94: SOLD | C94: Consignment | D94: VW | E94: Passat Variant | F94: Alltrack | G94: 44501 | H94: 2.0 TDI 147 kW 4Motion | I94: DSG7 | J94: 4x4 | K94: 48300 | M94: CZ | N94: M | O94: 45841 | P94: 1966.74 | Q94: =IF(A94="","",SUMIF(Expenses!$B$2:$B$3000,A94,Expenses!$E$2:$E$3000)) -> 0 | R94: =IF(A94="","",N(P94)+N(Q94)) -> 1966.74 | T94: 45847 | U94: 31617 | W94: 3166.74 | X94: =IF(B94<>"SOLD","",IF(C94="Consignment",N(W94)-R94,N(U94)-R94-N(V94))) -> 1200 | Y94: =IF(OR(X94="",N(R94)=0),"",X94/R94) -> 0.61014674 | Z94: =IF(O94="","",IF(T94="",TODAY(),T94)-O94) -> 6 | AA94: =IF(T94="","",TEXT(T94,"YYYY-MM")) -> 2025-07 | AB94: =IF(X94="","",X94/2) -> 600
A95: 95 | B95: SOLD | C95: Own purchase | D95: Škoda | E95: Octavia Combi | F95: Ambition | G95: 43282 | H95: 1.5 TSI 110 kW | I95: DSG7 | K95: 126200 | M95: FR | N95: M | O95: 45853 | P95: 12050.48 | Q95: =IF(A95="","",SUMIF(Expenses!$B$2:$B$3000,A95,Expenses!$E$2:$E$3000)) -> 0 | R95: =IF(A95="","",N(P95)+N(Q95)) -> 12050.48 | T95: 45876 | U95: 14740 | V95: -0.48 | X95: =IF(B95<>"SOLD","",IF(C95="Consignment",N(W95)-R95,N(U95)-R95-N(V95))) -> 2690 | Y95: =IF(OR(X95="",N(R95)=0),"",X95/R95) -> 0.22322762 | Z95: =IF(O95="","",IF(T95="",TODAY(),T95)-O95) -> 23 | AA95: =IF(T95="","",TEXT(T95,"YYYY-MM")) -> 2025-08 | AB95: =IF(X95="","",X95/2) -> 1345
A96: 96 | B96: SOLD | C96: Consignment | D96: Maserati | E96: Ghibli S Q4 | F96: GranSport | G96: 43009 | H96: 3.0 V6 316 kW | I96: AT8 | J96: 4x4 | K96: 118800 | M96: CZ | N96: M | O96: 45841 | P96: 1451 | Q96: =IF(A96="","",SUMIF(Expenses!$B$2:$B$3000,A96,Expenses!$E$2:$E$3000)) -> 0 | R96: =IF(A96="","",N(P96)+N(Q96)) -> 1451 | T96: 45847 | U96: 38701 | W96: 2701 | X96: =IF(B96<>"SOLD","",IF(C96="Consignment",N(W96)-R96,N(U96)-R96-N(V96))) -> 1250 | Y96: =IF(OR(X96="",N(R96)=0),"",X96/R96) -> 0.86147484 | Z96: =IF(O96="","",IF(T96="",TODAY(),T96)-O96) -> 6 | AA96: =IF(T96="","",TEXT(T96,"YYYY-MM")) -> 2025-07 | AB96: =IF(X96="","",X96/2) -> 625
A97: 97 | B97: SOLD | C97: Own purchase | D97: VW | E97: Passat Variant | F97: Highline | G97: 42339 | H97: 2.0 TDI 140 kW 4Motion | I97: DSG6 | J97: 4x4 | K97: 195000 | M97: DE | N97: M | O97: 45859 | P97: 12063.57 | Q97: =IF(A97="","",SUMIF(Expenses!$B$2:$B$3000,A97,Expenses!$E$2:$E$3000)) -> 0 | R97: =IF(A97="","",N(P97)+N(Q97)) -> 12063.57 | T97: 46033 | U97: 12700 | V97: 0.43 | X97: =IF(B97<>"SOLD","",IF(C97="Consignment",N(W97)-R97,N(U97)-R97-N(V97))) -> 636 | Y97: =IF(OR(X97="",N(R97)=0),"",X97/R97) -> 0.052720712 | Z97: =IF(O97="","",IF(T97="",TODAY(),T97)-O97) -> 174 | AA97: =IF(T97="","",TEXT(T97,"YYYY-MM")) -> 2026-01 | AB97: =IF(X97="","",X97/2) -> 318
A98: 98 | B98: SOLD | C98: Own purchase | D98: Škoda | E98: Octavia Combi | F98: Ambition | G98: 41609 | H98: 2.0 TDI 110 kW | I98: DSG6 | K98: 191300 | M98: DE | N98: M | O98: 45870 | P98: 7310 | Q98: =IF(A98="","",SUMIF(Expenses!$B$2:$B$3000,A98,Expenses!$E$2:$E$3000)) -> 0 | R98: =IF(A98="","",N(P98)+N(Q98)) -> 7310 | T98: 46040 | U98: 8100 | V98: 0 | X98: =IF(B98<>"SOLD","",IF(C98="Consignment",N(W98)-R98,N(U98)-R98-N(V98))) -> 790 | Y98: =IF(OR(X98="",N(R98)=0),"",X98/R98) -> 0.10807114 | Z98: =IF(O98="","",IF(T98="",TODAY(),T98)-O98) -> 170 | AA98: =IF(T98="","",TEXT(T98,"YYYY-MM")) -> 2026-01 | AB98: =IF(X98="","",X98/2) -> 395
A99: 99 | B99: SOLD | C99: Consignment | D99: Kia | E99: Sportage | F99: Gold | G99: 44986 | H99: 1.6 CRDi 100 kW | I99: DCT7 | K99: 63000 | N99: M | O99: 45884 | P99: 43 | Q99: =IF(A99="","",SUMIF(Expenses!$B$2:$B$3000,A99,Expenses!$E$2:$E$3000)) -> 0 | R99: =IF(A99="","",N(P99)+N(Q99)) -> 43 | T99: 45919 | U99: 900 | W99: 900 | X99: =IF(B99<>"SOLD","",IF(C99="Consignment",N(W99)-R99,N(U99)-R99-N(V99))) -> 857 | Y99: =IF(OR(X99="",N(R99)=0),"",X99/R99) -> 19.930233 | Z99: =IF(O99="","",IF(T99="",TODAY(),T99)-O99) -> 35 | AA99: =IF(T99="","",TEXT(T99,"YYYY-MM")) -> 2025-09 | AB99: =IF(X99="","",X99/2) -> 428.5
A100: 100 | B100: SOLD | C100: Own purchase | D100: Škoda | E100: Karoq | F100: Style | G100: 43435 | H100: 1.5 TSI 110 kW | I100: DSG7 | K100: 177600 | M100: BE | N100: M | O100: 45884 | P100: 14692.85 | Q100: =IF(A100="","",SUMIF(Expenses!$B$2:$B$3000,A100,Expenses!$E$2:$E$3000)) -> 0 | R100: =IF(A100="","",N(P100)+N(Q100)) -> 14692.85 | T100: 46036 | U100: 15800 | V100: 0.15 | X100: =IF(B100<>"SOLD","",IF(C100="Consignment",N(W100)-R100,N(U100)-R100-N(V100))) -> 1107 | Y100: =IF(OR(X100="",N(R100)=0),"",X100/R100) -> 0.075342769 | Z100: =IF(O100="","",IF(T100="",TODAY(),T100)-O100) -> 152 | AA100: =IF(T100="","",TEXT(T100,"YYYY-MM")) -> 2026-01 | AB100: =IF(X100="","",X100/2) -> 553.5
...

Sheet Expenses
A1: Date | B1: Car ID | C1: Category | D1: Description | E1: Amount (€) | F1: Paid by | G1: Invoice / receipt no.
A2: 46223 | B2: EXAMPLE | C2: Repair & service | D2: Example row — serpentine belt + oil change (delete me) | E2: 240 | F2: Partner 1 | G2: FA-2026-0123

Sheet Lists
A1: Status | B1: Deal type | C1: Brand | D1: Gearbox | E1: Drive | F1: Country | G1: VAT scheme | H1: Expense category | I1: Paid by
A2: STOCK | B2: Own purchase | C2: Alfa Romeo | D2: MT5 | E2: FWD | F2: SK | G2: M | H2: Transport / import | I2: Partner 1
A3: RESERVED | B3: Consignment | C3: Audi | D3: MT6 | E3: RWD | F3: CZ | G3: D | H3: Repair & service | I3: Partner 2
A4: SOLD | C4: BMW | D4: DSG6 | E4: 4x4 | F4: AT | H4: Tyres | I4: Company account
C5: Citroën | D5: DSG7 | F5: DE | H5: Cleaning & detailing
C6: Cupra | D6: DCT7 | F6: NL | H6: STK / EK
C7: Ford | D7: DCT8 | F7: BE | H7: Registration & fees
C8: Hyundai | D8: AT1 | F8: LU | H8: Advertising
C9: Kia | D9: AT6 | F9: DK | H9: Fuel
C10: Maserati | D10: AT7 | F10: SE | H10: Other
C11: Mazda | D11: AT8 | F11: FR
C12: Mercedes-Benz | D12: AT9 | F12: IT
C13: Nissan | D13: EDC6 | F13: ES
C14: Opel | F14: HU
C15: Renault | F15: PL
C16: Seat
C17: Toyota
C18: VW
C19: Volvo
C20: Škoda
A62: Add new values at the bottom of a column — the dropdowns pick them up automatically (up to row 60). Rename "Partner 1 / Partner 2" to your names.

Sheet Check these
A1: Things found while moving your data — please check and fix on the Cars tab, then delete the line here
A3: Car ID | B3: Car | C3: What looks wrong | D3: What I did
A4: 1 | B4: Hyundai i40 CW (?) | C4: Purchase date missing. | D4: Left empty — "Days in stock" cannot be calculated. Please fill in.
A5: 1 | B5: Hyundai i40 CW (?) | C5: First registration (model year) missing. | D5: Left empty. Please fill in from the registration papers.
A6: 2 | B6: Kia Cee'd SW (08/2019) | C6: Purchase date missing. | D6: Left empty — "Days in stock" cannot be calculated. Please fill in.
A7: 3 | B7: Škoda Superb Combi (04/2016) | C7: Purchase date missing. | D7: Left empty — "Days in stock" cannot be calculated. Please fill in.
A8: 4 | B8: Mazda 6 (05/2013) | C8: Purchase date missing. | D8: Left empty — "Days in stock" cannot be calculated. Please fill in.
A9: 5 | B9: Škoda Kodiaq (10/2017) | C9: Purchase date missing. | D9: Left empty — "Days in stock" cannot be calculated. Please fill in.
A10: 6 | B10: VW Touran (08/2019) | C10: Purchase date missing. | D10: Left empty — "Days in stock" cannot be calculated. Please fill in.
A11: 7 | B11: Audi A4 Avant (07/2018) | C11: Purchase date missing. | D11: Left empty — "Days in stock" cannot be calculated. Please fill in.
A12: 8 | B12: Škoda Octavia Combi (03/2018) | C12: Purchase date missing. | D12: Left empty — "Days in stock" cannot be calculated. Please fill in.
A13: 9 | B13: Volkswagen Passat (02/2017) | C13: Purchase date missing. | D13: Left empty — "Days in stock" cannot be calculated. Please fill in.
A14: 13 | B14: Seat Ateca (02/2020) | C14: Old profit (576 €) ≠ sale − costs (566 €) and ≠ sale − costs − VAT column (2,250 €). | D14: "VAT & deductions" set to -10.00 € so profit matches the old sheet. Check which number is right.
A15: 16 | B15: Audi A4 Avant (01/2016) | C15: Old profit (1,768 €) ≠ sale − costs (4,101 €) and ≠ sale − costs − VAT column (1,965 €). | D15: "VAT & deductions" set to 2,333.33 € so profit matches the old sheet. Check which number is right.
... A31: 147 | B31: Audi A6 Avant (11/2019) | C31: Commission / consignment deal: "Costs" is a small fee, not a purchase price. | D31: Marked as Consignment. Commission set to recorded profit + costs = 1,000.00 € so profit stays 950.00 €. Please confirm the real commission.
