Workbook

Sheet Overview
B2: AUTOBONO — Full Sales & Inventory Analysis
B3: Bottom-up analysis of the master AUTOBONO Google Sheet ("2023" + "2024" tabs), rebuilt from row-level data.
B4: Data pulled 25 Jul 2026. Every figure below is a live formula against the "Raw Data" tab — nothing is hand-typed.
B6: Completed sales | D6: Total revenue (sold) | F6: Total realized profit
B7: =COUNTIF('Raw Data'!$U$2:$U$149,"SOLD") -> 129 | D7: =SUMIF('Raw Data'!$U$2:$U$149,"SOLD",'Raw Data'!$O$2:$O$149) -> 1813360 | F7: =SUMIF('Raw Data'!$U$2:$U$149,"SOLD",'Raw Data'!$P$2:$P$149) -> 217918.12
B11: Weighted margin (total profit ÷ total cost, sold deals) | D11: =SUMIF('Raw Data'!$U$2:$U$149,"SOLD",'Raw Data'!$P$2:$P$149)/SUMIF('Raw Data'!$U$2:$U$149,"SOLD",'Raw Data'!$K$2:$K$149) -> 0.16219911
B12: Average profit / deal | D12: =SUMIF('Raw Data'!$U$2:$U$149,"SOLD",'Raw Data'!$P$2:$P$149)/COUNTIF('Raw Data'!$U$2:$U$149,"SOLD") -> 1689.2878
B13: Median profit / deal | D13: =MEDIAN('Raw Data'!$W$2:$W$149) -> 1693
B14: Average margin % of cost (simple average across deals) | D14: =AVERAGEIF('Raw Data'!$U$2:$U$149,"SOLD",'Raw Data'!$Q$2:$Q$149) -> 0.69859535
B15: Median margin % of cost | D15: =MEDIAN('Raw Data'!$X$2:$X$149) -> 0.1672
B16: Cars currently in stock / pending | D16: =COUNTIF('Raw Data'!$U$2:$U$149,"STOCK") -> 19
B17: Capital tied up in current stock (cost basis) | D17: =SUMIF('Raw Data'!$U$2:$U$149,"STOCK",'Raw Data'!$K$2:$K$149) -> 173310.06
B18: Total unique vehicles logged (2023 start – Jul 2026) | D18: =COUNTA('Raw Data'!$A$2:$A$149) -> 148
B20: Cross-check vs. the sheet's own embedded dashboard
B21: The AUTOBONO sheet has its own dashboard totals baked into the "2024" tab (row 4). Comparing them to our bottom-up recompute:
B22: Metric | C22: Sheet's own dashboard value | D22: Our bottom-up formula result | E22: Match?
B23: 2024 tab: Total Costs, all 139 logged cars (sold + stock) | C23: 1400197.1 | D23: =SUMIFS('Raw Data'!$K$2:$K$149,'Raw Data'!$B$2:$B$149,2024) -> 1400197.1 | E23: =IF(ABS(C23-D23)<500,"Match","Check") -> Match
B24: 2024 tab: Total Sale revenue, sold cars only | C24: 1697960 | D24: =SUMIFS('Raw Data'!$O$2:$O$149,'Raw Data'!$B$2:$B$149,2024,'Raw Data'!$U$2:$U$149,"SOLD") -> 1697960 | E24: =IF(ABS(C24-D24)<500,"Match","Check") -> Match
B25: 2024 tab: Total Brutto (purchase side), all 139 cars | C25: 1433350 | D25: =SUMIFS('Raw Data'!$N$2:$N$149,'Raw Data'!$B$2:$B$149,2024) -> 1433350 | E25: =IF(ABS(C25-D25)<500,"Match","Check") -> Match
B26: 2024 tab: Total profit, sold cars only | C26: 206543 | D26: =SUMIFS('Raw Data'!$P$2:$P$149,'Raw Data'!$B$2:$B$149,2024,'Raw Data'!$U$2:$U$149,"SOLD") -> 206686 | E26: =IF(ABS(C26-D26)<500,"Match","Check") -> Match
B28: Note: the "2023" tab's own dashboard total profit (–84,824.22 €) is NOT comparable — its formula counts unsold cars as a full loss (sale price 0 minus full cost) rather than excluding them. Our figures exclude unsold cars from profit and report them separately as inventory instead (see "Cars currently in stock" above). Also: the 2024 dashboard's Netto total (1,281,133.14 €) is ~10.7k € lower than our bottom-up Netto sum (~1,291,870 €) — a small unexplained residual in the original sheet; it does not affect Costs, Brutto, Sales or Profit, which all reconcile within rounding.
B33: Top takeaways
B34: 1. Touran is your thinnest high-volume model.
B35: VW Touran: 8 sold, only 10,233 € total profit at a 10.6% weighted margin — well below the 16.2% company average and the lowest of any model with 5+ deals. Avg profit/deal is 1,279 € vs. ~1,690 € company-wide. Worth a firmer floor buy-price or walking away from thin Touran deals.
B38: 2. Audi A4 is your best repeat performer.
B39: 8 sold, 19,622 € total profit at 19.9% margin, avg profit/deal 2,453 € — the strongest volume model in the book. Skoda Octavia is the volume leader (21 sold, 30,749 € total profit) but at a lower 15.8% margin — good for cash flow, less good per unit.
B42: 3. Profit is concentrated in a handful of models.
B43: The top 5 models by profit (Skoda Octavia, Audi A4, Seat Ateca, VW Tiguan, VW Golf) produced ≈ 98.6k € of the 217.9k € total — about 45% of all profit from 5 of 41 model groups.
B46: 4. ≈160k € of capital is sitting in 19 unsold cars.
B47: Several have been listed since Nov 2025–Feb 2026 without selling (e.g. Alfa Romeo Stelvio, VW Tiguan, Seat Ateca, Skoda Karoq). Worth a slow-mover review — price cuts or wholesale exit on the oldest ones frees up cash.
B50: 5. Watch for consignment deals skewing "margin %".
B51: BMW 420d, Audi A6 Avant, Kia Sportage and Nissan Navara show 900%+ "margin" — these are investor consignment/commission flips with a nominal 50–650 € recorded cost, not real buy-resell economics. Their euro profit is real; exclude them when benchmarking margin % by model.

Sheet By Model
B2: Sold deals by model group
B3: Only completed (SOLD) deals are counted. Sorted by total profit, high to low. All cells are live formulas against the Raw Data tab.
B5: Model group | C5: Deals sold | D5: Total revenue (€) | E5: Total costs (€) | F5: Total profit (€) | G5: Avg profit / deal (€) | H5: Avg margin % of cost | I5: Weighted margin % (profit/cost)
B6: Škoda Octavia | C6: =COUNTIFS('Raw Data'!$V$2:$V$149,$B6,'Raw Data'!$U$2:$U$149,"SOLD") -> 21 | D6: =SUMIFS('Raw Data'!$O$2:$O$149,'Raw Data'!$V$2:$V$149,$B6,'Raw Data'!$U$2:$U$149,"SOLD") -> 237510 | E6: =SUMIFS('Raw Data'!$K$2:$K$149,'Raw Data'!$V$2:$V$149,$B6,'Raw Data'!$U$2:$U$149,"SOLD") -> 196245.81 | F6: =SUMIFS('Raw Data'!$P$2:$P$149,'Raw Data'!$V$2:$V$149,$B6,'Raw Data'!$U$2:$U$149,"SOLD") -> 30749.4 | G6: =IF(C6=0,"",F6/C6) -> 1464.2571 | H6: =IFERROR(AVERAGEIFS('Raw Data'!$Q$2:$Q$149,'Raw Data'!$V$2:$V$149,$B6,'Raw Data'!$U$2:$U$149,"SOLD"),"") -> 0.15797143 | I6: =IF(E6=0,"",F6/E6) -> 0.15668819
B7: Audi A4 | C7: =COUNTIFS('Raw Data'!$V$2:$V$149,$B7,'Raw Data'!$U$2:$U$149,"SOLD") -> 8 | D7: =SUMIFS('Raw Data'!$O$2:$O$149,'Raw Data'!$V$2:$V$149,$B7,'Raw Data'!$U$2:$U$149,"SOLD") -> 123140 | E7: =SUMIFS('Raw Data'!$K$2:$K$149,'Raw Data'!$V$2:$V$149,$B7,'Raw Data'!$U$2:$U$149,"SOLD") -> 98067.59 | F7: =SUMIFS('Raw Data'!$P$2:$P$149,'Raw Data'!$V$2:$V$149,$B7,'Raw Data'!$U$2:$U$149,"SOLD") -> 19622 | G7: =IF(C7=0,"",F7/C7) -> 2452.75 | H7: =IFERROR(AVERAGEIFS('Raw Data'!$Q$2:$Q$149,'Raw Data'!$V$2:$V$149,$B7,'Raw Data'!$U$2:$U$149,"SOLD"),"") -> 0.199225 | I7: =IF(E7=0,"",F7/E7) -> 0.20008649
B8: Seat Ateca | C8: =COUNTIFS('Raw Data'!$V$2:$V$149,$B8,'Raw Data'!$U$2:$U$149,"SOLD") -> 10 | D8: =SUMIFS('Raw Data'!$O$2:$O$149,'Raw Data'!$V$2:$V$149,$B8,'Raw Data'!$U$2:$U$149,"SOLD") -> 138490 | E8: =SUMIFS('Raw Data'!$K$2:$K$149,'Raw Data'!$V$2:$V$149,$B8,'Raw Data'!$U$2:$U$149,"SOLD") -> 116385.16 | F8: =SUMIFS('Raw Data'!$P$2:$P$149,'Raw Data'!$V$2:$V$149,$B8,'Raw Data'!$U$2:$U$149,"SOLD") -> 18825 | G8: =IF(C8=0,"",F8/C8) -> 1882.5 | H8: =IFERROR(AVERAGEIFS('Raw Data'!$Q$2:$Q$149,'Raw Data'!$V$2:$V$149,$B8,'Raw Data'!$U$2:$U$149,"SOLD"),"") -> 0.16513 | I8: =IF(E8=0,"",F8/E8) -> 0.16174743
B9: VW Tiguan | C9: =COUNTIFS('Raw Data'!$V$2:$V$149,$B9,'Raw Data'!$U$2:$U$149,"SOLD") -> 8 | D9: =SUMIFS('Raw Data'!$O$2:$O$149,'Raw Data'!$V$2:$V$149,$B9,'Raw Data'!$U$2:$U$149,"SOLD") -> 92195 | E9: =SUMIFS('Raw Data'!$K$2:$K$149,'Raw Data'!$V$2:$V$149,$B9,'Raw Data'!$U$2:$U$149,"SOLD") -> 76456.11 | F9: =SUMIFS('Raw Data'!$P$2:$P$149,'Raw Data'!$V$2:$V$149,$B9,'Raw Data'!$U$2:$U$149,"SOLD") -> 15344 | G9: =IF(C9=0,"",F9/C9) -> 1918 | H9: =IFERROR(AVERAGEIFS('Raw Data'!$Q$2:$Q$149,'Raw Data'!$V$2:$V$149,$B9,'Raw Data'!$U$2:$U$149,"SOLD"),"") -> 0.2044875 | I9: =IF(E9=0,"",F9/E9) -> 0.2006903
B10: VW Golf | C10: =COUNTIFS('Raw Data'!$V$2:$V$149,$B10,'Raw Data'!$U$2:$U$149,"SOLD") -> 7 | D10: =SUMIFS('Raw Data'!$O$2:$O$149,'Raw Data'!$V$2:$V$149,$B10,'Raw Data'!$U$2:$U$149,"SOLD") -> 82750 | E10: =SUMIFS('Raw Data'!$K$2:$K$149,'Raw Data'!$V$2:$V$149,$B10,'Raw Data'!$U$2:$U$149,"SOLD") -> 65831.89 | F10: =SUMIFS('Raw Data'!$P$2:$P$149,'Raw Data'!$V$2:$V$149,$B10,'Raw Data'!$U$2:$U$149,"SOLD") -> 13977 | G10: =IF(C10=0,"",F10/C10) -> 1996.7143 | H10: =IFERROR(AVERAGEIFS('Raw Data'!$Q$2:$Q$149,'Raw Data'!$V$2:$V$149,$B10,'Raw Data'!$U$2:$U$149,"SOLD"),"") -> 0.212 | I10: =IF(E10=0,"",F10/E10) -> 0.21231352
B11: Škoda Superb | C11: =COUNTIFS('Raw Data'!$V$2:$V$149,$B11,'Raw Data'!$U$2:$U$149,"SOLD") -> 6 | D11: =SUMIFS('Raw Data'!$O$2:$O$149,'Raw Data'!$V$2:$V$149,$B11,'Raw Data'!$U$2:$U$149,"SOLD") -> 91440 | E11: =SUMIFS('Raw Data'!$K$2:$K$149,'Raw Data'!$V$2:$V$149,$B11,'Raw Data'!$U$2:$U$149,"SOLD") -> 75821.79 | F11: =SUMIFS('Raw Data'!$P$2:$P$149,'Raw Data'!$V$2:$V$149,$B11,'Raw Data'!$U$2:$U$149,"SOLD") -> 12890.59 | G11: =IF(C11=0,"",F11/C11) -> 2148.4317 | H11: =IFERROR(AVERAGEIFS('Raw Data'!$Q$2:$Q$149,'Raw Data'!$V$2:$V$149,$B11,'Raw Data'!$U$2:$U$149,"SOLD"),"") -> 0.17955 | I11: =IF(E11=0,"",F11/E11) -> 0.17001168
B12: VW Passat | C12: =COUNTIFS('Raw Data'!$V$2:$V$149,$B12,'Raw Data'!$U$2:$U$149,"SOLD") -> 9 | D12: =SUMIFS('Raw Data'!$O$2:$O$149,'Raw Data'!$V$2:$V$149,$B12,'Raw Data'!$U$2:$U$149,"SOLD") -> 147116 | E12: =SUMIFS('Raw Data'!$K$2:$K$149,'Raw Data'!$V$2:$V$149,$B12,'Raw Data'!$U$2:$U$149,"SOLD") -> 102510.96 | F12: =SUMIFS('Raw Data'!$P$2:$P$149,'Raw Data'!$V$2:$V$149,$B12,'Raw Data'!$U$2:$U$149,"SOLD") -> 11657 | G12: =IF(C12=0,"",F12/C12) -> 1295.2222 | H12: =IFERROR(AVERAGEIFS('Raw Data'!$Q$2:$Q$149,'Raw Data'!$V$2:$V$149,$B12,'Raw Data'!$U$2:$U$149,"SOLD"),"") -> 0.16414444 | I12: =IF(E12=0,"",F12/E12) -> 0.11371467
B13: VW Touran | C13: =COUNTIFS('Raw Data'!$V$2:$V$149,$B13,'Raw Data'!$U$2:$U$149,"SOLD") -> 8 | D13: =SUMIFS('Raw Data'!$O$2:$O$149,'Raw Data'!$V$2:$V$149,$B13,'Raw Data'!$U$2:$U$149,"SOLD") -> 111840 | E13: =SUMIFS('Raw Data'!$K$2:$K$149,'Raw Data'!$V$2:$V$149,$B13,'Raw Data'!$U$2:$U$149,"SOLD") -> 100761.68 | F13: =SUMIFS('Raw Data'!$P$2:$P$149,'Raw Data'!$V$2:$V$149,$B13,'Raw Data'!$U$2:$U$149,"SOLD") -> 10233 | G13: =IF(C13=0,"",F13/C13) -> 1279.125 | H13: =IFERROR(AVERAGEIFS('Raw Data'!$Q$2:$Q$149,'Raw Data'!$V$2:$V$149,$B13,'Raw Data'!$U$2:$U$149,"SOLD"),"") -> 0.10565 | I13: =IF(E13=0,"",F13/E13) -> 0.10155646
B14: VW ID.3 | C14: =COUNTIFS('Raw Data'!$V$2:$V$149,$B14,'Raw Data'!$U$2:$U$149,"SOLD") -> 5 | D14: =SUMIFS('Raw Data'!$O$2:$O$149,'Raw Data'!$V$2:$V$149,$B14,'Raw Data'!$U$2:$U$149,"SOLD") -> 74250 | E14: =SUMIFS('Raw Data'!$K$2:$K$149,'Raw Data'!$V$2:$V$149,$B14,'Raw Data'!$U$2:$U$149,"SOLD") -> 56891 | F14: =SUMIFS('Raw Data'!$P$2:$P$149,'Raw Data'!$V$2:$V$149,$B14,'Raw Data'!$U$2:$U$149,"SOLD") -> 10010 | G14: =IF(C14=0,"",F14/C14) -> 2002 | H14: =IFERROR(AVERAGEIFS('Raw Data'!$Q$2:$Q$149,'Raw Data'!$V$2:$V$149,$B14,'Raw Data'!$U$2:$U$149,"SOLD"),"") -> 0.18448 | I14: =IF(E14=0,"",F14/E14) -> 0.1759505
B15: Seat Leon | C15: =COUNTIFS('Raw Data'!$V$2:$V$149,$B15,'Raw Data'!$U$2:$U$149,"SOLD") -> 4 | D15: =SUMIFS('Raw Data'!$O$2:$O$149,'Raw Data'!$V$2:$V$149,$B15,'Raw Data'!$U$2:$U$149,"SOLD") -> 50078 | E15: =SUMIFS('Raw Data'!$K$2:$K$149,'Raw Data'!$V$2:$V$149,$B15,'Raw Data'!$U$2:$U$149,"SOLD") -> 39426.34 | F15: =SUMIFS('Raw Data'!$P$2:$P$149,'Raw Data'!$V$2:$V$149,$B15,'Raw Data'!$U$2:$U$149,"SOLD") -> 6565 | G15: =IF(C15=0,"",F15/C15) -> 1641.25 | H15: =IFERROR(AVERAGEIFS('Raw Data'!$Q$2:$Q$149,'Raw Data'!$V$2:$V$149,$B15,'Raw Data'!$U$2:$U$149,"SOLD"),"") -> 0.201325 | I15: =IF(E15=0,"",F15/E15) -> 0.16651305
B16: Seat Arona | C16: =COUNTIFS('Raw Data'!$V$2:$V$149,$B16,'Raw Data'!$U$2:$U$149,"SOLD") -> 3 | D16: =SUMIFS('Raw Data'!$O$2:$O$149,'Raw Data'!$V$2:$V$149,$B16,'Raw Data'!$U$2:$U$149,"SOLD") -> 41200 | E16: =SUMIFS('Raw Data'!$K$2:$K$149,'Raw Data'!$V$2:$V$149,$B16,'Raw Data'!$U$2:$U$149,"SOLD") -> 34841.27 | F16: =SUMIFS('Raw Data'!$P$2:$P$149,'Raw Data'!$V$2:$V$149,$B16,'Raw Data'!$U$2:$U$149,"SOLD") -> 6358 | G16: =IF(C16=0,"",F16/C16) -> 2119.3333 | H16: =IFERROR(AVERAGEIFS('Raw Data'!$Q$2:$Q$149,'Raw Data'!$V$2:$V$149,$B16,'Raw Data'!$U$2:$U$149,"SOLD"),"") -> 0.1866 | I16: =IF(E16=0,"",F16/E16) -> 0.18248474
B17: Citroën Jumpy | C17: =COUNTIFS('Raw Data'!$V$2:$V$149,$B17,'Raw Data'!$U$2:$U$149,"SOLD") -> 3 | D17: =SUMIFS('Raw Data'!$O$2:$O$149,'Raw Data'!$V$2:$V$149,$B17,'Raw Data'!$U$2:$U$149,"SOLD") -> 43190 | E17: =SUMIFS('Raw Data'!$K$2:$K$149,'Raw Data'!$V$2:$V$149,$B17,'Raw Data'!$U$2:$U$149,"SOLD") -> 32639.93 | F17: =SUMIFS('Raw Data'!$P$2:$P$149,'Raw Data'!$V$2:$V$149,$B17,'Raw Data'!$U$2:$U$149,"SOLD") -> 5930 | G17: =IF(C17=0,"",F17/C17) -> 1976.6667 | H17: =IFERROR(AVERAGEIFS('Raw Data'!$Q$2:$Q$149,'Raw Data'!$V$2:$V$149,$B17,'Raw Data'!$U$2:$U$149,"SOLD"),"") -> 0.2106 | I17: =IF(E17=0,"",F17/E17) -> 0.18167931
... B46: Alfa Romeo Mito | C46: =COUNTIFS('Raw Data'!$V$2:$V$149,$B46,'Raw Data'!$U$2:$U$149,"SOLD") -> 1 | D46: =SUMIFS('Raw Data'!$O$2:$O$149,'Raw Data'!$V$2:$V$149,$B46,'Raw Data'!$U$2:$U$149,"SOLD") -> 1800 | E46: =SUMIFS('Raw Data'!$K$2:$K$149,'Raw Data'!$V$2:$V$149,$B46,'Raw Data'!$U$2:$U$149,"SOLD") -> 1798 | F46: =SUMIFS('Raw Data'!$P$2:$P$149,'Raw Data'!$V$2:$V$149,$B46,'Raw Data'!$U$2:$U$149,"SOLD") -> 2 | G46: =IF(C46=0,"",F46/C46) -> 2 | H46: =IFERROR(AVERAGEIFS('Raw Data'!$Q$2:$Q$149,'Raw Data'!$V$2:$V$149,$B46,'Raw Data'!$U$2:$U$149,"SOLD"),"") -> 0.0011 | I46: =IF(E46=0,"",F46/E46) -> 0.0011123471
B47: TOTAL / ALL SOLD | C47: =SUM(C6:C46) -> 129 | D47: =SUM(D6:D46) -> 1813360 | E47: =SUM(E6:E46) -> 1343522.3 | F47: =SUM(F6:F46) -> 217918.12 | G47: =F47/C47 -> 1689.2878 | H47: =AVERAGEIF('Raw Data'!$U$2:$U$149,"SOLD",'Raw Data'!$Q$2:$Q$149) -> 0.69859535 | I47: =F47/E47 -> 0.16219911
B50: Note: a few single-deal rows (BMW 420d, Audi A6 Avant, Kia Sportage, Nissan Navara) show very high "margin % of cost" (900%+). These are investor-consignment / commission-only deals where AUTOBONO never carried the full purchase cost, so "Costs" is a nominal figure (e.g. 50 €) rather than a real acquisition price. Their € profit is genuine but the % figure is not comparable to normal buy-resell deals.

Sheet By Month
B2: Sold deals by month (sale date)
B3: Covers the full running log from Apr 2023 through Jul 2026. All cells are live formulas against the Raw Data tab.
B5: Month | C5: Deals sold | D5: Total revenue (€) | E5: Total costs (€) | F5: Total profit (€) | G5: Weighted margin %
B6: 2023-04 | C6: =COUNTIF('Raw Data'!$Y$2:$Y$149,$B6) -> 1 | D6: =SUMIF('Raw Data'!$Y$2:$Y$149,$B6,'Raw Data'!$O$2:$O$149) -> 12800 | E6: =SUMIF('Raw Data'!$Y$2:$Y$149,$B6,'Raw Data'!$K$2:$K$149) -> 11103.79 | F6: =SUMIF('Raw Data'!$Y$2:$Y$149,$B6,'Raw Data'!$P$2:$P$149) -> 1696.21 | G6: =IF(E6=0,"",F6/E6) -> 0.15275955
B7: 2023-07 | C7: =COUNTIF('Raw Data'!$Y$2:$Y$149,$B7) -> 2 | D7: =SUMIF('Raw Data'!$Y$2:$Y$149,$B7,'Raw Data'!$O$2:$O$149) -> 28300 | E7: =SUMIF('Raw Data'!$Y$2:$Y$149,$B7,'Raw Data'!$K$2:$K$149) -> 25816.08 | F7: =SUMIF('Raw Data'!$Y$2:$Y$149,$B7,'Raw Data'!$P$2:$P$149) -> 2483.92 | G7: =IF(E7=0,"",F7/E7) -> 0.096216002
B8: 2023-10 | C8: =COUNTIF('Raw Data'!$Y$2:$Y$149,$B8) -> 2 | D8: =SUMIF('Raw Data'!$Y$2:$Y$149,$B8,'Raw Data'!$O$2:$O$149) -> 33050 | E8: =SUMIF('Raw Data'!$Y$2:$Y$149,$B8,'Raw Data'!$K$2:$K$149) -> 30163 | F8: =SUMIF('Raw Data'!$Y$2:$Y$149,$B8,'Raw Data'!$P$2:$P$149) -> 2887 | G8: =IF(E8=0,"",F8/E8) -> 0.095713291
B9: 2023-11 | C9: =COUNTIF('Raw Data'!$Y$2:$Y$149,$B9) -> 2 | D9: =SUMIF('Raw Data'!$Y$2:$Y$149,$B9,'Raw Data'!$O$2:$O$149) -> 26400 | E9: =SUMIF('Raw Data'!$Y$2:$Y$149,$B9,'Raw Data'!$K$2:$K$149) -> 22985.44 | F9: =SUMIF('Raw Data'!$Y$2:$Y$149,$B9,'Raw Data'!$P$2:$P$149) -> 2936.99 | G9: =IF(E9=0,"",F9/E9) -> 0.12777611
B10: 2023-12 | C10: =COUNTIF('Raw Data'!$Y$2:$Y$149,$B10) -> 1 | D10: =SUMIF('Raw Data'!$Y$2:$Y$149,$B10,'Raw Data'!$O$2:$O$149) -> 14850 | E10: =SUMIF('Raw Data'!$Y$2:$Y$149,$B10,'Raw Data'!$K$2:$K$149) -> 13622 | F10: =SUMIF('Raw Data'!$Y$2:$Y$149,$B10,'Raw Data'!$P$2:$P$149) -> 1228 | G10: =IF(E10=0,"",F10/E10) -> 0.09014829
B11: 2024-02 | C11: =COUNTIF('Raw Data'!$Y$2:$Y$149,$B11) -> 1 | D11: =SUMIF('Raw Data'!$Y$2:$Y$149,$B11,'Raw Data'!$O$2:$O$149) -> 14500 | E11: =SUMIF('Raw Data'!$Y$2:$Y$149,$B11,'Raw Data'!$K$2:$K$149) -> 12564.68 | F11: =SUMIF('Raw Data'!$Y$2:$Y$149,$B11,'Raw Data'!$P$2:$P$149) -> 1935 | G11: =IF(E11=0,"",F11/E11) -> 0.15400313
B12: 2024-03 | C12: =COUNTIF('Raw Data'!$Y$2:$Y$149,$B12) -> 1 | D12: =SUMIF('Raw Data'!$Y$2:$Y$149,$B12,'Raw Data'!$O$2:$O$149) -> 20500 | E12: =SUMIF('Raw Data'!$Y$2:$Y$149,$B12,'Raw Data'!$K$2:$K$149) -> 18000.19 | F12: =SUMIF('Raw Data'!$Y$2:$Y$149,$B12,'Raw Data'!$P$2:$P$149) -> 2500 | G12: =IF(E12=0,"",F12/E12) -> 0.13888742
B13: 2024-04 | C13: =COUNTIF('Raw Data'!$Y$2:$Y$149,$B13) -> 3 | D13: =SUMIF('Raw Data'!$Y$2:$Y$149,$B13,'Raw Data'!$O$2:$O$149) -> 46380 | E13: =SUMIF('Raw Data'!$Y$2:$Y$149,$B13,'Raw Data'!$K$2:$K$149) -> 41100.72 | F13: =SUMIF('Raw Data'!$Y$2:$Y$149,$B13,'Raw Data'!$P$2:$P$149) -> 2956 | G13: =IF(E13=0,"",F13/E13) -> 0.071920881
B14: 2024-05 | C14: =COUNTIF('Raw Data'!$Y$2:$Y$149,$B14) -> 2 | D14: =SUMIF('Raw Data'!$Y$2:$Y$149,$B14,'Raw Data'!$O$2:$O$149) -> 32600 | E14: =SUMIF('Raw Data'!$Y$2:$Y$149,$B14,'Raw Data'!$K$2:$K$149) -> 25834 | F14: =SUMIF('Raw Data'!$Y$2:$Y$149,$B14,'Raw Data'!$P$2:$P$149) -> 3649 | G14: =IF(E14=0,"",F14/E14) -> 0.14124797
B15: 2024-06 | C15: =COUNTIF('Raw Data'!$Y$2:$Y$149,$B15) -> 4 | D15: =SUMIF('Raw Data'!$Y$2:$Y$149,$B15,'Raw Data'!$O$2:$O$149) -> 48640 | E15: =SUMIF('Raw Data'!$Y$2:$Y$149,$B15,'Raw Data'!$K$2:$K$149) -> 39161.56 | F15: =SUMIF('Raw Data'!$Y$2:$Y$149,$B15,'Raw Data'!$P$2:$P$149) -> 3205 | G15: =IF(E15=0,"",F15/E15) -> 0.081840458
B16: 2024-07 | C16: =COUNTIF('Raw Data'!$Y$2:$Y$149,$B16) -> 1 | D16: =SUMIF('Raw Data'!$Y$2:$Y$149,$B16,'Raw Data'!$O$2:$O$149) -> 20800 | E16: =SUMIF('Raw Data'!$Y$2:$Y$149,$B16,'Raw Data'!$K$2:$K$149) -> 18813.42 | F16: =SUMIF('Raw Data'!$Y$2:$Y$149,$B16,'Raw Data'!$P$2:$P$149) -> 1987 | G16: =IF(E16=0,"",F16/E16) -> 0.1056161
B17: 2024-08 | C17: =COUNTIF('Raw Data'!$Y$2:$Y$149,$B17) -> 8 | D17: =SUMIF('Raw Data'!$Y$2:$Y$149,$B17,'Raw Data'!$O$2:$O$149) -> 115300 | E17: =SUMIF('Raw Data'!$Y$2:$Y$149,$B17,'Raw Data'!$K$2:$K$149) -> 90840.67 | F17: =SUMIF('Raw Data'!$Y$2:$Y$149,$B17,'Raw Data'!$P$2:$P$149) -> 20027 | G17: =IF(E17=0,"",F17/E17) -> 0.22046293
... B40: 2026-07 | C40: =COUNTIF('Raw Data'!$Y$2:$Y$149,$B40) -> 2 | D40: =SUMIF('Raw Data'!$Y$2:$Y$149,$B40,'Raw Data'!$O$2:$O$149) -> 43490 | E40: =SUMIF('Raw Data'!$Y$2:$Y$149,$B40,'Raw Data'!$K$2:$K$149) -> 11037.5 | F40: =SUMIF('Raw Data'!$Y$2:$Y$149,$B40,'Raw Data'!$P$2:$P$149) -> 2972 | G40: =IF(E40=0,"",F40/E40) -> 0.26926387
B41: TOTAL | C41: =SUM(C6:C40) -> 129 | D41: =SUM(D6:D40) -> 1813360 | E41: =SUM(E6:E40) -> 1343522.3 | F41: =SUM(F6:F40) -> 217918.12 | G41: =F41/E41 -> 0.16219911

Sheet By VAT Type
B2: Sold deals by VAT scheme
B3: M = margin scheme (VAT only on margin, no input VAT deduction). D = deductible/netto scheme (VAT reclaimed on purchase, charged on sale).
B5: VAT type | C5: Deals sold | D5: Total revenue (€) | E5: Total costs (€) | F5: Total profit (€) | G5: Weighted margin %
B6: M | C6: =COUNTIFS('Raw Data'!$I$2:$I$149,$B6,'Raw Data'!$U$2:$U$149,"SOLD") -> 86 | D6: =SUMIFS('Raw Data'!$O$2:$O$149,'Raw Data'!$I$2:$I$149,$B6,'Raw Data'!$U$2:$U$149,"SOLD") -> 1133258 | E6: =SUMIFS('Raw Data'!$K$2:$K$149,'Raw Data'!$I$2:$I$149,$B6,'Raw Data'!$U$2:$U$149,"SOLD") -> 900754.23 | F6: =SUMIFS('Raw Data'!$P$2:$P$149,'Raw Data'!$I$2:$I$149,$B6,'Raw Data'!$U$2:$U$149,"SOLD") -> 143917.01 | G6: =F6/E6 -> 0.15977389
B7: D | C7: =COUNTIFS('Raw Data'!$I$2:$I$149,$B7,'Raw Data'!$U$2:$U$149,"SOLD") -> 43 | D7: =SUMIFS('Raw Data'!$O$2:$O$149,'Raw Data'!$I$2:$I$149,$B7,'Raw Data'!$U$2:$U$149,"SOLD") -> 680102 | E7: =SUMIFS('Raw Data'!$K$2:$K$149,'Raw Data'!$I$2:$I$149,$B7,'Raw Data'!$U$2:$U$149,"SOLD") -> 442768.07 | F7: =SUMIFS('Raw Data'!$P$2:$P$149,'Raw Data'!$I$2:$I$149,$B7,'Raw Data'!$U$2:$U$149,"SOLD") -> 74001.11 | G7: =F7/E7 -> 0.1671329
B9: Note: per-deal average margin % (not shown here) is heavily skewed by a few near-zero-cost consignment deals. The weighted margin % above (total profit ÷ total cost) is the reliable comparison — and it shows M and D scheme deals perform almost identically (~16% each), i.e. VAT scheme itself is not driving profitability.

Sheet Raw Data
A1: No. | B1: Year (tab) | C1: Vehicle | D1: Trim | E1: Model year | F1: Engine | G1: Gearbox | H1: Mileage (km) | I1: VAT type (M=margin, D=deductible) | J1: Buyer country | K1: Costs (€) | L1: Netto (€) | M1: VAT (€) | N1: Brutto (€) | O1: Sale price (€) | P1: Profit (€) | Q1: Margin % of cost | R1: Purchase date | S1: Sale date | T1: Days listed→sold | U1: Status | V1: Model group | W1: Helper: profit if sold | X1: Helper: margin% if sold | Y1: Helper: sale year-month
A2: 1 | B2: 2023 | C2: Hyundai i40 CW | D2: Business | F2: 1.7 CRDi 104 kW | G2: DCT7 | H2: 159713 | I2: M | J2: 🇨🇿 | K2: 11103.79 | L2: 12800 | M2: 0 | N2: 12800 | O2: 12800 | P2: 1696.21 | Q2: 0.1528 | S2: 45034 | U2: SOLD | V2: Hyundai i40 | W2: =IF(U2="SOLD",P2,"") -> 1696.21 | X2: =IF(U2="SOLD",Q2,"") -> 0.1528 | Y2: =IF(U2="SOLD",TEXT(S2,"YYYY-MM"),"") -> 2023-04
A3: 2 | B3: 2023 | C3: Kia Cee'd SW | D3: Gold | E3: 08/2019 | F3: 1.6 CRDi 85 kW | G3: MT6 | H3: 118900 | I3: D | J3: 🇧🇪 | K3: 12942.29 | L3: 10650 | M3: 2130 | N3: 12780 | O3: 14350 | P3: 1407.71 | Q3: 0.1088 | S3: 45115 | U3: SOLD | V3: Kia Cee'd | W3: =IF(U3="SOLD",P3,"") -> 1407.71 | X3: =IF(U3="SOLD",Q3,"") -> 0.1088 | Y3: =IF(U3="SOLD",TEXT(S3,"YYYY-MM"),"") -> 2023-07
A4: 3 | B4: 2023 | C4: Škoda Superb Combi | D4: Style | E4: 04/2016 | F4: 2.0 TDI 110 kW | G4: DSG6 | H4: 194400 | I4: M | J4: 🇧🇪 | K4: 12955.84 | L4: 15400 | M4: 477.58 | N4: 15400 | O4: 15400 | P4: 1966.59 | Q4: 0.1518 | S4: 45236 | U4: SOLD | V4: Škoda Superb | W4: =IF(U4="SOLD",P4,"") -> 1966.59 | X4: =IF(U4="SOLD",Q4,"") -> 0.1518 | Y4: =IF(U4="SOLD",TEXT(S4,"YYYY-MM"),"") -> 2023-11
A5: 4 | B5: 2023 | C5: Mazda 6 | D5: Revolution | E5: 05/2013 | F5: 2.5 Skyactiv-G192 | G5: AT6 | H5: 146187 | I5: M | J5: 🇩🇪 | K5: 12873.79 | L5: 11700 | M5: 30.43 | N5: 11700 | O5: 13950 | P5: 1076.21 | Q5: 0.0836 | S5: 45120 | U5: SOLD | V5: Mazda 6 | W5: =IF(U5="SOLD",P5,"") -> 1076.21 | X5: =IF(U5="SOLD",Q5,"") -> 0.0836 | Y5: =IF(U5="SOLD",TEXT(S5,"YYYY-MM"),"") -> 2023-07
A6: 5 | B6: 2023 | C6: Škoda Kodiaq | D6: Ambition | E6: 10/2017 | F6: 1.4 TSI 92 kW | G6: MT6 | H6: 178383 | I6: D | J6: 🇳🇱 | K6: 15569 | L6: 12850 | M6: 2570 | N6: 15420 | O6: 17000 | P6: 1431 | Q6: 0.0919 | S6: 45215 | U6: SOLD | V6: Škoda Kodiaq | W6: =IF(U6="SOLD",P6,"") -> 1431 | X6: =IF(U6="SOLD",Q6,"") -> 0.0919 | Y6: =IF(U6="SOLD",TEXT(S6,"YYYY-MM"),"") -> 2023-10
A7: 6 | B7: 2023 | C7: VW Touran | D7: Highline | E7: 08/2019 | F7: 2.0 TDI 110 kW | G7: DSG7 | H7: 188761 | I7: D | J7: 🇩🇪 | K7: 14594 | L7: 12000 | M7: 2400 | N7: 14400 | O7: 16050 | P7: 1456 | Q7: 0.0998 | S7: 45209 | U7: SOLD | V7: VW Touran | W7: =IF(U7="SOLD",P7,"") -> 1456 | X7: =IF(U7="SOLD",Q7,"") -> 0.0998 | Y7: =IF(U7="SOLD",TEXT(S7,"YYYY-MM"),"") -> 2023-10
A8: 7 | B8: 2023 | C8: Audi A4 Avant | D8: Basis | E8: 07/2018 | F8: 2.0 TDI 110 kW | G8: DSG7 | H8: 177534 | I8: D | J8: 🇮🇹 | K8: 12945 | L8: 0 | M8: 0 | N8: 0 | U8: STOCK | V8: Audi A4 | W8: =IF(U8="SOLD",P8,"") | X8: =IF(U8="SOLD",Q8,"") | Y8: =IF(U8="SOLD",TEXT(S8,"YYYY-MM"),"")
A9: 8 | B9: 2023 | C9: Škoda Octavia Combi | D9: Ambition | E9: 03/2018 | F9: 1.0 TSI 85 kW | G9: DSG7 | H9: 188436 | I9: D | J9: 🇳🇱 | K9: 10029.6 | L9: 8200 | M9: 1640 | N9: 9840 | O9: 11000 | P9: 970.4 | Q9: 0.0968 | S9: 45238 | U9: SOLD | V9: Škoda Octavia | W9: =IF(U9="SOLD",P9,"") -> 970.4 | X9: =IF(U9="SOLD",Q9,"") -> 0.0968 | Y9: =IF(U9="SOLD",TEXT(S9,"YYYY-MM"),"") -> 2023-11
A10: 9 | B10: 2023 | C10: Volkswagen Passat | D10: Comfortline | E10: 02/2017 | F10: 2.0 TDI 110 kW | G10: DSG6 | H10: 185900 | I10: D | J10: 🇸🇰 | K10: 13622 | L10: 12375 | M10: 2475 | N10: 14850 | O10: 14850 | P10: 1228 | Q10: 0.0901 | S10: 45289 | U10: SOLD | V10: VW Passat | W10: =IF(U10="SOLD",P10,"") -> 1228 | X10: =IF(U10="SOLD",Q10,"") -> 0.0901 | Y10: =IF(U10="SOLD",TEXT(S10,"YYYY-MM"),"") -> 2023-12
A11: 10 | B11: 2024 | C11: VW Passat Variant R-line | D11: Highline Business | E11: 09/2015 | F11: 1.8 TSI 132 kW | G11: DSG7 | H11: 187200 | I11: D | J11: 🇳🇱 | K11: 12362.56 | L11: 10333.33 | M11: 2066.67 | N11: 12400 | O11: 12900 | P11: -1529 | Q11: -0.1237 | R11: 45232 | S11: 45449 | T11: 196 | U11: SOLD | V11: VW Passat | W11: =IF(U11="SOLD",P11,"") -> -1529 | X11: =IF(U11="SOLD",Q11,"") -> -0.1237 | Y11: =IF(U11="SOLD",TEXT(S11,"YYYY-MM"),"") -> 2024-06
A12: 11 | B12: 2024 | C12: VW Touran R-line | D12: Highline | E12: 01/2018 | F12: 1.8 TSI 132 kW | G12: DSG7 | H12: 151400 | I12: M | J12: 🇳🇱 | K12: 17778.05 | L12: 1210.44 | M12: 242.09 | N12: 1453 | O12: 18390 | P12: 612 | Q12: 0.0344 | R12: 45236 | S12: 45400 | T12: 141 | U12: SOLD | V12: VW Touran | W12: =IF(U12="SOLD",P12,"") -> 612 | X12: =IF(U12="SOLD",Q12,"") -> 0.0344 | Y12: =IF(U12="SOLD",TEXT(S12,"YYYY-MM"),"") -> 2024-04
A13: 12 | B13: 2024 | C13: Škoda Kodiaq | D13: Style | E13: 06/2017 | F13: 1.4 TSI 110 kW | G13: DSG6 | H13: 154100 | I13: M | J13: 🇫🇷 | K13: 18000.19 | L13: 15000 | M13: 0 | N13: 15000 | O13: 20500 | P13: 2500 | Q13: 0.1389 | R13: 45233 | S13: 45380 | T13: 23 | U13: SOLD | V13: Škoda Kodiaq | W13: =IF(U13="SOLD",P13,"") -> 2500 | X13: =IF(U13="SOLD",Q13,"") -> 0.1389 | Y13: =IF(U13="SOLD",TEXT(S13,"YYYY-MM"),"") -> 2024-03
A14: 13 | B14: 2024 | C14: Seat Ateca | D14: Style | E14: 02/2020 | F14: 1.0 TSI 85 kW | G14: MT6 | H14: 176499 | I14: D | J14: 🇳🇱 | K14: 13424 | L14: 11250 | M14: 2250 | N14: 13500 | O14: 13990 | P14: 576 | Q14: 0.0429 | R14: 45243 | S14: 45386 | T14: 78 | U14: SOLD | V14: Seat Ateca | W14: =IF(U14="SOLD",P14,"") -> 576 | X14: =IF(U14="SOLD",Q14,"") -> 0.0429 | Y14: =IF(U14="SOLD",TEXT(S14,"YYYY-MM"),"") -> 2024-04
A15: 15 | B15: 2024 | C15: Seat Arona | D15: Style | E15: 02/2019 | F15: 1.6 TDI 70 kW | G15: MT6 | H15: 67396 | I15: M | J15: 🇧🇪 | K15: 12564.68 | L15: 1165 | M15: 233 | N15: 1398 | O15: 14500 | P15: 1935 | Q15: 0.154 | R15: 45251 | S15: 45339 | T15: 38 | U15: SOLD | V15: Seat Arona | W15: =IF(U15="SOLD",P15,"") -> 1935 | X15: =IF(U15="SOLD",Q15,"") -> 0.154 | Y15: =IF(U15="SOLD",TEXT(S15,"YYYY-MM"),"") -> 2024-02
A16: 16 | B16: 2024 | C16: Audi A4 Avant | D16: Basis | E16: 01/2016 | F16: 2.0 TDI 110 kW | G16: DSG7 | H16: 211000 | I16: D | J16: 🇩🇰 | K16: 9898.67 | L16: 9825 | M16: 1965 | N16: 11790 | O16: 14000 | P16: 1768 | Q16: 0.1786 | R16: 45352 | S16: 45384 | T16: 8 | U16: SOLD | V16: Audi A4 | W16: =IF(U16="SOLD",P16,"") -> 1768 | X16: =IF(U16="SOLD",Q16,"") -> 0.1786 | Y16: =IF(U16="SOLD",TEXT(S16,"YYYY-MM"),"") -> 2024-04
A17: 17 | B17: 2024 | C17: Volvo V60 | D17: Cross Country | E17: 10/2017 | F17: 2.0 D4 140 kW | G17: AT8 | H17: 196000 | I17: M | J17: 🇩🇪 | K17: 13305 | L17: 297.5 | M17: 59.5 | N17: 357 | O17: 13900 | P17: 595 | Q17: 0.0447 | R17: 45380 | S17: 45418 | T17: 26 | U17: SOLD | V17: Volvo V60 | W17: =IF(U17="SOLD",P17,"") -> 595 | X17: =IF(U17="SOLD",Q17,"") -> 0.0447 | Y17: =IF(U17="SOLD",TEXT(S17,"YYYY-MM"),"") -> 2024-05
A18: 18 | B18: 2024 | C18: Mercedes-Benz C 220d T-Modell | D18: Business Plus | E18: 10/2017 | F18: 2.2d 125 kW | G18: AT9 | H18: 212000 | I18: D | J18: 🇩🇰 | K18: 11629 | L18: 10833.33 | M18: 2166.67 | N18: 13000 | O18: 14900 | P18: 788 | Q18: 0.0678 | R18: 45394 | S18: 45537 | T18: 125 | U18: SOLD | V18: Mercedes-Benz C | W18: =IF(U18="SOLD",P18,"") -> 788 | X18: =IF(U18="SOLD",Q18,"") -> 0.0678 | Y18: =IF(U18="SOLD",TEXT(S18,"YYYY-MM"),"") -> 2024-09
A19: 19 | B19: 2024 | C19: Škoda Octavia Combi | D19: Style | E19: 11/2018 | F19: 1.0 TSI 85 kW | G19: MT6 | H19: 201000 | I19: D | J19: 🇳🇱 | K19: 8067 | L19: 6475 | M19: 1295 | N19: 7770 | O19: 10500 | P19: 2433 | Q19: 0.3016 | R19: 45412 | S19: 45451 | T19: 18 | U19: SOLD | V19: Škoda Octavia | W19: =IF(U19="SOLD",P19,"") -> 2433 | X19: =IF(U19="SOLD",Q19,"") -> 0.3016 | Y19: =IF(U19="SOLD",TEXT(S19,"YYYY-MM"),"") -> 2024-06
A20: 20 | B20: 2024 | C20: Škoda Octavia Combi | D20: Style | E20: 03/2020 | F20: 2.0 TDI 110 kW | G20: DSG7 | H20: 193000 | I20: D | J20: 🇩🇰 | K20: 10345 | L20: 12075 | M20: 2415 | N20: 14490 | O20: 14490 | P20: 1730 | Q20: 0.1672 | R20: 45415 | S20: 45471 | T20: 44 | U20: SOLD | V20: Škoda Octavia | W20: =IF(U20="SOLD",P20,"") -> 1730 | X20: =IF(U20="SOLD",Q20,"") -> 0.1672 | Y20: =IF(U20="SOLD",TEXT(S20,"YYYY-MM"),"") -> 2024-06
A21: 21 | B21: 2024 | C21: Audi A4 Avant | D21: S-line | E21: 03/2016 | F21: 2.0 TDI 140 kW | G21: DSG7 | H21: 160000 | I21: D | J21: 🇩🇰 | K21: 12529 | L21: 15583.33 | M21: 3116.67 | N21: 18700 | O21: 18700 | P21: 3054 | Q21: 0.2438 | R21: 45422 | S21: 45443 | T21: 3 | U21: SOLD | V21: Audi A4 | W21: =IF(U21="SOLD",P21,"") -> 3054 | X21: =IF(U21="SOLD",Q21,"") -> 0.2438 | Y21: =IF(U21="SOLD",TEXT(S21,"YYYY-MM"),"") -> 2024-05
A22: 22 | B22: 2024 | C22: Audi Q5 quattro | D22: Basis | E22: 09/2011 | F22: 3.0 TDI 176 kW 4x4 | G22: DSG7 | H22: 182000 | I22: D | J22: 🇮🇹 | K22: 9024 | L22: 10916.67 | M22: 2183.33 | N22: 13100 | O22: 13100 | P22: 1893 | Q22: 0.2098 | R22: 45444 | S22: 45508 | T22: 26 | U22: SOLD | V22: Audi Q5 | W22: =IF(U22="SOLD",P22,"") -> 1893 | X22: =IF(U22="SOLD",Q22,"") -> 0.2098 | Y22: =IF(U22="SOLD",TEXT(S22,"YYYY-MM"),"") -> 2024-08
... A45: 45 | B45: 2024 | C45: Seat Ateca | D45: Style | E45: 09/2017 | F45: 2.0 TDI 110 kW | G45: MT6 4x4 | H45: 163600 | I45: M | J45: 🇩🇪 | K45: 14120.83 | L45: 16346.17 | M45: 653.83 | N45: 17000 | O45: 17000 | P45: 2879 | Q45: 0.2039 | R45: 45566 | S45: 45619 | T45: 16 | U45: SOLD | V45: Seat Ateca | W45: =IF(U45="SOLD",P45,"") -> 2879 | X45: =IF(U45="SOLD",Q45,"") -> 0.2039 | Y45: =IF(U45="SOLD",TEXT(S45,"YYYY-MM"),"") -> 2024-11
A46: 46 | B46: 2024 | C46: Alfa Romeo Giulietta | D46: Distinctive | E46: 08/2010 | F46: 1.4 TB 125 kW | G46: MT6 | H46: 169700 | I46: M | J46: 🇦🇹 | K46: 4975 | O46: 6650 | P46: 1675 | Q46: 0.3367 | R46: 45572 | S46: 45610 | T46: 35 | U46: SOLD | V46: Alfa Romeo Giulietta | W46: =IF(U46="SOLD",P46,"") -> 1675 | X46: =IF(U46="SOLD",Q46,"") -> 0.3367 | Y46: =IF(U46="SOLD",TEXT(S46,"YYYY-MM"),"") -> 2024-11
A47: 47 | B47: 2024 | C47: Škoda Octavia Combi | D47: Style | E47: 12/2017 | F47: 2.0 TDI 110 kW | G47: MT6 | H47: 188600 | I47: M | J47: 🇦🇹 | K47: 11332.67 | L47: 12344.33 | M47: 555.67 | N47: 12900 | O47: 13100 | P47: 1767 | Q47: 0.1559 | R47: 45582 | S47: 45620 | T47: 7 | U47: SOLD | V47: Škoda Octavia | W47: =IF(U47="SOLD",P47,"") -> 1767 | X47: =IF(U47="SOLD",Q47,"") -> 0.1559 | Y47: =IF(U47="SOLD",TEXT(S47,"YYYY-MM"),"") -> 2024-11
A48: 48 | B48: 2024 | C48: Audi A4 Avant | D48: Design | E48: 12/2016 | F48: 2.0 TDI | G48: DSG7 | H48: 185800 | I48: M | J48: 🇧🇪 | K48: 12498.33 | L48: 14229.67 | M48: 520.33 | N48: 14750 | O48: 14750 | P48: 2252 | Q48: 0.1802 | R48: 45597 | S48: 45634 | T48: 5 | U48: SOLD | V48: Audi A4 | W48: =IF(U48="SOLD",P48,"") -> 2252 | X48: =IF(U48="SOLD",Q48,"") -> 0.1802 | Y48: =IF(U48="SOLD",TEXT(S48,"YYYY-MM"),"") -> 2024-12
A49: 49 | B49: 2024 | C49: Škoda Octavia Combi | D49: Ambition | E49: 01/2018 | F49: 1.4 TSI 110 kW | G49: MT6 | H49: 185200 | I49: M | J49: 🇧🇪 | K49: 9410 | L49: 9043 | M49: 57 | N49: 9100 | O49: 12000 | P49: 2590 | Q49: 0.2752 | R49: 45600 | S49: 45649 | T49: 6 | U49: SOLD | V49: Škoda Octavia | W49: =IF(U49="SOLD",P49,"") -> 2590 | X49: =IF(U49="SOLD",Q49,"") -> 0.2752 | Y49: =IF(U49="SOLD",TEXT(S49,"YYYY-MM"),"") -> 2024-12
A50: 50 | B50: 2024 | C50: Citroën Jumpy | D50: L2H1 | E50: 11/2017 | F50: 2.0 HDI 130 kW | G50: AT6 | H50: 166200 | I50: D | J50: 🇩🇰 | K50: 9640 | L50: 11491.67 | M50: 2578.62 | N50: 13790 | O50: 13990 | P50: 1852 | Q50: 0.1921 | R50: 45611 | S50: 45701 | T50: 67 | U50: SOLD | V50: Citroën Jumpy | W50: =IF(U50="SOLD",P50,"") -> 1852 | X50: =IF(U50="SOLD",Q50,"") -> 0.1921 | Y50: =IF(U50="SOLD",TEXT(S50,"YYYY-MM"),"") -> 2025-02
A51: 51 | B51: 2024 | C51: VW Tiguan 4Motion | D51: Sport & Style | E51: 11/2011 | F51: 1.4 TSI 118 kW | G51: MT6 4x4 | H51: 186200 | I51: M | J51: 🇸🇪 | K51: 6907.5 | M51: 70.5 | N51: 6750 | O51: 8850 | P51: 1943 | Q51: 0.2813 | R51: 45616 | S51: 45756 | T51: 110 | U51: SOLD | V51: VW Tiguan | W51: =IF(U51="SOLD",P51,"") -> 1943 | X51: =IF(U51="SOLD",Q51,"") -> 0.2813 | Y51: =IF(U51="SOLD",TEXT(S51,"YYYY-MM"),"") -> 2025-04
A52: 52 | B52: 2024 | C52: VW Touran | D52: Comfortline | E52: 11/2010 | F52: 1.6 TDI | G52: MT6 | H52: 139800 | I52: M | J52: 🇩🇪 | K52: 9084.59 | L52: 8450 | M52: 50 | N52: 8500 | O52: 9800 | P52: 715 | Q52: 0.0787 | R52: 45616 | S52: 45638 | T52: 22 | U52: SOLD | V52: VW Touran | W52: =IF(U52="SOLD",P52,"") -> 715 | X52: =IF(U52="SOLD",Q52,"") -> 0.0787 | Y52: =IF(U52="SOLD",TEXT(S52,"YYYY-MM"),"") -> 2024-12
A53: 53 | B53: 2024 | C53: VW Golf Variant | D53: Comfortline | E53: 11/2018 | F53: 1.0 TSI | G53: MT6 | H53: 181500 | I53: D | J53: 🇳🇱 | K53: 7515.33 | L53: 5916.67 | M53: 1183.33 | N53: 7100 | O53: 9500 | P53: 1985 | Q53: 0.2641 | R53: 45624 | S53: 45674 | T53: 32 | U53: SOLD | V53: VW Golf | W53: =IF(U53="SOLD",P53,"") -> 1985 | X53: =IF(U53="SOLD",Q53,"") -> 0.2641 | Y53: =IF(U53="SOLD",TEXT(S53,"YYYY-MM"),"") -> 2025-01
A54: 54 | B54: 2024 | C54: Renault Espace | D54: Zen | E54: 01/2021 | F54: 2.0 dCi 118 kW | G54: EDC6 | H54: 191300 | I54: D | J54: 🇫🇷 | K54: 11099 | L54: 14416.67 | M54: 2883.33 | N54: 17300 | O54: 17300 | P54: 3318 | Q54: 0.2989 | R54: 45628 | S54: 45657 | T54: 15 | U54: SOLD | V54: Renault Espace | W54: =IF(U54="SOLD",P54,"") -> 3318 | X54: =IF(U54="SOLD",Q54,"") -> 0.2989 | Y54: =IF(U54="SOLD",TEXT(S54,"YYYY-MM"),"") -> 2024-12
A55: 55 | B55: 2024 | C55: Škoda Superb Combi | D55: Style | E55: 09/2016 | F55: 1.6 TDI 88 kW | G55: MT6 | H55: 157400 | I55: M | J55: 🇧🇪 | K55: 11585.54 | L55: 12358.46 | M55: 331.54 | N55: 12690 | O55: 12690 | P55: 1104 | Q55: 0.0953 | R55: 45629 | S55: 45849 | T55: 201 | U55: SOLD | V55: Škoda Superb | W55: =IF(U55="SOLD",P55,"") -> 1104 | X55: =IF(U55="SOLD",Q55,"") -> 0.0953 | Y55: =IF(U55="SOLD",TEXT(S55,"YYYY-MM"),"") -> 2025-07
A56: 56 | B56: 2024 | C56: VW Golf Variant | D56: Comfortline | E56: 05/2018 | F56: 2.0 TDI | G56: MT6 | H56: 168000 | I56: M | J56: 🇩🇪 | K56: 9849.59 | L56: 12121.41 | M56: 678.59 | N56: 12800 | O56: 12800 | P56: 2950 | Q56: 0.2995 | R56: 45636 | S56: 45716 | T56: 2 | U56: SOLD | V56: VW Golf | W56: =IF(U56="SOLD",P56,"") -> 2950 | X56: =IF(U56="SOLD",Q56,"") -> 0.2995 | Y56: =IF(U56="SOLD",TEXT(S56,"YYYY-MM"),"") -> 2025-02
A57: 57 | B57: 2024 | C57: Seat Ateca | D57: Style | E57: 10/2016 | F57: 1.6 TDI 85 kW | G57: MT6 | H57: 182200 | I57: M | J57: 🇫🇷 | K57: 11360.24 | L57: 11521.76 | M57: 278.24 | N57: 11800 | O57: 12150 | P57: 790 | Q57: 0.0695 | R57: 45638 | S57: 45806 | T57: 127 | U57: SOLD | V57: Seat Ateca | W57: =IF(U57="SOLD",P57,"") -> 790 | X57: =IF(U57="SOLD",Q57,"") -> 0.0695 | Y57: =IF(U57="SOLD",TEXT(S57,"YYYY-MM"),"") -> 2025-05
A58: 58 | B58: 2024 | C58: Audi A4 Avant | D58: Sport | E58: 07/2017 | F58: 2.0 TDI 140 kW | G58: DSG7 | H58: 196170 | I58: M | J58: 🇩🇪 | K58: 12846.5 | L58: 15186.5 | M58: 803.5 | N58: 15990 | O58: 15990 | P58: 3143 | Q58: 0.2447 | R58: 45641 | S58: 45690 | T58: 19 | U58: SOLD | V58: Audi A4 | W58: =IF(U58="SOLD",P58,"") -> 3143 | X58: =IF(U58="SOLD",Q58,"") -> 0.2447 | Y58: =IF(U58="SOLD",TEXT(S58,"YYYY-MM"),"") -> 2025-02
A59: 59 | B59: 2024 | C59: Škoda Kodiaq | D59: Style | E59: 12/2016 | F59: 2.0 TDI 140 kW | G59: DSG7 4x4 | H59: 221950 | I59: M | J59: 🇨🇿 | K59: 90 | O59: 18800 | P59: 700 | Q59: 7.7778 | R59: 45643 | S59: 45688 | T59: 42 | U59: SOLD | V59: Škoda Kodiaq | W59: =IF(U59="SOLD",P59,"") -> 700 | X59: =IF(U59="SOLD",Q59,"") -> 7.7778 | Y59: =IF(U59="SOLD",TEXT(S59,"YYYY-MM"),"") -> 2025-01
A60: 60 | B60: 2024 | C60: Audi A4 Avant | D60: Basis | E60: 05/2016 | F60: 2.0 TDI 140 kW | G60: DSG7 | H60: 196700 | I60: M | J60: 🇧🇪 | K60: 12236.75 | L60: 13585.25 | M60: 414.75 | N60: 14000 | O60: 14000 | P60: 1763 | Q60: 0.1441 | R60: 45653 | S60: 45773 | T60: 86 | U60: SOLD | V60: Audi A4 | W60: =IF(U60="SOLD",P60,"") -> 1763 | X60: =IF(U60="SOLD",Q60,"") -> 0.1441 | Y60: =IF(U60="SOLD",TEXT(S60,"YYYY-MM"),"") -> 2025-04
A61: 61 | B61: 2024 | C61: Seat Ateca | D61: Style | E61: 03/2017 | F61: 1.4 TSI 110 kW | G61: MT6 | H61: 191400 | I61: M | J61: 🇩🇪 | K61: 11746.65 | L61: 13623.35 | M61: 726.65 | N61: 14350 | O61: 14350 | P61: 2603 | Q61: 0.2216 | R61: 45653 | S61: 45751 | T61: 72 | U61: SOLD | V61: Seat Ateca | W61: =IF(U61="SOLD",P61,"") -> 2603 | X61: =IF(U61="SOLD",Q61,"") -> 0.2216 | Y61: =IF(U61="SOLD",TEXT(S61,"YYYY-MM"),"") -> 2025-04
A62: 62 | B62: 2024 | C62: Škoda Octavia Combi | D62: Ambition | E62: 03/2018 | F62: 1.0 TSI 85 kW | G62: MT6 | H62: 201400 | I62: M | J62: 🇩🇪 | K62: 7322.09 | L62: 8210.91 | M62: 289.09 | N62: 8500 | O62: 8500 | P62: 1178 | Q62: 0.1609 | R62: 45653 | S62: 45777 | T62: 93 | U62: SOLD | V62: Škoda Octavia | W62: =IF(U62="SOLD",P62,"") -> 1178 | X62: =IF(U62="SOLD",Q62,"") -> 0.1609 | Y62: =IF(U62="SOLD",TEXT(S62,"YYYY-MM"),"") -> 2025-04
A63: 63 | B63: 2024 | C63: Seat Leon ST | D63: Style | E63: 08/2015 | F63: 2.0 TDI 110 kW | G63: MT6 | H63: 198300 | I63: M | J63: 🇩🇪 | K63: 8776.34 | L63: 9900.66 | M63: 449.34 | N63: 10350 | O63: 10350 | P63: 1574 | Q63: 0.1793 | R63: 45653 | S63: 45746 | T63: 67 | U63: SOLD | V63: Seat Leon | W63: =IF(U63="SOLD",P63,"") -> 1574 | X63: =IF(U63="SOLD",Q63,"") -> 0.1793 | Y63: =IF(U63="SOLD",TEXT(S63,"YYYY-MM"),"") -> 2025-03
A64: 64 | B64: 2024 | C64: Alfa Romeo Mito | D64: Distinctive | E64: 06/2009 | F64: 1.4 T-Jet 114 kW | G64: MT6 | H64: 213940 | I64: M | J64: 🇮🇹 | K64: 1798 | L64: 1799.63 | M64: 0.37 | N64: 1800 | O64: 1800 | P64: 2 | Q64: 0.0011 | R64: 45655 | S64: 45655 | T64: 0 | U64: SOLD | V64: Alfa Romeo Mito | W64: =IF(U64="SOLD",P64,"") -> 2 | X64: =IF(U64="SOLD",Q64,"") -> 0.0011 | Y64: =IF(U64="SOLD",TEXT(S64,"YYYY-MM"),"") -> 2024-12
A65: 65 | B65: 2024 | C65: VW Tiguan | D65: Trend & Fun | E65: 12/2013 | F65: 2.0 TDI 103 kW | G65: MT6 | H65: 180200 | I65: M | J65: 🇩🇪 | K65: 7404.88 | L65: 7709.12 | M65: 90.88 | N65: 7800 | O65: 9700 | P65: 1900 | Q65: 0.2566 | R65: 45655 | S65: 45675 | T65: 1 | U65: SOLD | V65: VW Tiguan | W65: =IF(U65="SOLD",P65,"") -> 1900 | X65: =IF(U65="SOLD",Q65,"") -> 0.2566 | Y65: =IF(U65="SOLD",TEXT(S65,"YYYY-MM"),"") -> 2025-01
A66: 66 | B66: 2024 | C66: Audi Q5 quattro | D66: Basis | E66: 07/2009 | F66: 3.0 TDI 176 kW | G66: DSG7 4x4 | H66: 183500 | I66: M | J66: 🇩🇪 | K66: 9560 | L66: 9425.33 | M66: 74.67 | N66: 9500 | O66: 11000 | P66: 1440 | Q66: 0.1506 | R66: 45657 | S66: 45793 | T66: 116 | U66: SOLD | V66: Audi Q5 | W66: =IF(U66="SOLD",P66,"") -> 1440 | X66: =IF(U66="SOLD",Q66,"") -> 0.1506 | Y66: =IF(U66="SOLD",TEXT(S66,"YYYY-MM"),"") -> 2025-05
A67: 67 | B67: 2024 | C67: Mazda MX-5 | D67: Revolution | E67: 05/2016 | F67: 2.0 Skyactiv-G 118 kW | G67: MT6 | H67: 185700 | I67: D | J67: 🇩🇪 | K67: 11145.56 | L67: 10731.71 | M67: 2468.29 | N67: 13200 | O67: 13200 | P67: 2886 | Q67: 0.2589 | R67: 45664 | S67: 46177 | T67: 3 | U67: SOLD | V67: Mazda MX-5 | W67: =IF(U67="SOLD",P67,"") -> 2886 | X67: =IF(U67="SOLD",Q67,"") -> 0.2589 | Y67: =IF(U67="SOLD",TEXT(S67,"YYYY-MM"),"") -> 2026-06
A68: 68 | B68: 2024 | C68: Mercedes-Benz E53 AMG | D68: AMG | E68: 02/2023 | F68: 3.0i 320 kW | G68: AT9 4Matic+ | H68: 7860 | I68: D | J68: 🇩🇪 | K68: 1708.42 | L68: 3764.23 | M68: 865.77 | N68: 4630 | O68: 72390 | P68: 2056 | Q68: 1.2035 | R68: 45677 | S68: 45693 | T68: 1 | U68: SOLD | V68: Mercedes-Benz E53 | W68: =IF(U68="SOLD",P68,"") -> 2056 | X68: =IF(U68="SOLD",Q68,"") -> 1.2035 | Y68: =IF(U68="SOLD",TEXT(S68,"YYYY-MM"),"") -> 2025-02
A69: 69 | B69: 2024 | C69: VW Golf Variant | D69: Comfortline | E69: 09/2016 | F69: 2.0 TDI 110 kW | G69: MT6 | H69: 197900 | I69: M | J69: 🇩🇪 | K69: 9156.5 | L69: 9032.5 | M69: 67.5 | N69: 9100 | O69: 10850 | P69: 1693 | Q69: 0.1849 | R69: 45681 | S69: 45748 | T69: 46 | U69: SOLD | V69: VW Golf | W69: =IF(U69="SOLD",P69,"") -> 1693 | X69: =IF(U69="SOLD",Q69,"") -> 0.1849 | Y69: =IF(U69="SOLD",TEXT(S69,"YYYY-MM"),"") -> 2025-04
A70: 70 | B70: 2024 | C70: Škoda Octavia Combi | D70: Ambition | E70: 11/2019 | F70: 1.5 TSI 110 kW | G70: MT6 | H70: 187900 | I70: D | J70: 🇳🇱 | K70: 7835 | L70: 9959.35 | M70: 2290.65 | N70: 12250 | O70: 12250 | P70: 2124 | Q70: 0.2711 | R70: 45681 | S70: 45746 | T70: 40 | U70: SOLD | V70: Škoda Octavia | W70: =IF(U70="SOLD",P70,"") -> 2124 | X70: =IF(U70="SOLD",Q70,"") -> 0.2711 | Y70: =IF(U70="SOLD",TEXT(S70,"YYYY-MM"),"") -> 2025-03
A71: 71 | B71: 2024 | C71: Škoda Karoq | D71: Style | E71: 09/2020 | F71: 1.5 TSI 110 kW | G71: MT6 | H71: 171000 | I71: D | J71: 🇩🇰 | K71: 11747 | L71: 12195.12 | M71: 2804.88 | N71: 15000 | O71: 17300 | P71: 2748 | Q71: 0.2339 | R71: 45684 | S71: 45709 | T71: 7 | U71: SOLD | V71: Škoda Karoq | W71: =IF(U71="SOLD",P71,"") -> 2748 | X71: =IF(U71="SOLD",Q71,"") -> 0.2339 | Y71: =IF(U71="SOLD",TEXT(S71,"YYYY-MM"),"") -> 2025-02
A72: 72 | B72: 2024 | C72: Opel Vivaro | D72: L2H1 | E72: 08/2020 | F72: 2.0 HDI 90 kW | G72: MT6 | H72: 136400 | I72: D | J72: 🇮🇹 | K72: 8739 | L72: 0 | M72: 0 | N72: 0 | R72: 45698 | U72: STOCK | V72: Opel Vivaro | W72: =IF(U72="SOLD",P72,"") | X72: =IF(U72="SOLD",Q72,"") | Y72: =IF(U72="SOLD",TEXT(S72,"YYYY-MM"),"")
A73: 73 | B73: 2024 | C73: Volvo V90 | D73: Inscription | E73: 12/2017 | F73: 2.0 D5 173 kW AWD | G73: AT8 | H73: 166500 | I73: M | J73: 🇫🇷 | K73: 20190.81 | L73: 20678.19 | M73: 321.81 | N73: 21000 | O73: 21550 | P73: 1359 | Q73: 0.0673 | R73: 45705 | S73: 45919 | T73: 195 | U73: SOLD | V73: Volvo V90 | W73: =IF(U73="SOLD",P73,"") -> 1359 | X73: =IF(U73="SOLD",Q73,"") -> 0.0673 | Y73: =IF(U73="SOLD",TEXT(S73,"YYYY-MM"),"") -> 2025-09
A74: 74 | B74: 2024 | C74: BMW 530i xDrive Touring | D74: M Sport | E74: 09/2019 | F74: 2.0i 185 kW xDrive | G74: AT8 | H74: 182000 | I74: M | J74: 🇩🇪 | K74: 24341.45 | L74: 23300 | M74: 0 | N74: 23300 | O74: 25500 | P74: 1000 | Q74: 0.0411 | R74: 45706 | S74: 45707 | T74: 0 | U74: SOLD | V74: BMW 530i | W74: =IF(U74="SOLD",P74,"") -> 1000 | X74: =IF(U74="SOLD",Q74,"") -> 0.0411 | Y74: =IF(U74="SOLD",TEXT(S74,"YYYY-MM"),"") -> 2025-02
A75: 75 | B75: 2024 | C75: Citroën Jumpy | D75: L2H1 | E75: 09/2020 | F75: 2.0 HDI 90 kW | G75: MT6 | H75: 73300 | I75: D | J75: 🇩🇰 | K75: 16047.93 | L75: 14512.2 | M75: 3337.8 | N75: 17500 | O75: 17850 | P75: 1802 | Q75: 0.1123 | R75: 45708 | S75: 45851 | T75: 129 | U75: SOLD | V75: Citroën Jumpy | W75: =IF(U75="SOLD",P75,"") -> 1802 | X75: =IF(U75="SOLD",Q75,"") -> 0.1123 | Y75: =IF(U75="SOLD",TEXT(S75,"YYYY-MM"),"") -> 2025-07
A76: 76 | B76: 2024 | C76: Seat Leon ST | D76: Style | E76: 05/2022 | F76: 2.0 TDI 85 kW | G76: MT6 | H76: 68100 | I76: D | J76: 🇮🇹 | K76: 16011 | L76: 13600 | M76: 3128 | N76: 16728 | O76: 16728 | P76: 717 | Q76: 0.0448 | R76: 45715 | S76: 45903 | T76: 150 | U76: SOLD | V76: Seat Leon | W76: =IF(U76="SOLD",P76,"") -> 717 | X76: =IF(U76="SOLD",Q76,"") -> 0.0448 | Y76: =IF(U76="SOLD",TEXT(S76,"YYYY-MM"),"") -> 2025-09
A77: 77 | B77: 2024 | C77: Škoda Karoq | D77: Style | E77: 05/2021 | F77: 2.0 TDI 85 kW | G77: MT6 | H77: 199700 | I77: D | J77: 🇮🇹 | K77: 11429 | L77: 13252.03 | M77: 3047.97 | N77: 16300 | O77: 16300 | P77: 1823 | Q77: 0.1595 | R77: 45715 | S77: 45784 | T77: 30 | U77: SOLD | V77: Škoda Karoq | W77: =IF(U77="SOLD",P77,"") -> 1823 | X77: =IF(U77="SOLD",Q77,"") -> 0.1595 | Y77: =IF(U77="SOLD",TEXT(S77,"YYYY-MM"),"") -> 2025-05
A78: 78 | B78: 2024 | C78: Citroën Jumpy | D78: L2H1 | E78: 10/2017 | F78: 2.0 HDI 90 kW | G78: MT6 | H78: 195600 | I78: D | J78: 🇩🇪 | K78: 6952 | L78: 9227.64 | M78: 2122.37 | N78: 11350 | O78: 11350 | P78: 2276 | Q78: 0.3274 | R78: 45723 | S78: 45770 | T78: 5 | U78: SOLD | V78: Citroën Jumpy | W78: =IF(U78="SOLD",P78,"") -> 2276 | X78: =IF(U78="SOLD",Q78,"") -> 0.3274 | Y78: =IF(U78="SOLD",TEXT(S78,"YYYY-MM"),"") -> 2025-04
A79: 79 | B79: 2024 | C79: Škoda Octavia Combi | D79: Ambition | E79: 05/2017 | F79: 2.0 TDI 110 kW | G79: MT6 | H79: 150400 | I79: M | J79: 🇩🇪 | K79: 11856.99 | L79: 13272.01 | M79: 577.99 | N79: 13850 | O79: 13850 | P79: 1993 | Q79: 0.1681 | R79: 45735 | S79: 45773 | T79: 18 | U79: SOLD | V79: Škoda Octavia | W79: =IF(U79="SOLD",P79,"") -> 1993 | X79: =IF(U79="SOLD",Q79,"") -> 0.1681 | Y79: =IF(U79="SOLD",TEXT(S79,"YYYY-MM"),"") -> 2025-04
A80: 80 | B80: 2024 | C80: VW Golf Variant | D80: Comfortline | E80: 12/2014 | F80: 1.4 TSI 92 kW CZCA | G80: DSG7 | H80: 161500 | I80: M | J80: 🇩🇪 | K80: 9242 | L80: 8235.11 | M80: 64.89 | N80: 8300 | O80: 9500 | P80: 258 | Q80: 0.0279 | R80: 45756 | S80: 46005 | T80: 213 | U80: SOLD | V80: VW Golf | W80: =IF(U80="SOLD",P80,"") -> 258 | X80: =IF(U80="SOLD",Q80,"") -> 0.0279 | Y80: =IF(U80="SOLD",TEXT(S80,"YYYY-MM"),"") -> 2025-12
A81: 81 | B81: 2024 | C81: VW Touran | D81: Comfortline | E81: 10/2017 | F81: 2.0 TDI 110 kW DFGA | G81: MT6 | H81: 190800 | I81: M | J81: 🇫🇷 | K81: 12351.11 | L81: 13158.89 | M81: 441.11 | N81: 13600 | O81: 13950 | P81: 1599 | Q81: 0.1295 | R81: 45756 | S81: 45834 | T81: 42 | U81: SOLD | V81: VW Touran | W81: =IF(U81="SOLD",P81,"") -> 1599 | X81: =IF(U81="SOLD",Q81,"") -> 0.1295 | Y81: =IF(U81="SOLD",TEXT(S81,"YYYY-MM"),"") -> 2025-06
A82: 82 | B82: 2024 | C82: Škoda Octavia Combi | D82: Elegance | E82: 12/2013 | F82: 1.4 TSI 103 kW | G82: MT6 | H82: 194400 | I82: M | J82: 🇳🇱 | K82: 7971.17 | L82: 8658.95 | M82: 341.05 | N82: 9000 | O82: 9350 | P82: 1379 | Q82: 0.173 | R82: 45765 | S82: 45879 | T82: 87 | U82: SOLD | V82: Škoda Octavia | W82: =IF(U82="SOLD",P82,"") -> 1379 | X82: =IF(U82="SOLD",Q82,"") -> 0.173 | Y82: =IF(U82="SOLD",TEXT(S82,"YYYY-MM"),"") -> 2025-08
A83: 83 | B83: 2024 | C83: Seat Ateca | D83: Style | E83: 10/2016 | F83: 1.4 TSI 110 kW | G83: MT6 | H83: 147600 | I83: M | J83: 🇧🇪 | K83: 13198.16 | L83: 13926.84 | M83: 423.16 | N83: 14350 | O83: 14900 | P83: 1702 | Q83: 0.129 | R83: 45769 | S83: 45840 | T83: 27 | U83: SOLD | V83: Seat Ateca | W83: =IF(U83="SOLD",P83,"") -> 1702 | X83: =IF(U83="SOLD",Q83,"") -> 0.129 | Y83: =IF(U83="SOLD",TEXT(S83,"YYYY-MM"),"") -> 2025-07
A84: 84 | B84: 2024 | C84: VW Tiguan | D84: Trend & Fun | E84: 12/2013 | F84: 1.4 TSI 90 kW | G84: MT6 | H84: 161600 | I84: M | J84: 🇩🇪 | K84: 8134.43 | L84: 8738.57 | M84: 416.43 | N84: 9155 | O84: 9655 | P84: 1521 | Q84: 0.187 | R84: 45770 | S84: 45871 | T84: 73 | U84: SOLD | V84: VW Tiguan | W84: =IF(U84="SOLD",P84,"") -> 1521 | X84: =IF(U84="SOLD",Q84,"") -> 0.187 | Y84: =IF(U84="SOLD",TEXT(S84,"YYYY-MM"),"") -> 2025-08
... A87: 87 | B87: 2024 | C87: VW Passat Variant | D87: Comfortline | E87: 10/2016 | F87: 2.0 TDI 140 kW 4Motion | G87: DSG6 | H87: 181400 | I87: M | J87: 🇩🇪 | K87: 12668 | L87: 12077.56 | M87: 22.44 | N87: 12100 | O87: 14900 | P87: 2232 | Q87: 0.1762 | R87: 45782 | S87: 45793 | T87: 1 | U87: SOLD | V87: VW Passat | W87: =IF(U87="SOLD",P87,"") -> 2232 | X87: =IF(U87="SOLD",Q87,"") -> 0.1762 | Y87: =IF(U87="SOLD",TEXT(S87,"YYYY-MM"),"") -> 2025-05
A88: 88 | B88: 2024 | C88: Hyundai Tucson | D88: Style | E88: 03/2018 | F88: 1.7 CRDI 104 kW | G88: DCT7 | H88: 187000 | I88: M | J88: 🇫🇷 | K88: 11500 | O88: 12300 | P88: 800 | Q88: 0.0696 | R88: 45784 | S88: 45803 | T88: 11 | U88: SOLD | V88: Hyundai Tucson | W88: =IF(U88="SOLD",P88,"") -> 800 | X88: =IF(U88="SOLD",Q88,"") -> 0.0696 | Y88: =IF(U88="SOLD",TEXT(S88,"YYYY-MM"),"") -> 2025-05
A89: 89 | B89: 2024 | C89: Škoda Superb Combi | D89: Style | E89: 07/2016 | F89: 2.0 TDI 140 kW | G89: MT6 | H89: 106100 | I89: M | J89: 🇦🇹 | K89: 15334.24 | L89: 16215.76 | M89: 784.24 | N89: 17000 | O89: 17550 | P89: 2216 | Q89: 0.1445 | R89: 45793 | S89: 45890 | T89: 80 | U89: SOLD | V89: Škoda Superb | W89: =IF(U89="SOLD",P89,"") -> 2216 | X89: =IF(U89="SOLD",Q89,"") -> 0.1445 | Y89: =IF(U89="SOLD",TEXT(S89,"YYYY-MM"),"") -> 2025-08
A90: 90 | B90: 2024 | C90: Seat Ateca | D90: Xcellence | E90: 11/2016 | F90: 1.4 TIS 110 kW | G90: MT6 | H90: 150400 | I90: M | J90: 🇩🇪 | K90: 12492 | L90: 12033.8 | M90: 66.2 | N90: 12100 | O90: 15000 | P90: 2508 | Q90: 0.2008 | R90: 45794 | S90: 45852 | T90: 16 | U90: SOLD | V90: Seat Ateca | W90: =IF(U90="SOLD",P90,"") -> 2508 | X90: =IF(U90="SOLD",Q90,"") -> 0.2008 | Y90: =IF(U90="SOLD",TEXT(S90,"YYYY-MM"),"") -> 2025-07
A91: 91 | B91: 2024 | C91: Škoda Octavia Combi | D91: Style | E91: 08/2019 | F91: 2.0 TDI 110 kW | G91: MT6 | H91: 195400 | I91: M | J91: 🇦🇹 | K91: 11716.54 | L91: 12726.46 | M91: 423.54 | N91: 13150 | O91: 13400 | P91: 1683 | Q91: 0.1436 | R91: 45813 | S91: 45848 | T91: 16 | U91: SOLD | V91: Škoda Octavia | W91: =IF(U91="SOLD",P91,"") -> 1683 | X91: =IF(U91="SOLD",Q91,"") -> 0.1436 | Y91: =IF(U91="SOLD",TEXT(S91,"YYYY-MM"),"") -> 2025-07
A92: 92 | B92: 2024 | C92: VW Tiguan | D92: Trend & Fun | E92: 08/2012 | F92: 2.0 TDI 81 kW | G92: MT6 | H92: 197500 | I92: M | J92: 🇩🇪 | K92: 8214.9 | L92: 9200.1 | M92: 449.9 | N92: 9650 | O92: 10000 | P92: 1785 | Q92: 0.2173 | R92: 45813 | S92: 45847 | T92: 7 | U92: SOLD | V92: VW Tiguan | W92: =IF(U92="SOLD",P92,"") -> 1785 | X92: =IF(U92="SOLD",Q92,"") -> 0.2173 | Y92: =IF(U92="SOLD",TEXT(S92,"YYYY-MM"),"") -> 2025-07
A93: 93 | B93: 2024 | C93: Škoda Octavia Combi | D93: Ambition | E93: 07/2017 | F93: 2.0 TDI 110 kW | G93: DSG6 | H93: 180200 | I93: M | J93: 🇩🇪 | K93: 10565 | L93: 10345.97 | M93: 34.03 | N93: 10380 | O93: 11600 | P93: 1035 | Q93: 0.098 | R93: 45828 | S93: 46056 | T93: 174 | U93: SOLD | V93: Škoda Octavia | W93: =IF(U93="SOLD",P93,"") -> 1035 | X93: =IF(U93="SOLD",Q93,"") -> 0.098 | Y93: =IF(U93="SOLD",TEXT(S93,"YYYY-MM"),"") -> 2026-02
A94: 94 | B94: 2024 | C94: VW Passat Variant | D94: Alltrack | E94: 11/2021 | F94: 2.0 TDI 147 kW 4Motion | G94: DSG7 | H94: 48300 | I94: M | J94: 🇨🇿 | K94: 1966.74 | L94: 28446.26 | M94: 3.74 | N94: 28450 | O94: 31617 | P94: 1200 | Q94: 0.6101 | R94: 45841 | S94: 45847 | T94: 1 | U94: SOLD | V94: VW Passat | W94: =IF(U94="SOLD",P94,"") -> 1200 | X94: =IF(U94="SOLD",Q94,"") -> 0.6101 | Y94: =IF(U94="SOLD",TEXT(S94,"YYYY-MM"),"") -> 2025-07
A95: 95 | B95: 2024 | C95: Škoda Octavia Combi | D95: Ambition | E95: 07/2018 | F95: 1.5 TSI 110 kW | G95: DSG7 | H95: 126200 | I95: M | J95: 🇫🇷 | K95: 12050.48 | L95: 13761.52 | M95: 628.48 | N95: 14390 | O95: 14740 | P95: 2690 | Q95: 0.2232 | R95: 45853 | S95: 45876 | T95: 6 | U95: SOLD | V95: Škoda Octavia | W95: =IF(U95="SOLD",P95,"") -> 2690 | X95: =IF(U95="SOLD",Q95,"") -> 0.2232 | Y95: =IF(U95="SOLD",TEXT(S95,"YYYY-MM"),"") -> 2025-08
A96: 96 | B96: 2024 | C96: Maserati Ghibli S Q4 | D96: GranSport | E96: 10/2017 | F96: 3.0 V6 316 kW | G96: AT8 | H96: 118800 | I96: M | J96: 🇨🇿 | K96: 1451 | L96: 36000 | M96: 0 | N96: 36000 | O96: 38701 | P96: 1250 | Q96: 0.8615 | R96: 45841 | S96: 45847 | T96: 1 | U96: SOLD | V96: Maserati Ghibli | W96: =IF(U96="SOLD",P96,"") -> 1250 | X96: =IF(U96="SOLD",Q96,"") -> 0.8615 | Y96: =IF(U96="SOLD",TEXT(S96,"YYYY-MM"),"") -> 2025-07
A97: 97 | B97: 2024 | C97: VW Passat Variant | D97: Highline | E97: 12/2015 | F97: 2.0 TDI 140 kW 4Motion | G97: DSG6 | H97: 195000 | I97: M | J97: 🇩🇪 | K97: 12063.57 | L97: 12380.43 | M97: 319.57 | N97: 12700 | O97: 12700 | P97: 636 | Q97: 0.0527 | R97: 45859 | S97: 46033 | T97: 128 | U97: SOLD | V97: VW Passat | W97: =IF(U97="SOLD",P97,"") -> 636 | X97: =IF(U97="SOLD",Q97,"") -> 0.0527 | Y97: =IF(U97="SOLD",TEXT(S97,"YYYY-MM"),"") -> 2026-01
A98: 98 | B98: 2024 | C98: Škoda Octavia Combi | D98: Ambition | E98: 12/2013 | F98: 2.0 TDI 110 kW | G98: DSG6 | H98: 191300 | I98: M | J98: 🇩🇪 | K98: 7310 | L98: 7047.83 | M98: 52.17 | N98: 7100 | O98: 8100 | P98: 790 | Q98: 0.1081 | R98: 45870 | S98: 46040 | T98: 126 | U98: SOLD | V98: Škoda Octavia | W98: =IF(U98="SOLD",P98,"") -> 790 | X98: =IF(U98="SOLD",Q98,"") -> 0.1081 | Y98: =IF(U98="SOLD",TEXT(S98,"YYYY-MM"),"") -> 2026-01
A99: 99 | B99: 2024 | C99: Kia Sportage | D99: Gold | E99: 03/2023 | F99: 1.6 CRDi 100 kW | G99: DCT7 | H99: 63000 | I99: M | K99: 43 | O99: 900 | P99: 857 | Q99: 19.9302 | R99: 45884 | S99: 45919 | T99: 34 | U99: SOLD | V99: Kia Sportage | W99: =IF(U99="SOLD",P99,"") -> 857 | X99: =IF(U99="SOLD",Q99,"") -> 19.9302 | Y99: =IF(U99="SOLD",TEXT(S99,"YYYY-MM"),"") -> 2025-09
A100: 100 | B100: 2024 | C100: Škoda Karoq | D100: Style | E100: 12/2018 | F100: 1.5 TSI 110 kW | G100: DSG7 | H100: 177600 | I100: M | J100: 🇧🇪 | K100: 14692.85 | L100: 15490.15 | M100: 309.85 | N100: 15800 | O100: 15800 | P100: 1107 | Q100: 0.0753 | R100: 45884 | S100: 46036 | T100: 114 | U100: SOLD | V100: Škoda Karoq | W100: =IF(U100="SOLD",P100,"") -> 1107 | X100: =IF(U100="SOLD",Q100,"") -> 0.0753 | Y100: =IF(U100="SOLD",TEXT(S100,"YYYY-MM"),"") -> 2026-01
A101: 101 | B101: 2024 | C101: VW Passat Variant | D101: Comfortline | E101: 12/2015 | F101: 2.0 TDI | G101: MT6 | H101: 159000 | I101: M | J101: 🇩🇪 | K101: 10133 | L101: 11540 | M101: 460 | N101: 12000 | O101: 12500 | P101: 2367 | Q101: 0.2336 | R101: 45888 | S101: 46024 | T101: 93 | U101: SOLD | V101: VW Passat | W101: =IF(U101="SOLD",P101,"") -> 2367 | X101: =IF(U101="SOLD",Q101,"") -> 0.2336 | Y101: =IF(U101="SOLD",TEXT(S101,"YYYY-MM"),"") -> 2026-01
A102: 102 | B102: 2024 | C102: Seat Alhambra | D102: Style | E102: 04/2013 | F102: 2.0 TDI 103 kW | G102: MT6 | H102: 193600 | I102: M | J102: 🇩🇪 | K102: 10000 | L102: 10517 | M102: 483 | N102: 11000 | O102: 11350 | P102: 1350 | Q102: 0.135 | R102: 45897 | S102: 45950 | T102: 14 | U102: SOLD | V102: Seat Alhambra | W102: =IF(U102="SOLD",P102,"") -> 1350 | X102: =IF(U102="SOLD",Q102,"") -> 0.135 | Y102: =IF(U102="SOLD",TEXT(S102,"YYYY-MM"),"") -> 2025-10
A103: 103 | B103: 2024 | C103: Seat Arona | D103: FR | E103: 08/2018 | F103: 1.5 TSI 110 kW | G103: MT6 | H103: 151500 | I103: M | J103: 🇫🇷 | K103: 12131.59 | L103: 13456.41 | M103: 543.59 | N103: 14000 | O103: 14000 | P103: 1868 | Q103: 0.154 | R103: 45899 | S103: 45984 | T103: 48 | U103: SOLD | V103: Seat Arona | W103: =IF(U103="SOLD",P103,"") -> 1868 | X103: =IF(U103="SOLD",Q103,"") -> 0.154 | Y103: =IF(U103="SOLD",TEXT(S103,"YYYY-MM"),"") -> 2025-11
A104: 104 | B104: 2024 | C104: VW Tiguan | D104: Sport & Style | E104: 12/2013 | F104: 2.0 TDI 103 kW 4Motion | G104: MT6 | H104: 123200 | I104: M | J104: 🇩🇪 | K104: 10480 | L104: 10252.69 | M104: 47.31 | N104: 10300 | O104: 12000 | P104: 1520 | Q104: 0.145 | R104: 45902 | S104: 46079 | T104: 148 | U104: SOLD | V104: VW Tiguan | W104: =IF(U104="SOLD",P104,"") -> 1520 | X104: =IF(U104="SOLD",Q104,"") -> 0.145 | Y104: =IF(U104="SOLD",TEXT(S104,"YYYY-MM"),"") -> 2026-02
A105: 105 | B105: 2024 | C105: VW Tiguan | D105: Trend & Fun | E105: 04/2013 | F105: 2.0 TDI 81 kW | G105: MT6 | H105: 83600 | I105: M | J105: 🇩🇪 | K105: 10187.07 | L105: 10786.93 | M105: 203.07 | N105: 10990 | O105: 10990 | P105: 803 | Q105: 0.0788 | R105: 45902 | S105: 46069 | T105: 132 | U105: SOLD | V105: VW Tiguan | W105: =IF(U105="SOLD",P105,"") -> 803 | X105: =IF(U105="SOLD",Q105,"") -> 0.0788 | Y105: =IF(U105="SOLD",TEXT(S105,"YYYY-MM"),"") -> 2026-02
A106: 106 | B106: 2024 | C106: Škoda Octavia Combi | D106: Ambition | E106: 02/2018 | F106: 1.4 TSI 110 kW | G106: MT6 | H106: 180300 | I106: D | J106: 🇳🇱 | K106: 8262 | L106: 8699.19 | M106: 2000.82 | N106: 10700 | O106: 10700 | P106: 437 | Q106: 0.0529 | R106: 45906 | S106: 46087 | T106: 123 | U106: SOLD | V106: Škoda Octavia | W106: =IF(U106="SOLD",P106,"") -> 437 | X106: =IF(U106="SOLD",Q106,"") -> 0.0529 | Y106: =IF(U106="SOLD",TEXT(S106,"YYYY-MM"),"") -> 2026-03
A107: 107 | B107: 2024 | C107: VW Touran | D107: Comfortline | E107: 10/2017 | F107: 2.0 TDI 110 kW | G107: DSG6 | H107: 191100 | I107: M | J107: 🇫🇷 | K107: 11313.93 | L107: 12004.07 | M107: 345.93 | N107: 12350 | O107: 12350 | P107: 1036 | Q107: 0.0916 | R107: 45906 | S107: 45972 | T107: 4 | U107: SOLD | V107: VW Touran | W107: =IF(U107="SOLD",P107,"") -> 1036 | X107: =IF(U107="SOLD",Q107,"") -> 0.0916 | Y107: =IF(U107="SOLD",TEXT(S107,"YYYY-MM"),"") -> 2025-11
A108: 108 | B108: 2024 | C108: Seat Ateca | D108: Xcellence | E108: 01/2017 | F108: 1.4 TSI 110 kW | G108: MT6 | H108: 173750 | I108: M | J108: 🇩🇪 | K108: 12207.44 | L108: 14179.56 | M108: 620.44 | N108: 14800 | O108: 14800 | P108: 2593 | Q108: 0.2124 | R108: 45919 | S108: 45976 | T108: 35 | U108: SOLD | V108: Seat Ateca | W108: =IF(U108="SOLD",P108,"") -> 2593 | X108: =IF(U108="SOLD",Q108,"") -> 0.2124 | Y108: =IF(U108="SOLD",TEXT(S108,"YYYY-MM"),"") -> 2025-11
A109: 109 | B109: 2024 | C109: VW Tiguan | D109: Sport & Style | E109: 09/2014 | F109: 2.0 TDI 130 kW 4Motion | G109: MT6 | H109: 160600 | I109: M | J109: 🇩🇪 | K109: 10966.63 | L109: 13006.37 | M109: 643.63 | N109: 13650 | O109: 13650 | P109: 2683 | Q109: 0.2447 | R109: 45925 | S109: 45973 | T109: 9 | U109: SOLD | V109: VW Tiguan | W109: =IF(U109="SOLD",P109,"") -> 2683 | X109: =IF(U109="SOLD",Q109,"") -> 0.2447 | Y109: =IF(U109="SOLD",TEXT(S109,"YYYY-MM"),"") -> 2025-11
A110: 110 | B110: 2024 | C110: VW Golf Variant | D110: Comfortline | E110: 03/2017 | F110: 2.0 TDI 110 kW | G110: MT6 | H110: 184000 | I110: M | J110: 🇩🇪 | K110: 10394.47 | L110: 12391.53 | M110: 608.47 | N110: 13000 | O110: 13000 | P110: 2606 | Q110: 0.2507 | R110: 45930 | S110: 45983 | T110: 2 | U110: SOLD | V110: VW Golf | W110: =IF(U110="SOLD",P110,"") -> 2606 | X110: =IF(U110="SOLD",Q110,"") -> 0.2507 | Y110: =IF(U110="SOLD",TEXT(S110,"YYYY-MM"),"") -> 2025-11
A111: 111 | B111: 2024 | C111: Opel Insignia Grand Sport | D111: OPC line | E111: 12/2017 | F111: 2.0 CDTI 125 kW | G111: AT8 | H111: 208600 | I111: M | J111: 🇸🇰 | K111: 8540 | N111: 10495 | O111: 10495 | P111: 1955 | Q111: 0.2289 | R111: 45953 | S111: 45973 | T111: 9 | U111: SOLD | V111: Opel Insignia | W111: =IF(U111="SOLD",P111,"") -> 1955 | X111: =IF(U111="SOLD",Q111,"") -> 0.2289 | Y111: =IF(U111="SOLD",TEXT(S111,"YYYY-MM"),"") -> 2025-11
A112: 112 | B112: 2024 | C112: Nissan Navara Double | D112: N-Guard | E112: 04/2022 | F112: 2.3 dCi 140 kW | G112: AT7 | H112: 123000 | I112: M | J112: 🇭🇺 | K112: 650 | O112: 1650 | P112: 1000 | Q112: 1.5385 | R112: 45958 | S112: 45961 | T112: 3 | U112: SOLD | V112: Nissan Navara | W112: =IF(U112="SOLD",P112,"") -> 1000 | X112: =IF(U112="SOLD",Q112,"") -> 1.5385 | Y112: =IF(U112="SOLD",TEXT(S112,"YYYY-MM"),"") -> 2025-10
A113: 113 | B113: 2024 | C113: VW Tayron | D113: Highline R-line | E113: 12/2025 | F113: 2.0 TDI 142 kW 4Motion | G113: DSG7 | H113: 650 | I113: D | J113: 🇩🇪 | K113: 984.12 | L113: 1500 | M113: 345 | N113: 1845 | O113: 1845 | P113: 516 | Q113: 0.5243 | R113: 45958 | S113: 46010 | T113: 3 | U113: SOLD | V113: VW Tayron | W113: =IF(U113="SOLD",P113,"") -> 516 | X113: =IF(U113="SOLD",Q113,"") -> 0.5243 | Y113: =IF(U113="SOLD",TEXT(S113,"YYYY-MM"),"") -> 2025-12
A114: 114 | B114: 2024 | C114: BMW 420d Gran Coupé | D114: M Sport | E114: 09/2017 | F114: 2.0d 140 kW | G114: AT8 | H114: 208000 | I114: M | J114: 🇸🇰 | K114: 50 | O114: 1000 | P114: 950 | Q114: 19 | R114: 45976 | S114: 46085 | T114: 104 | U114: SOLD | V114: BMW 420d | W114: =IF(U114="SOLD",P114,"") -> 950 | X114: =IF(U114="SOLD",Q114,"") -> 19 | Y114: =IF(U114="SOLD",TEXT(S114,"YYYY-MM"),"") -> 2026-03
A115: 115 | B115: 2024 | C115: Seat Ateca | D115: Style | E115: 11/2017 | F115: 1.4 TSI 110 kW | G115: MT6 | H115: 202900 | I115: M | J115: 🇧🇪 | K115: 7972.84 | L115: 10000 | M115: 2300.01 | N115: 12300 | O115: 12300 | P115: 2027 | Q115: 0.2542 | R115: 45986 | S115: 46084 | T115: 51 | U115: SOLD | V115: Seat Ateca | W115: =IF(U115="SOLD",P115,"") -> 2027 | X115: =IF(U115="SOLD",Q115,"") -> 0.2542 | Y115: =IF(U115="SOLD",TEXT(S115,"YYYY-MM"),"") -> 2026-03
A116: 116 | B116: 2024 | C116: VW Golf Variant | D116: Highline | E116: 05/2017 | F116: 2.0 TDI 110 kW | G116: MT6 | H116: 151000 | I116: D | J116: 🇩🇪 | K116: 8387 | L116: 0 | M116: 0 | N116: 0 | R116: 45987 | T116: 0 | U116: STOCK | V116: VW Golf | W116: =IF(U116="SOLD",P116,"") | X116: =IF(U116="SOLD",Q116,"") | Y116: =IF(U116="SOLD",TEXT(S116,"YYYY-MM"),"")
A117: 117 | B117: 2024 | C117: Alfa Romeo Stelvio | D117: Super | E117: 10/2017 | F117: 2.2d 110 kW | G117: AT8 | H117: 169200 | I117: M | J117: 🇮🇹 | K117: 15515 | L117: 11675.88 | M117: 24.12 | N117: 11700 | R117: 45987 | T117: 0 | U117: STOCK | V117: Alfa Romeo Stelvio | W117: =IF(U117="SOLD",P117,"") | X117: =IF(U117="SOLD",Q117,"") | Y117: =IF(U117="SOLD",TEXT(S117,"YYYY-MM"),"")
A118: 118 | B118: 2024 | C118: VW ID.3 | D118: 1st Pro | E118: 12/2020 | F118: 58 kWh 150 kW | G118: AT1 | H118: 150800 | I118: D | J118: 🇳🇱 | K118: 9599 | L118: 9593.5 | M118: 2206.51 | N118: 11800 | O118: 13800 | P118: 1994 | Q118: 0.2077 | R118: 46031 | S118: 46094 | T118: 33 | U118: SOLD | V118: VW ID.3 | W118: =IF(U118="SOLD",P118,"") -> 1994 | X118: =IF(U118="SOLD",Q118,"") -> 0.2077 | Y118: =IF(U118="SOLD",TEXT(S118,"YYYY-MM"),"") -> 2026-03
A119: 119 | B119: 2024 | C119: Seat Ateca | D119: Style | E119: 04/2017 | F119: 1.4 TSI 110 kW | G119: MT6 | H119: 199700 | I119: M | J119: 🇫🇷 | K119: 10074 | L119: 11623.02 | M119: 376.98 | N119: 12000 | O119: 12000 | P119: 1549 | Q119: 0.1538 | R119: 46038 | S119: 46172 | T119: 75 | U119: SOLD | V119: Seat Ateca | W119: =IF(U119="SOLD",P119,"") -> 1549 | X119: =IF(U119="SOLD",Q119,"") -> 0.1538 | Y119: =IF(U119="SOLD",TEXT(S119,"YYYY-MM"),"") -> 2026-05
A120: 120 | B120: 2024 | C120: Seat Ateca | D120: Style | E120: 05/2017 | F120: 1.6 TDI 85 kW | G120: MT6 | H120: 194000 | I120: M | J120: 🇮🇹 | K120: 9789 | L120: 11387.41 | M120: 612.59 | N120: 12000 | O120: 12000 | P120: 1598 | Q120: 0.1632 | R120: 46041 | S120: 46119 | T120: 52 | U120: SOLD | V120: Seat Ateca | W120: =IF(U120="SOLD",P120,"") -> 1598 | X120: =IF(U120="SOLD",Q120,"") -> 0.1632 | Y120: =IF(U120="SOLD",TEXT(S120,"YYYY-MM"),"") -> 2026-04
A121: 121 | B121: 2024 | C121: BMW 525d Touring | E121: 11/2005 | F121: 2.5d 130 kW | G121: AT6 | H121: 425000 | I121: M | J121: 🇸🇰 | K121: 2680 | O121: 3000 | P121: 320 | Q121: 0.1194 | R121: 46013 | S121: 46078 | T121: 36 | U121: SOLD | V121: BMW 525d | W121: =IF(U121="SOLD",P121,"") -> 320 | X121: =IF(U121="SOLD",Q121,"") -> 0.1194 | Y121: =IF(U121="SOLD",TEXT(S121,"YYYY-MM"),"") -> 2026-02
A122: 122 | B122: 2024 | C122: VW Tiguan | D122: Sport & Style | E122: 03/2013 | F122: 2.0 TDI 130 kW 4Motion | G122: MT6 | H122: 169000 | I122: M | J122: 🇩🇪 | K122: 10391 | L122: 0 | M122: 0 | N122: 0 | R122: 46052 | T122: 0 | U122: STOCK | V122: VW Tiguan | W122: =IF(U122="SOLD",P122,"") | X122: =IF(U122="SOLD",Q122,"") | Y122: =IF(U122="SOLD",TEXT(S122,"YYYY-MM"),"")
A123: 123 | B123: 2024 | C123: VW ID.3 | D123: Pro | E123: 12/2020 | F123: 58 kWh 150 kW | G123: AT1 | H123: 144750 | I123: D | J123: 🇳🇱 | K123: 9683 | L123: 11788.62 | M123: 2711.4 | N123: 14500 | O123: 14500 | P123: 2106 | Q123: 0.2175 | R123: 46053 | S123: 46093 | T123: 0 | U123: SOLD | V123: VW ID.3 | W123: =IF(U123="SOLD",P123,"") -> 2106 | X123: =IF(U123="SOLD",Q123,"") -> 0.2175 | Y123: =IF(U123="SOLD",TEXT(S123,"YYYY-MM"),"") -> 2026-03
A124: 124 | B124: 2024 | C124: VW ID.4 | D124: Pro | E124: 11/2021 | F124: 77 kWh 150 kW | G124: AT1 | H124: 190400 | I124: D | J124: 🇳🇱 | K124: 11954 | L124: 11544.72 | M124: 2655.3 | N124: 14200 | O124: 16000 | P124: 1391 | Q124: 0.1164 | R124: 46060 | S124: 46083 | T124: 3 | U124: SOLD | V124: VW ID.4 | W124: =IF(U124="SOLD",P124,"") -> 1391 | X124: =IF(U124="SOLD",Q124,"") -> 0.1164 | Y124: =IF(U124="SOLD",TEXT(S124,"YYYY-MM"),"") -> 2026-03
...
